Workbook

Sheet Sheet2
A1: Sec | B1: Row Labels | C1: Apr-2023 | D1: May-2023 | E1: Jun-2023 | F1: Jul-2023 | G1: Aug-2023 | H1: Sep-2023 | I1: Oct-2023 | J1: Nov-2023 | K1: Dec-2023 | L1: May-2024 | M1: Jun-2024 | N1: Jul-2024 | O1: Sep-2024 | P1: Aug-2024 | Q1: Oct-2024 | R1: Nov-2024 | S1: Dec-2024 | T1: Jan-2025 | U1: Feb-2025 | V1: Mar-2025 | W1: Apr-2025 | X1: May-2025 | Y1: Jun-2025 | Z1: Jul-2025 | AA1: Aug-2025 | AB1: Sep-2025 | AC1: Nov-2025 | AD1: Oct-2025 | AE1: Dec-2025 | AF1: Jan-2026 | AG1: Feb-2026 | AH1: Mar-2026 | AI1: Apr-2026 | AJ1: May-2026
A2: Rent | B2: Abohar 2337
A3: Rent | B3: ABOHAR 3196 | AC3: 39000 | AE3: 45000 | AF3: 45000 | AG3: 45000 | AH3: 45000 | AI3: 90000 | AJ3: 90000
A4: Rent | B4: AKBARPUR 3300 | AI4: 96428 | AJ4: 137754
A5: Rent | B5: AKOLA 2657 | C5: 74592 | D5: 74592 | E5: 74592 | F5: 74592 | G5: 74592 | H5: 74592 | I5: 74592 | J5: 74592 | K5: 74592 | L5: 74592 | M5: 74592 | N5: 74592 | O5: 74592 | P5: 74592 | Q5: 74592
A6: Rent | B6: Akola 1519 | AI6: 3658.9 | AJ6: 109767
A7: Rent | B7: Akola 1728
A8: Rent | B8: Akola 2353 | C8: 104583 | D8: 104583 | E8: 104583 | F8: 104583 | G8: 104583 | H8: 104583 | I8: 104583 | J8: 104583 | K8: 104583 | L8: 308892 | M8: 308892 | N8: 308892 | O8: 204309 | P8: 204309 | Q8: 102879 | R8: 102879 | S8: 102879 | T8: 102879 | U8: 211194 | V8: 211194 | W8: 211194 | X8: 211194 | Y8: 211194 | Z8: 211194 | AA8: 211194 | AB8: 108315 | AC8: 108315 | AD8: 108315 | AE8: 108315 | AF8: 102879 | AG8: 102879 | AH8: 102879 | AI8: 102879 | AJ8: 102879
A9: Rent | B9: Akola 2354
A10: Rent | B10: Akola 2362
A11: Rent | B11: Akola 2373
A12: Rent | B12: AKOLA 2516 | AI12: 65859 | AJ12: 109767
A13: Rent | B13: AKOLA 2528
A14: Rent | B14: AKOLA 2894 | L14: 170856 | M14: 170856 | N14: 170856 | P14: 67889
A15: Rent | B15: AKOLA 2908 | L15: 60288 | M15: 60288 | N15: 60288 | O15: 60288 | P15: 60288 | Q15: 60288
A16: Rent | B16: AKOLA 3069 | V16: 92872 | W16: 92872 | X16: 92872 | Y16: 92872 | Z16: 92872 | AA16: 92872 | AB16: 92872 | AC16: 92872 | AD16: 92872 | AE16: 92872 | AF16: 92872 | AG16: 92872 | AH16: 92872 | AI16: 228756 | AJ16: 228756
A17: Rent | B17: AKOLA 3222
A18: Rent | B18: AKOLA 3279 | AI18: 410350 | AJ18: 410350
A19: Rent | B19: AKOLA CON 3283 | AI19: 142013 | AJ19: 142013
A20: Rent | B20: ALWAR 3005 | Q20: 29661 | R20: 29661 | S20: 29661
A21: Rent | B21: ALWAR 3006 | O21: 12896 | Q21: 96720 | R21: 96720 | S21: 96720
A22: Rent | B22: AMETHI 2823 | J22: 20167 | K22: 55000
A23: Rent | B23: AMETHI 3115 | W23: 112700 | X23: 120750 | Y23: 120750 | Z23: 120750 | AA23: 120750 | AB23: 120750 | AC23: 120750 | AD23: 120750 | AE23: 120750 | AF23: 120750 | AG23: 120750
A24: Rent | B24: AMETHI 3293 | AI24: 136000 | AJ24: 136000
A25: Rent | B25: AMETHI 3351 | AJ25: 34066
A26: Rent | B26: AMRAVATI 3282 | AI26: 139400 | AJ26: 139400
A27: Rent | B27: AMRITSAR 2625 | C27: 65450
A28: Rent | B28: ANANTHASAGAR 2454
A29: Rent | B29: ANANTHASAGAR 2455
A30: Rent | B30: ANNUR 3076 | V30: 119786 | W30: 195440 | X30: 195440 | Y30: 195440 | Z30: 195440 | AA30: 195440 | AB30: 195440 | AC30: 195440 | AD30: 195440 | AE30: 195440 | AF30: 195440 | AG30: 27920
A31: Rent | B31: ANTAWADI 2549
A32: Rent | B32: ARUPPUKOTTAI 3053 | S32: 209032 | T32: 240000 | U32: 240000 | V32: 240000 | W32: -176000
A33: Rent | B33: ARUPPUKOTTAI 3210 | AE33: 373787 | AF33: 429163 | AG33: 429163 | AH33: 429163 | AI33: 429163 | AJ33: 429163
A34: Rent | B34: ARUPPUKOTTAI 3211 | AE34: 193390 | AF34: 285480 | AG34: 285480 | AH34: 285480 | AI34: 285480 | AJ34: 285480
A35: Rent | B35: ARUPPUKOTTAI 3218 | AE35: 602183 | AF35: 933383 | AG35: 933383 | AH35: 933383 | AI35: 933383 | AJ35: 933383
A36: Rent | B36: ARUPPUKOTTAI 3221 | AE36: 235759 | AF36: 487236 | AG36: 487236 | AH36: 487236 | AI36: 487236 | AJ36: 487236
A37: Rent | B37: Ashok Nagar 453 | C37: 197030 | D37: 197030 | E37: 197030 | F37: 197030 | G37: 197030 | H37: 197030 | I37: 197030 | J37: 197030 | K37: 197030 | L37: 197030 | M37: 197030 | N37: 197030 | O37: 197030 | P37: 197030 | Q37: 197030 | R37: 197030 | S37: 197030 | T37: 197030 | U37: 197030 | V37: 197030 | W37: 197030 | X37: 197030 | Y37: 197030 | Z37: 197030 | AA37: 197030 | AB37: 197030 | AC37: 197030 | AD37: 197030 | AE37: 197030 | AF37: 197030 | AG37: 197030 | AH37: 197030 | AI37: 197030 | AJ37: 197030
A38: Rent | B38: ASHOKNAGAR 2540 | C38: 227811 | D38: 227811 | E38: 227811 | F38: 227811 | G38: 227811 | H38: 227811 | I38: 227811 | J38: 78635 | K38: 78635 | L38: 157270 | M38: 78635 | N38: 78635 | O38: 78635 | P38: 78635 | Q38: 78635 | R38: 78635 | S38: 78635 | T38: 78635 | U38: 78635 | V38: 78635 | W38: 78635 | X38: 78635 | Y38: 78635 | Z38: 78635 | AA38: 78635 | AB38: 78635 | AC38: 78635 | AD38: 78635 | AE38: 66640 | AF38: 66640 | AG38: 66640 | AH38: 66640 | AI38: 66640 | AJ38: 66640
A39: Rent | B39: ASHOKNAGAR CON 3171 | Y39: 135878 | Z39: 135878 | AA39: 135878 | AB39: 135878 | AC39: 135878 | AD39: 135878 | AE39: 135878 | AF39: 135878 | AG39: 135878 | AH39: 135878 | AI39: 135878 | AJ39: 135878
A40: Rent | B40: ATMAKUR 2964 | L40: 158895 | M40: 158895 | N40: 158895 | P40: 158895
A41: Rent | B41: ATRAULI 3160 | X41: 46087 | Y41: 75195 | Z41: 75195 | AA41: 75195 | AB41: 75195 | AC41: 75195 | AD41: 75195 | AE41: 75195 | AF41: 75195 | AG41: 75195 | AH41: 75195 | AI41: 75195 | AJ41: 75195
A42: Rent | B42: BAHRAICH 2601
A43: Rent | B43: BALABHADRAPURAM 3220 | AE43: 7875 | AF43: 100351 | AG43: 110207 | AH43: 110207 | AI43: 110207 | AJ43: 110207
A44: Rent | B44: BANGALORE 2785 | F44: 14687 | G44: 65043 | H44: 65043 | I44: 65043 | J44: 65043 | K44: 65043 | L44: 65043 | M44: 65043 | N44: 65043 | O44: 41193.5 | P44: 65043
A45: Rent | B45: BANGALORE 2786 | F45: 1935.4839
A46: Rent | B46: BARABANKI 2667 | C46: 140265 | D46: 140265 | E46: 140265 | F46: 140265 | G46: 140265 | H46: 140265 | I46: 140265 | J46: 140265 | K46: 140265 | L46: 149616 | M46: 149616 | N46: 149616 | O46: 149616 | P46: 149616 | Q46: 149616 | R46: 149616 | S46: 149616
A47: Rent | B47: BARABANKI 2880 | L47: 155818 | M47: 155818 | N47: 155818 | O47: 155818 | P47: 155818 | Q47: 155818 | R47: 155818 | S47: 155818 | T47: 155818
A48: Rent | B48: BARABANKI 3102 | W48: 166448 | X48: 166448 | Y48: 166448 | Z48: 166448 | AA48: 166448 | AB48: 166448 | AC48: 166448 | AD48: 166448 | AE48: 166448 | AF48: 107386
A49: Rent | B49: BARABANKI 3136 | W49: 92452 | X49: 173348 | Y49: 173348 | Z49: 173348 | AA49: 173348 | AB49: 173348 | AC49: 86674 | AD49: 173348
A50: Rent | B50: BARAN 3073 | W50: 48978 | X50: 48978 | Y50: 48978 | Z50: 48978 | AA50: 48978 | AB50: 48978 | AC50: 48978 | AD50: 48978 | AE50: 48978 | AF50: 48978 | AG50: 48978 | AI50: 48978 | AJ50: 48978
A51: Rent | B51: Barauni 2435
A52: Rent | B52: Barauni 2445
A53: Rent | B53: Barauni 2446
A54: Rent | B54: BARAUNI 2591
A55: Rent | B55: BARAUNI 2592
A56: Rent | B56: BARAUNI 2593
A57: Rent | B57: BASMATH 2867 | L57: 97945 | M57: 67473 | N57: 67473 | P57: 67473
A58: Rent | B58: BASTI 3120 | W58: 168000 | X58: 168000 | Y58: 168000 | Z58: 168000 | AA58: 168000 | AB58: 168000 | AC58: 168000 | AD58: 168000 | AE58: 168000 | AF58: 168000 | AG58: 168000
A59: Rent | B59: Beed 2293
A60: Rent | B60: BEED 2783 | E60: 18000 | F60: 180000 | G60: 180000 | H60: 180000 | L60: 210000 | M60: 210000 | N60: 210000 | P60: 189677
A61: Rent | B61: BEED 2784 | E61: 11862 | F61: 118620 | G61: 118620 | H61: 106758
A62: Rent | B62: BEED 2856 | L62: 140000 | M62: 140000 | N62: 140000 | P62: 135484
A63: Rent | B63: BEED 2866 | L63: 49166 | M63: 26222
A64: Rent | B64: BEGUSARAI 2919 | L64: 231000 | M64: 231000 | N64: 231000 | O64: 231000 | P64: 231000 | Q64: 231000 | R64: 231000 | S64: 231000 | T64: 231000
A65: Rent | B65: BEGUSARAI 2673 | C65: 396110 | D65: 396110 | E65: 396110 | F65: 396110 | G65: 396110 | H65: 396110 | I65: 396110 | J65: 396110 | K65: 396110
A66: Rent | B66: BEGUSARAI 2674 | C66: 145200 | D66: 145200 | E66: 145200 | F66: 145200 | G66: 145200 | H66: 145200 | I66: 145200 | J66: 145200 | K66: 145200
A67: Rent | B67: BEGUSARAI 2704 | C67: 76285 | D67: 76285 | E67: 76285 | F67: 76285 | G67: 76285 | H67: 76285 | I67: 76285 | J67: 76285 | K67: 76285 | L67: 83220 | M67: 83220 | N67: 83220 | O67: 83220 | P67: 83220 | Q67: 83220 | R67: 83220 | S67: 83220 | T67: 83220 | U67: 83220 | AI67: 3005.1667 | AJ67: 90155
A68: Rent | B68: BEGUSARAI 2705 | C68: 324000 | D68: 324000 | E68: 324000 | F68: 324000 | G68: 324000 | H68: 324000 | I68: 324000 | J68: 324000 | K68: 324000 | L68: 324000 | M68: 324000 | N68: 324000 | O68: 324000 | P68: 324000 | Q68: 324000 | R68: 324000 | S68: 324000 | T68: 324000 | U68: 138857
A69: Rent | B69: BEGUSARAI 2706 | C69: 107261 | D69: 107261 | E69: 107261 | F69: 107261 | G69: 107261 | H69: 107261 | I69: 107261 | J69: 107261 | K69: 107261
A70: Rent | B70: BEGUSARAI 2707 | C70: 206954 | D70: 206954 | E70: 206954 | F70: 206954 | G70: 206954 | H70: 206954 | I70: 206954 | J70: 206954 | K70: 206954
A71: Rent | B71: BEGUSARAI 2712 | D71: 202400 | E71: 202400 | F71: 202400 | G71: 202400 | H71: 202400 | I71: 202400 | J71: 202400 | K71: 202400
A72: Rent | B72: BEGUSARAI 2929 | L72: 107261 | M72: 107261 | N72: 107261 | O72: 107261 | P72: 107261 | Q72: 107261 | R72: 107261 | S72: 107261 | T72: 107261 | U72: 107261 | V72: 107261
A73: Rent | B73: BEGUSARAI 2930 | L73: 208560 | M73: 208560 | N73: 208560 | O73: 208560 | P73: 208560 | Q73: 208560 | R73: 208560 | S73: 208560 | T73: 208560
A74: Rent | B74: BEGUSARAI 2931 | L74: 392230 | M74: 392230 | N74: 392230 | O74: 392230 | P74: 392230 | Q74: 392230 | R74: 392230 | S74: 392230 | T74: 392230 | U74: 240430 | V74: 240430 | AI74: 5575.2 | AJ74: 167256
A75: Rent | B75: BEGUSARAI 2933 | L75: 191208 | M75: 191208 | N75: 191208 | O75: 191208 | P75: 191208 | Q75: 191208 | R75: 191208 | S75: 191208 | T75: 191208 | AJ75: 127472
A76: Rent | B76: BEGUSARAI 2934 | L76: 471576 | M76: 471576 | N76: 471576 | O76: 471576 | P76: 471576 | Q76: 471576 | R76: 471576 | S76: 471576 | T76: 177456 | U76: 177456
A77: Rent | B77: BEGUSARAI 2946 | L77: 102456 | M77: 102456 | N77: 102456 | O77: 102456 | P77: 102456 | Q77: 102456 | R77: 102456 | S77: 102456 | T77: 102456 | U77: 102456
A78: Rent | B78: BEGUSARAI 2985 | L78: 79143 | M78: 153340 | N78: 153340 | O78: 153340 | P78: 153340 | Q78: 153340 | R78: -66447.333
A79: Rent | B79: BEGUSARAI 3109 | W79: 219440 | X79: 253200 | Y79: 253200 | Z79: 253200 | AA79: 253200 | AB79: 253200 | AC79: 253200 | AD79: 253200 | AE79: 253200 | AF79: 253200 | AG79: 253200
A80: Rent | B80: BEGUSARAI 3158 | X80: 351000 | Y80: 351000 | Z80: 351000 | AA80: 351000 | AB80: 351000 | AC80: 351000 | AD80: 351000 | AE80: 351000 | AF80: 351000
A81: Rent | B81: BEGUSARAI 3185 | AB81: 35460 | AC81: 118200 | AD81: 118200 | AE81: 118200 | AF81: 118200 | AG81: 118200 | AH81: 118200 | AI81: 118200 | AJ81: 118200
A82: Rent | B82: BEGUSARAI 3323 | AI82: 87610.1 | AJ82: 223938
A83: Rent | B83: BEGUSARAI 3324 | AI83: 5115 | AJ83: 153450
A84: Rent | B84: Bharatpur 1741 | C84: 98307 | D84: 103220 | E84: 103220 | F84: 103220 | G84: 103220 | H84: 103220 | I84: 103220 | J84: 104203 | K84: 104203 | L84: 104203 | M84: 104203 | N84: 104203 | O84: 104203 | P84: 104203 | Q84: 104203 | R84: 104203 | S84: 104203 | T84: 104203 | U84: 104203 | V84: 104203 | W84: 104203 | X84: 104203 | Y84: 104203 | Z84: 104203 | AA84: 104203 | AB84: 104203 | AC84: 104203 | AD84: 104203 | AE84: 104203 | AF84: 104203 | AG84: 104203 | AH84: 104203 | AI84: 104203 | AJ84: 104203
A85: Rent | B85: Bharatpur 2402
A86: Rent | B86: BHARATPUR 2634 | C86: 153902
A87: Rent | B87: BHARATPUR 2638 | C87: 70500 | D87: 70500 | E87: 70500 | F87: 70500
A88: Rent | B88: BHARATPUR 2643 | C88: 222554 | D88: 222554 | E88: 222554
A89: Rent | B89: BHARATPUR 2789 | Q89: 182200 | R89: 182200 | S89: 182200 | T89: 182200 | U89: 182200 | V89: 182200 | W89: 182200 | X89: 182200 | Y89: 182200 | Z89: 182200 | AA89: 182200 | AB89: 182200 | AC89: 182200 | AD89: 182200 | AE89: 182200 | AF89: 182200 | AG89: 182200 | AH89: 182200 | AI89: 182200 | AJ89: 182200
A90: Rent | B90: BHARATPUR 2790 | I90: 88725 | J90: 88725 | K90: 88725 | L90: 88725 | M90: 88725 | N90: 88725 | O90: 88725 | P90: 88725 | Q90: 88725 | R90: 88725 | S90: 88725 | T90: 88725 | U90: 88725 | V90: 88725 | W90: 88725 | X90: 88725 | Y90: 88725 | Z90: 88725 | AA90: 88725 | AB90: 88725 | AD90: 88725
A91: Rent | B91: Bharatpur 400
A92: Rent | B92: BHAWANIPATNA 2502
A93: Rent | B93: BHOJPUR 3217 | AE93: 45480 | AF93: 93993 | AG93: 53710
A94: Rent | B94: Bihta 2079
A95: Rent | B95: BODWAD 3020 | R95: 90594 | S95: 90594 | T95: 90594 | U95: 90594 | V95: 90594 | AI95: 2253.3333 | AJ95: 67600
A96: Rent | B96: BODWAD 3021 | R96: 42329 | S96: 42329 | T96: 42329 | U96: 42329 | V96: 42329 | W96: 42329 | X96: 42329 | Y96: 42329 | Z96: 13655 | AJ96: 40222.097
A97: Rent | B97: BODWAD 3039 | R97: 24500 | S97: 35000 | T97: 35000 | U97: 35000 | V97: 35000 | W97: 35000 | X97: 58710 | Y97: 70000 | Z97: 35000
A98: Rent | B98: BODWAD 3125 | W98: 36400 | X98: 109200 | Y98: 109200 | Z98: 70452
A99: Rent | B99: BODWAD 3199 | AC99: 58240 | AE99: 109200 | AF99: 109200 | AG99: 109200 | AH99: 109200 | AI99: 109200 | AJ99: 109200
A100: Rent | B100: BODWAD 3333 | AI100: 2360 | AJ100: 70800
...

Sheet Sheet4
A3: Row Labels | B3: Sum of Apr-2023 | C3: Sum of May-2023 | D3: Sum of Jun-2023 | E3: Sum of Jul-2023 | F3: Sum of Aug-2023 | G3: Sum of Sep-2023 | H3: Sum of Oct-2023 | I3: Sum of Nov-2023 | J3: Sum of Dec-2023 | K3: Sum of Jan-2024 | L3: Sum of Feb-2024 | M3: Sum of Mar-2024 | N3: Sum of Apr-2024 | O3: Sum of May-2024 | P3: Sum of Jun-2024 | Q3: Sum of Jul-2024 | R3: Sum of Aug-2024 | S3: Sum of Sep-2024 | T3: Sum of Oct-2024 | U3: Sum of Nov-2024 | V3: Sum of Dec-2024 | W3: Sum of Jan-2025 | X3: Sum of Feb-2025 | Y3: Sum of Mar-2025 | Z3: Sum of Apr-2025 | AA3: Sum of May-2025 | AB3: Sum of Jun-2025 | AC3: Sum of Jul-2025 | AD3: Sum of Aug-2025 | AE3: Sum of Sep-2025 | AF3: Sum of Oct-2025 | AG3: Sum of Nov-2025 | AH3: Sum of Dec-2025 | AI3: Sum of Jan-2026 | AJ3: Sum of Feb-2026 | AK3: Sum of Mar-2026 | AL3: Sum of Apr-2026 | AM3: Sum of May-2026
A4: Abohar 2337
A5: ABOHAR 3196 | AG5: 39000 | AH5: 45000 | AI5: 45000 | AJ5: 45000 | AK5: 45000 | AL5: 90000 | AM5: 90000
A6: AKBARPUR 3300 | AL6: 96428 | AM6: 137754
A7: AKOLA 2657 | B7: 74592 | C7: 74592 | D7: 74592 | E7: 74592 | F7: 74592 | G7: 74592 | H7: 74592 | I7: 74592 | J7: 74592 | K7: 74592 | L7: 74592 | M7: 74592 | N7: 74592 | O7: 74592 | P7: 74592 | Q7: 74592 | R7: 74592 | S7: 74592 | T7: 74592
A8: Akola 1519 | AL8: 3658.9 | AM8: 109767
A9: Akola 1728
A10: Akola 2353 | B10: 104583 | C10: 104583 | D10: 104583 | E10: 104583 | F10: 104583 | G10: 104583 | H10: 104583 | I10: 104583 | J10: 104583 | K10: 199469 | L10: 308892 | M10: 308892 | N10: 308892 | O10: 308892 | P10: 308892 | Q10: 308892 | R10: 204309 | S10: 204309 | T10: 102879 | U10: 102879 | V10: 102879 | W10: 102879 | X10: 211194 | Y10: 211194 | Z10: 211194 | AA10: 211194 | AB10: 211194 | AC10: 211194 | AD10: 211194 | AE10: 108315 | AF10: 108315 | AG10: 108315 | AH10: 108315 | AI10: 102879 | AJ10: 102879 | AK10: 102879 | AL10: 102879 | AM10: 102879
A11: Akola 2354
A12: Akola 2362
A13: Akola 2373
A14: AKOLA 2516 | AL14: 65859 | AM14: 109767
A15: AKOLA 2528
A16: AKOLA 2894 | M16: 102967 | N16: 170856 | O16: 170856 | P16: 170856 | Q16: 170856 | R16: 67889
A17: AKOLA 2908 | M17: 19448 | N17: 60288 | O17: 60288 | P17: 60288 | Q17: 60288 | R17: 60288 | S17: 60288 | T17: 60288
A18: AKOLA 3069 | Y18: 92872 | Z18: 92872 | AA18: 92872 | AB18: 92872 | AC18: 92872 | AD18: 92872 | AE18: 92872 | AF18: 92872 | AG18: 92872 | AH18: 92872 | AI18: 92872 | AJ18: 92872 | AK18: 92872 | AL18: 228756 | AM18: 228756
A19: AKOLA 3222
A20: AKOLA 3279 | AL20: 410350 | AM20: 410350
A21: AKOLA CON 3283 | AL21: 142013 | AM21: 142013
A22: ALWAR 3005 | T22: 29661 | U22: 29661 | V22: 29661
A23: ALWAR 3006 | S23: 12896 | T23: 96720 | U23: 96720 | V23: 96720
A24: AMETHI 2823 | I24: 20167 | J24: 55000 | K24: 55000 | L24: 55000 | M24: 55000 | N24: 36667
A25: AMETHI 3115 | Z25: 112700 | AA25: 120750 | AB25: 120750 | AC25: 120750 | AD25: 120750 | AE25: 120750 | AF25: 120750 | AG25: 120750 | AH25: 120750 | AI25: 120750 | AJ25: 120750
A26: AMETHI 3293 | AL26: 136000 | AM26: 136000
A27: AMETHI 3351 | AM27: 34066
A28: AMRAVATI 3282 | AL28: 139400 | AM28: 139400
A29: AMRITSAR 2625 | B29: 65450
A30: ANANTHASAGAR 2454
A31: ANANTHASAGAR 2455
A32: ANNUR 3076 | Y32: 119786 | Z32: 195440 | AA32: 195440 | AB32: 195440 | AC32: 195440 | AD32: 195440 | AE32: 195440 | AF32: 195440 | AG32: 195440 | AH32: 195440 | AI32: 195440 | AJ32: 27920
A33: ANTAWADI 2549
A34: ARUPPUKOTTAI 3053 | V34: 209032 | W34: 240000 | X34: 240000 | Y34: 240000 | Z34: -176000
A35: ARUPPUKOTTAI 3210 | AH35: 373787 | AI35: 429163 | AJ35: 429163 | AK35: 429163 | AL35: 429163 | AM35: 429163
A36: ARUPPUKOTTAI 3211 | AH36: 193390 | AI36: 285480 | AJ36: 285480 | AK36: 285480 | AL36: 285480 | AM36: 285480
A37: ARUPPUKOTTAI 3218 | AH37: 602183 | AI37: 933383 | AJ37: 933383 | AK37: 933383 | AL37: 933383 | AM37: 933383
A38: ARUPPUKOTTAI 3221 | AH38: 235759 | AI38: 487236 | AJ38: 487236 | AK38: 487236 | AL38: 487236 | AM38: 487236
A39: Ashok Nagar 453 | B39: 197030 | C39: 197030 | D39: 197030 | E39: 197030 | F39: 197030 | G39: 197030 | H39: 197030 | I39: 197030 | J39: 197030 | K39: 197030 | L39: 197030 | M39: 197030 | N39: 197030 | O39: 197030 | P39: 197030 | Q39: 197030 | R39: 197030 | S39: 197030 | T39: 197030 | U39: 197030 | V39: 197030 | W39: 197030 | X39: 197030 | Y39: 197030 | Z39: 197030 | AA39: 197030 | AB39: 197030 | AC39: 197030 | AD39: 197030 | AE39: 197030 | AF39: 197030 | AG39: 197030 | AH39: 197030 | AI39: 197030 | AJ39: 197030 | AK39: 197030 | AL39: 197030 | AM39: 197030
A40: ASHOKNAGAR 2540 | B40: 227811 | C40: 227811 | D40: 227811 | E40: 227811 | F40: 227811 | G40: 227811 | H40: 227811 | I40: 78635 | J40: 78635 | K40: 78635 | L40: 78635 | M40: 78635 | N40: 78635 | O40: 157270 | P40: 78635 | Q40: 78635 | R40: 78635 | S40: 78635 | T40: 78635 | U40: 78635 | V40: 78635 | W40: 78635 | X40: 78635 | Y40: 78635 | Z40: 78635 | AA40: 78635 | AB40: 78635 | AC40: 78635 | AD40: 78635 | AE40: 78635 | AF40: 78635 | AG40: 78635 | AH40: 66640 | AI40: 66640 | AJ40: 66640 | AK40: 66640 | AL40: 66640 | AM40: 66640
A41: ASHOKNAGAR CON 3171 | AB41: 135878 | AC41: 135878 | AD41: 135878 | AE41: 135878 | AF41: 135878 | AG41: 135878 | AH41: 135878 | AI41: 135878 | AJ41: 135878 | AK41: 135878 | AL41: 135878 | AM41: 135878
A42: ATMAKUR 2964 | O42: 158895 | P42: 158895 | Q42: 158895 | R42: 158895
A43: ATRAULI 3160 | AA43: 46087 | AB43: 75195 | AC43: 75195 | AD43: 75195 | AE43: 75195 | AF43: 75195 | AG43: 75195 | AH43: 75195 | AI43: 75195 | AJ43: 75195 | AK43: 75195 | AL43: 75195 | AM43: 75195
A44: BAHRAICH 2601
A45: BALABHADRAPURAM 3220 | AH45: 7875 | AI45: 100351 | AJ45: 110207 | AK45: 110207 | AL45: 110207 | AM45: 110207
A46: BANGALORE 2785 | E46: 14687 | F46: 65043 | G46: 65043 | H46: 65043 | I46: 65043 | J46: 65043 | K46: 65043 | L46: 65043 | M46: 65043 | N46: 65043 | O46: 65043 | P46: 65043 | Q46: 65043 | R46: 65043 | S46: 41193.5
A47: BANGALORE 2786 | E47: 1935.4839
A48: BARABANKI 2667 | B48: 140265 | C48: 140265 | D48: 140265 | E48: 140265 | F48: 140265 | G48: 140265 | H48: 140265 | I48: 140265 | J48: 140265 | K48: 67870 | N48: 39898 | O48: 149616 | P48: 149616 | Q48: 149616 | R48: 149616 | S48: 149616 | T48: 149616 | U48: 149616 | V48: 149616
A49: BARABANKI 2880 | K49: 140739 | L49: 155818 | M49: 155818 | N49: 155818 | O49: 155818 | P49: 155818 | Q49: 155818 | R49: 155818 | S49: 155818 | T49: 155818 | U49: 155818 | V49: 155818 | W49: 155818
A50: BARABANKI 3102 | Z50: 166448 | AA50: 166448 | AB50: 166448 | AC50: 166448 | AD50: 166448 | AE50: 166448 | AF50: 166448 | AG50: 166448 | AH50: 166448 | AI50: 107386
A51: BARABANKI 3136 | Z51: 92452 | AA51: 173348 | AB51: 173348 | AC51: 173348 | AD51: 173348 | AE51: 173348 | AF51: 173348 | AG51: 86674
A52: BARAN 3073 | Z52: 48978 | AA52: 48978 | AB52: 48978 | AC52: 48978 | AD52: 48978 | AE52: 48978 | AF52: 48978 | AG52: 48978 | AH52: 48978 | AI52: 48978 | AJ52: 48978 | AL52: 48978 | AM52: 48978
A53: Barauni 2435
A54: Barauni 2445
A55: Barauni 2446
A56: BARAUNI 2591
A57: BARAUNI 2592
A58: BARAUNI 2593
A59: BASMATH 2867 | L59: 153558 | M59: 202419 | N59: 202419 | O59: 97945 | P59: 67473 | Q59: 67473 | R59: 67473
A60: BASTI 3120 | Z60: 168000 | AA60: 168000 | AB60: 168000 | AC60: 168000 | AD60: 168000 | AE60: 168000 | AF60: 168000 | AG60: 168000 | AH60: 168000 | AI60: 168000 | AJ60: 168000
A61: Beed 2293
A62: BEED 2783 | D62: 18000 | E62: 180000 | F62: 180000 | G62: 180000 | K62: 33871 | L62: 210000 | M62: 210000 | N62: 210000 | O62: 210000 | P62: 210000 | Q62: 210000 | R62: 189677
A63: BEED 2784 | D63: 11862 | E63: 118620 | F63: 118620 | G63: 106758
A64: BEED 2856 | L64: 140000 | M64: 140000 | N64: 140000 | O64: 140000 | P64: 140000 | Q64: 140000 | R64: 135484
A65: BEED 2866 | L65: 49166 | M65: 49166 | N65: 49166 | O65: 49166 | P65: 26222
A66: BEGUSARAI 2919 | O66: 231000 | P66: 231000 | Q66: 231000 | R66: 231000 | S66: 231000 | T66: 231000 | U66: 231000 | V66: 231000 | W66: 231000
A67: BEGUSARAI 2673 | B67: 396110 | C67: 396110 | D67: 396110 | E67: 396110 | F67: 396110 | G67: 396110 | H67: 396110 | I67: 396110 | J67: 396110 | K67: 153725 | L67: 153725
A68: BEGUSARAI 2674 | B68: 145200 | C68: 145200 | D68: 145200 | E68: 145200 | F68: 145200 | G68: 145200 | H68: 145200 | I68: 145200 | J68: 145200 | K68: 145200 | L68: 145200
A69: BEGUSARAI 2704 | B69: 76285 | C69: 76285 | D69: 76285 | E69: 76285 | F69: 76285 | G69: 76285 | H69: 76285 | I69: 76285 | J69: 76285 | K69: 76285 | L69: 76285 | M69: 76285 | N69: 83220 | O69: 83220 | P69: 83220 | Q69: 83220 | R69: 83220 | S69: 83220 | T69: 83220 | U69: 83220 | V69: 83220 | W69: 83220 | X69: 83220 | AL69: 3005.1667 | AM69: 90155
A70: BEGUSARAI 2705 | B70: 324000 | C70: 324000 | D70: 324000 | E70: 324000 | F70: 324000 | G70: 324000 | H70: 324000 | I70: 324000 | J70: 324000 | K70: 324000 | L70: 324000 | M70: 324000 | N70: 324000 | O70: 324000 | P70: 324000 | Q70: 324000 | R70: 324000 | S70: 324000 | T70: 324000 | U70: 324000 | V70: 324000 | W70: 324000 | X70: 138857
A71: BEGUSARAI 2706 | B71: 107261 | C71: 107261 | D71: 107261 | E71: 107261 | F71: 107261 | G71: 107261 | H71: 107261 | I71: 107261 | J71: 107261
A72: BEGUSARAI 2707 | B72: 206954 | C72: 206954 | D72: 206954 | E72: 206954 | F72: 206954 | G72: 206954 | H72: 206954 | I72: 206954 | J72: 206954 | K72: 206954 | L72: 206954
A73: BEGUSARAI 2712 | C73: 202400 | D73: 202400 | E73: 202400 | F73: 202400 | G73: 202400 | H73: 202400 | I73: 202400 | J73: 202400 | K73: 202400 | L73: 202400
A74: BEGUSARAI 2929 | N74: 107261 | O74: 107261 | P74: 107261 | Q74: 107261 | R74: 107261 | S74: 107261 | T74: 107261 | U74: 107261 | V74: 107261 | W74: 107261 | X74: 107261 | Y74: 107261
A75: BEGUSARAI 2930 | O75: 208560 | P75: 208560 | Q75: 208560 | R75: 208560 | S75: 208560 | T75: 208560 | U75: 208560 | V75: 208560 | W75: 208560
A76: BEGUSARAI 2931 | N76: 392230 | O76: 392230 | P76: 392230 | Q76: 392230 | R76: 392230 | S76: 392230 | T76: 392230 | U76: 392230 | V76: 392230 | W76: 392230 | X76: 240430 | Y76: 240430 | AL76: 5575.2 | AM76: 167256
A77: BEGUSARAI 2933 | O77: 191208 | P77: 191208 | Q77: 191208 | R77: 191208 | S77: 191208 | T77: 191208 | U77: 191208 | V77: 191208 | W77: 191208 | AM77: 127472
A78: BEGUSARAI 2934 | N78: 471576 | O78: 471576 | P78: 471576 | Q78: 471576 | R78: 471576 | S78: 471576 | T78: 471576 | U78: 471576 | V78: 471576 | W78: 177456 | X78: 177456
A79: BEGUSARAI 2946 | N79: 102456 | O79: 102456 | P79: 102456 | Q79: 102456 | R79: 102456 | S79: 102456 | T79: 102456 | U79: 102456 | V79: 102456 | W79: 102456 | X79: 102456
A80: BEGUSARAI 2985 | O80: 79143 | P80: 153340 | Q80: 153340 | R80: 153340 | S80: 153340 | T80: 153340 | U80: -66447.333
A81: BEGUSARAI 3109 | Z81: 219440 | AA81: 253200 | AB81: 253200 | AC81: 253200 | AD81: 253200 | AE81: 253200 | AF81: 253200 | AG81: 253200 | AH81: 253200 | AI81: 253200 | AJ81: 253200
A82: BEGUSARAI 3158 | AA82: 351000 | AB82: 351000 | AC82: 351000 | AD82: 351000 | AE82: 351000 | AF82: 351000 | AG82: 351000 | AH82: 351000 | AI82: 351000
A83: BEGUSARAI 3185 | AE83: 35460 | AF83: 118200 | AG83: 118200 | AH83: 118200 | AI83: 118200 | AJ83: 118200 | AK83: 118200 | AL83: 118200 | AM83: 118200
A84: BEGUSARAI 3323 | AL84: 87610.1 | AM84: 223938
A85: BEGUSARAI 3324 | AL85: 5115 | AM85: 153450
A86: Bharatpur 1741 | B86: 98307 | C86: 103220 | D86: 103220 | E86: 103220 | F86: 103220 | G86: 103220 | H86: 103220 | I86: 104203 | J86: 104203 | K86: 104203 | L86: 104203 | M86: 104203 | N86: 104203 | O86: 104203 | P86: 104203 | Q86: 104203 | R86: 104203 | S86: 104203 | T86: 104203 | U86: 104203 | V86: 104203 | W86: 104203 | X86: 104203 | Y86: 104203 | Z86: 104203 | AA86: 104203 | AB86: 104203 | AC86: 104203 | AD86: 104203 | AE86: 104203 | AF86: 104203 | AG86: 104203 | AH86: 104203 | AI86: 104203 | AJ86: 104203 | AK86: 104203 | AL86: 104203 | AM86: 104203
A87: Bharatpur 2402
A88: BHARATPUR 2634 | B88: 153902
A89: BHARATPUR 2638 | B89: 70500 | C89: 70500 | D89: 70500 | E89: 70500
A90: BHARATPUR 2643 | B90: 222554 | C90: 222554 | D90: 222554
A91: BHARATPUR 2789 | T91: 182200 | U91: 182200 | V91: 182200 | W91: 182200 | X91: 182200 | Y91: 182200 | Z91: 182200 | AA91: 182200 | AB91: 182200 | AC91: 182200 | AD91: 182200 | AE91: 182200 | AF91: 182200 | AG91: 182200 | AH91: 182200 | AI91: 182200 | AJ91: 182200 | AK91: 182200 | AL91: 182200 | AM91: 182200
A92: BHARATPUR 2790 | H92: 88725 | I92: 88725 | J92: 88725 | K92: 88725 | L92: 88725 | M92: 88725 | N92: 88725 | O92: 88725 | P92: 88725 | Q92: 88725 | R92: 88725 | S92: 88725 | T92: 88725 | U92: 88725 | V92: 88725 | W92: 88725 | X92: 88725 | Y92: 88725 | Z92: 88725 | AA92: 88725 | AB92: 88725 | AC92: 88725 | AD92: 88725 | AE92: 88725 | AF92: 88725
A93: Bharatpur 400
A94: BHAWANIPATNA 2502
A95: BHOJPUR 3217 | AH95: 45480 | AI95: 93993 | AJ95: 53710
A96: Bihta 2079
A97: BODWAD 3020 | U97: 90594 | V97: 90594 | W97: 90594 | X97: 90594 | Y97: 90594 | AL97: 2253.3333 | AM97: 67600
A98: BODWAD 3021 | U98: 42329 | V98: 42329 | W98: 42329 | X98: 42329 | Y98: 42329 | Z98: 42329 | AA98: 42329 | AB98: 42329 | AC98: 13655 | AM98: 40222.097
A99: BODWAD 3039 | U99: 24500 | V99: 35000 | W99: 35000 | X99: 35000 | Y99: 35000 | Z99: 35000 | AA99: 58710 | AB99: 70000 | AC99: 35000
A100: BODWAD 3125 | Z100: 36400 | AA100: 109200 | AB100: 109200 | AC100: 70452
A101: BODWAD 3199 | AG101: 58240 | AH101: 109200 | AI101: 109200 | AJ101: 109200 | AK101: 109200 | AL101: 109200 | AM101: 109200
A102: BODWAD 3333 | AL102: 2360 | AM102: 70800
...

Sheet Summary
C3: Values | D3: Det
C4: Sum of FY 23-24 | E4: Sum of FY 24-25 | G4: Sum of FY 25-26 | I4: Total Sum of FY 23-24 | J4: Total Sum of FY 24-25 | K4: Total Sum of FY 25-26
A5: CMP ID | B5: Capacity | C5: Rent | D5: Rev | E5: Rent | F5: Rev | G5: Rent | H5: Rev | L5: 23-24 to 24-25 | M5: 24-25 TO 25-26
A6: Abohar 2337 | B6: 1733 | C6: 0 | D6: 0 | E6: 0 | F6: 0 | G6: 0 | H6: 0 | I6: 0 | J6: 0 | K6: 0 | L6: =E6/C6-1 -> #DIV/0! | M6: =G6/E6-1 -> #DIV/0!
A7: ABOHAR 3196 | B7: 1679 | C7: 0 | D7: 0 | E7: 0 | F7: 0 | G7: 219000 | H7: 416038.7 | I7: 0 | J7: 0 | K7: 635038.7 | L7: =E7/C7-1 -> #DIV/0! | M7: =G7/E7-1 -> #DIV/0!
A8: AKBARPUR 3300 | B8: 2551 | C8: 0 | D8: 0 | E8: 0 | F8: 0 | G8: 0 | H8: 0 | I8: 0 | J8: 0 | K8: 0 | L8: =E8/C8-1 -> #DIV/0! | M8: =G8/E8-1 -> #DIV/0!
A9: AKOLA 2657 | B9: 1554 | C9: 895104 | D9: 1274245.8 | E9: 522144 | F9: 1061498.1 | G9: 0 | H9: 0 | I9: 2169349.8 | J9: 1583642.1 | K9: 0 | L9: =E9/C9-1 -> -0.41666667 | M9: =G9/E9-1 -> -1
A10: Akola 1519 | B10: 871 | C10: 0 | D10: 0 | E10: 0 | F10: 0 | G10: 0 | H10: 0 | I10: 0 | J10: 0 | K10: 0 | L10: =E10/C10-1 -> #DIV/0! | M10: =G10/E10-1 -> #DIV/0!
A11: Akola 1728 | B11: 1005 | C11: 0 | D11: 0 | E11: 0 | F11: 0 | G11: 0 | H11: 0 | I11: 0 | J11: 0 | K11: 0 | L11: =E11/C11-1 -> #DIV/0! | M11: =G11/E11-1 -> #DIV/0!
A12: Akola 2353 | B12: 2485 | C12: 1758500 | D12: 2088187 | E12: 2478090 | F12: 2964305.6 | G12: 1797867 | H12: 1647622.9 | I12: 3846687 | J12: 5442395.6 | K12: 3445489.9 | L12: =E12/C12-1 -> 0.40920671 | M12: =G12/E12-1 -> -0.27449487
A13: Akola 2354 | B13: 833 | C13: 0 | D13: 0 | E13: 0 | F13: 0 | G13: 0 | H13: 0 | I13: 0 | J13: 0 | K13: 0 | L13: =E13/C13-1 -> #DIV/0! | M13: =G13/E13-1 -> #DIV/0!
A14: Akola 2362 | B14: 813 | C14: 0 | D14: 0 | E14: 0 | F14: 0 | G14: 0 | H14: 0 | I14: 0 | J14: 0 | K14: 0 | L14: =E14/C14-1 -> #DIV/0! | M14: =G14/E14-1 -> #DIV/0!
A15: Akola 2373 | B15: 871 | C15: 0 | D15: 0 | E15: 0 | F15: 0 | G15: 0 | H15: 0 | I15: 0 | J15: 0 | K15: 0 | L15: =E15/C15-1 -> #DIV/0! | M15: =G15/E15-1 -> #DIV/0!
A16: AKOLA 2516 | B16: 871 | C16: 0 | D16: 0 | E16: 0 | F16: 1166748.3 | G16: 0 | H16: 0 | I16: 0 | J16: 1166748.3 | K16: 0 | L16: =E16/C16-1 -> #DIV/0! | M16: =G16/E16-1 -> #DIV/0!
A17: AKOLA 2528 | B17: 813 | C17: 0 | D17: 0 | E17: 0 | F17: 0 | G17: 0 | H17: 0 | I17: 0 | J17: 0 | K17: 0 | L17: =E17/C17-1 -> #DIV/0! | M17: =G17/E17-1 -> #DIV/0!
... A706: YAVATMAL 3363 | B706: 2500 | C706: 0 | D706: 0 | E706: 0 | F706: 0 | G706: 0 | H706: 0 | I706: 0 | J706: 0 | K706: 0 | L706: =E706/C706-1 -> #DIV/0! | M706: =G706/E706-1 -> #DIV/0!
A707: Grand Total | C707: 3.2348876e+08 | D707: 4.7347988e+08 | E707: 4.5590143e+08 | F707: 7.2245523e+08 | G707: 4.5636892e+08 | H707: 7.7090935e+08 | I707: 7.9696864e+08 | J707: 1.1783567e+09 | K707: 1.2272783e+09 | L707: =E707/C707-1 -> 0.40932694 | M707: =G707/E707-1 -> 0.0010254142

Sheet RAW Data
A1: Details | B1: CMP ID | C1: Capacity | D1: Cost Center | E1: 45017 | F1: 45047 | G1: 45078 | H1: 45108 | I1: 45139 | J1: 45170 | K1: 45200 | L1: 45231 | M1: 45261 | N1: 45292 | O1: 45323 | P1: 45352 | Q1: FY 23-24 | R1: 45383 | S1: 45413 | T1: 45444 | U1: 45474 | V1: 45505 | W1: 45536 | X1: 45566 | Y1: 45597 | Z1: 45627 | AA1: 45658 | AB1: 45689 | AC1: 45717 | AD1: FY 24-25 | AE1: 45748 | AF1: 45778 | AG1: 45809 | AH1: 45839 | AI1: 45870 | AJ1: 45901 | AK1: 45931 | AL1: 45962 | AM1: 45992 | AN1: 46023 | AO1: 46054 | AP1: 46082 | AQ1: FY 25-26 | AR1: 46113 | AS1: 46143 | AT1: FY 26-27
A2: Rent | B2: Abohar 2337 | C2: =VLOOKUP(B2,'Rent Data'!D:I,6,0) -> 1733 | D2: NULL | Q2: =SUM(E2:P2) -> 0 | AD2: =SUM(R2:AC2) -> 0 | AQ2: =SUM(AE2:AP2) -> 0 | AT2: =SUM(AR2:AS2) -> 0
A3: Rent | B3: ABOHAR 3196 | C3: =VLOOKUP(B3,'Rent Data'!D:I,6,0) -> 1679 | D3: WH-LE-3196 | Q3: =SUM(E3:P3) -> 0 | AD3: =SUM(R3:AC3) -> 0 | AL3: 39000 | AM3: 45000 | AN3: 45000 | AO3: 45000 | AP3: 45000 | AQ3: =SUM(AE3:AP3) -> 219000 | AR3: 90000 | AS3: 90000 | AT3: =SUM(AR3:AS3) -> 180000
A4: Rent | B4: AKBARPUR 3300 | C4: =VLOOKUP(B4,'Rent Data'!D:I,6,0) -> 2551 | D4: WH-LE-3300 | Q4: =SUM(E4:P4) -> 0 | AD4: =SUM(R4:AC4) -> 0 | AQ4: =SUM(AE4:AP4) -> 0 | AR4: 96428 | AS4: 137754 | AT4: =SUM(AR4:AS4) -> 234182
A5: Rent | B5: AKOLA 2657 | C5: =VLOOKUP(B5,'Rent Data'!D:I,6,0) -> 1554 | D5: WH-LE-2657 | E5: 74592 | F5: 74592 | G5: 74592 | H5: 74592 | I5: 74592 | J5: 74592 | K5: 74592 | L5: 74592 | M5: 74592 | N5: 74592 | O5: 74592 | P5: 74592 | Q5: =SUM(E5:P5) -> 895104 | R5: 74592 | S5: 74592 | T5: 74592 | U5: 74592 | V5: 74592 | W5: 74592 | X5: 74592 | AD5: =SUM(R5:AC5) -> 522144 | AQ5: =SUM(AE5:AP5) -> 0 | AT5: =SUM(AR5:AS5) -> 0
A6: Rent | B6: Akola 1519 | C6: =VLOOKUP(B6,'Rent Data'!D:I,6,0) -> 871 | D6: WH-LE-1519 | Q6: =SUM(E6:P6) -> 0 | AD6: =SUM(R6:AC6) -> 0 | AQ6: =SUM(AE6:AP6) -> 0 | AR6: 3658.9 | AS6: 109767 | AT6: =SUM(AR6:AS6) -> 113425.9
A7: Rent | B7: Akola 1728 | C7: =VLOOKUP(B7,'Rent Data'!D:I,6,0) -> 1005 | D7: NULL | Q7: =SUM(E7:P7) -> 0 | AD7: =SUM(R7:AC7) -> 0 | AQ7: =SUM(AE7:AP7) -> 0 | AT7: =SUM(AR7:AS7) -> 0
A8: Rent | B8: Akola 2353 | C8: =VLOOKUP(B8,'Rent Data'!D:I,6,0) -> 2485 | D8: WH-LE-2353 | E8: 104583 | F8: 104583 | G8: 104583 | H8: 104583 | I8: 104583 | J8: 104583 | K8: 104583 | L8: 104583 | M8: 104583 | N8: 199469 | O8: 308892 | P8: 308892 | Q8: =SUM(E8:P8) -> 1758500 | R8: 308892 | S8: 308892 | T8: 308892 | U8: 308892 | V8: 204309 | W8: 204309 | X8: 102879 | Y8: 102879 | Z8: 102879 | AA8: 102879 | AB8: 211194 | AC8: 211194 | AD8: =SUM(R8:AC8) -> 2478090 | AE8: 211194 | AF8: 211194 | AG8: 211194 | AH8: 211194 | AI8: 211194 | AJ8: 108315 | AK8: 108315 | AL8: 108315 | AM8: 108315 | AN8: 102879 | AO8: 102879 | AP8: 102879 | AQ8: =SUM(AE8:AP8) -> 1797867 | AR8: 102879 | AS8: 102879 | AT8: =SUM(AR8:AS8) -> 205758
A9: Rent | B9: Akola 2354 | C9: =VLOOKUP(B9,'Rent Data'!D:I,6,0) -> 833 | D9: NULL | Q9: =SUM(E9:P9) -> 0 | AD9: =SUM(R9:AC9) -> 0 | AQ9: =SUM(AE9:AP9) -> 0 | AT9: =SUM(AR9:AS9) -> 0
A10: Rent | B10: Akola 2362 | C10: =VLOOKUP(B10,'Rent Data'!D:I,6,0) -> 813 | D10: NULL | Q10: =SUM(E10:P10) -> 0 | AD10: =SUM(R10:AC10) -> 0 | AQ10: =SUM(AE10:AP10) -> 0 | AT10: =SUM(AR10:AS10) -> 0
A11: Rent | B11: Akola 2373 | C11: =VLOOKUP(B11,'Rent Data'!D:I,6,0) -> 871 | D11: NULL | Q11: =SUM(E11:P11) -> 0 | AD11: =SUM(R11:AC11) -> 0 | AQ11: =SUM(AE11:AP11) -> 0 | AT11: =SUM(AR11:AS11) -> 0
A12: Rent | B12: AKOLA 2516 | C12: =VLOOKUP(B12,'Rent Data'!D:I,6,0) -> 871 | D12: WH-FR-2516 | Q12: =SUM(E12:P12) -> 0 | AD12: =SUM(R12:AC12) -> 0 | AQ12: =SUM(AE12:AP12) -> 0 | AR12: 65859 | AS12: 109767 | AT12: =SUM(AR12:AS12) -> 175626
A13: Rent | B13: AKOLA 2528 | C13: =VLOOKUP(B13,'Rent Data'!D:I,6,0) -> 813 | D13: NULL | Q13: =SUM(E13:P13) -> 0 | AD13: =SUM(R13:AC13) -> 0 | AQ13: =SUM(AE13:AP13) -> 0 | AT13: =SUM(AR13:AS13) -> 0
A14: Rent | B14: AKOLA 2894 | C14: =VLOOKUP(B14,'Rent Data'!D:I,6,0) -> 2043 | D14: WH-FR-2894 | P14: 102967 | Q14: =SUM(E14:P14) -> 102967 | R14: 170856 | S14: 170856 | T14: 170856 | U14: 170856 | V14: 67889 | AD14: =SUM(R14:AC14) -> 751313 | AQ14: =SUM(AE14:AP14) -> 0 | AT14: =SUM(AR14:AS14) -> 0
A15: Rent | B15: AKOLA 2908 | C15: =VLOOKUP(B15,'Rent Data'!D:I,6,0) -> 1675 | D15: WH-LE-2908 | P15: 19448 | Q15: =SUM(E15:P15) -> 19448 | R15: 60288 | S15: 60288 | T15: 60288 | U15: 60288 | V15: 60288 | W15: 60288 | X15: 60288 | AD15: =SUM(R15:AC15) -> 422016 | AQ15: =SUM(AE15:AP15) -> 0 | AT15: =SUM(AR15:AS15) -> 0
A16: Rent | B16: AKOLA 3069 | C16: =VLOOKUP(B16,'Rent Data'!D:I,6,0) -> 2381 | D16: WH-LE-3069 | Q16: =SUM(E16:P16) -> 0 | AC16: 92872 | AD16: =SUM(R16:AC16) -> 92872 | AE16: 92872 | AF16: 92872 | AG16: 92872 | AH16: 92872 | AI16: 92872 | AJ16: 92872 | AK16: 92872 | AL16: 92872 | AM16: 92872 | AN16: 92872 | AO16: 92872 | AP16: 92872 | AQ16: =SUM(AE16:AP16) -> 1114464 | AR16: 228756 | AS16: 228756 | AT16: =SUM(AR16:AS16) -> 457512
A17: Rent | B17: AKOLA 3222 | C17: =VLOOKUP(B17,'Rent Data'!D:I,6,0) -> 2485 | D17: WH-LE-3222 | Q17: =SUM(E17:P17) -> 0 | AD17: =SUM(R17:AC17) -> 0 | AQ17: =SUM(AE17:AP17) -> 0 | AT17: =SUM(AR17:AS17) -> 0
A18: Rent | B18: AKOLA 3279 | C18: =VLOOKUP(B18,'Rent Data'!D:I,6,0) -> 2000 | D18: WH-LE-3279 | Q18: =SUM(E18:P18) -> 0 | AD18: =SUM(R18:AC18) -> 0 | AQ18: =SUM(AE18:AP18) -> 0 | AR18: 410350 | AS18: 410350 | AT18: =SUM(AR18:AS18) -> 820700
A19: Rent | B19: AKOLA CON 3283 | C19: =VLOOKUP(B19,'Rent Data'!D:I,6,0) -> 3156 | D19: WH-LE-3283 | Q19: =SUM(E19:P19) -> 0 | AD19: =SUM(R19:AC19) -> 0 | AQ19: =SUM(AE19:AP19) -> 0 | AR19: 142013 | AS19: 142013 | AT19: =SUM(AR19:AS19) -> 284026
A20: Rent | B20: ALWAR 3005 | C20: =VLOOKUP(B20,'Rent Data'!D:I,6,0) -> 761 | D20: WH-LE-3005 | Q20: =SUM(E20:P20) -> 0 | X20: 29661 | Y20: 29661 | Z20: 29661 | AD20: =SUM(R20:AC20) -> 88983 | AQ20: =SUM(AE20:AP20) -> 0 | AT20: =SUM(AR20:AS20) -> 0
A21: Rent | B21: ALWAR 3006 | C21: =VLOOKUP(B21,'Rent Data'!D:I,6,0) -> 1653 | D21: WH-LE-3006 | Q21: =SUM(E21:P21) -> 0 | W21: 12896 | X21: 96720 | Y21: 96720 | Z21: 96720 | AD21: =SUM(R21:AC21) -> 303056 | AQ21: =SUM(AE21:AP21) -> 0 | AT21: =SUM(AR21:AS21) -> 0
A22: Rent | B22: AMETHI 2823 | C22: =VLOOKUP(B22,'Rent Data'!D:I,6,0) -> 1833 | D22: WH-LE-2823 | L22: 20167 | M22: 55000 | N22: 55000 | O22: 55000 | P22: 55000 | Q22: =SUM(E22:P22) -> 240167 | R22: 36667 | AD22: =SUM(R22:AC22) -> 36667 | AQ22: =SUM(AE22:AP22) -> 0 | AT22: =SUM(AR22:AS22) -> 0
A23: Rent | B23: AMETHI 3115 | C23: =VLOOKUP(B23,'Rent Data'!D:I,6,0) -> 2875 | D23: WH-LE-3115 | Q23: =SUM(E23:P23) -> 0 | AD23: =SUM(R23:AC23) -> 0 | AE23: 112700 | AF23: 120750 | AG23: 120750 | AH23: 120750 | AI23: 120750 | AJ23: 120750 | AK23: 120750 | AL23: 120750 | AM23: 120750 | AN23: 120750 | AO23: 120750 | AQ23: =SUM(AE23:AP23) -> 1320200 | AT23: =SUM(AR23:AS23) -> 0
A24: Rent | B24: AMETHI 3293 | C24: =VLOOKUP(B24,'Rent Data'!D:I,6,0) -> 2875 | D24: WH-LE-3293 | Q24: =SUM(E24:P24) -> 0 | AD24: =SUM(R24:AC24) -> 0 | AQ24: =SUM(AE24:AP24) -> 0 | AR24: 136000 | AS24: 136000 | AT24: =SUM(AR24:AS24) -> 272000
A25: Rent | B25: AMETHI 3351 | C25: =VLOOKUP(B25,'Rent Data'!D:I,6,0) -> 1330 | D25: WH-LE-3351 | Q25: =SUM(E25:P25) -> 0 | AD25: =SUM(R25:AC25) -> 0 | AQ25: =SUM(AE25:AP25) -> 0 | AS25: 34066 | AT25: =SUM(AR25:AS25) -> 34066
A26: Rent | B26: AMRAVATI 3282 | C26: =VLOOKUP(B26,'Rent Data'!D:I,6,0) -> 2904 | D26: WH-LE-3282 | Q26: =SUM(E26:P26) -> 0 | AD26: =SUM(R26:AC26) -> 0 | AQ26: =SUM(AE26:AP26) -> 0 | AR26: 139400 | AS26: 139400 | AT26: =SUM(AR26:AS26) -> 278800
A27: Rent | B27: AMRITSAR 2625 | C27: =VLOOKUP(B27,'Rent Data'!D:I,6,0) -> 1983 | D27: NULL | E27: 65450 | Q27: =SUM(E27:P27) -> 65450 | AD27: =SUM(R27:AC27) -> 0 | AQ27: =SUM(AE27:AP27) -> 0 | AT27: =SUM(AR27:AS27) -> 0
A28: Rent | B28: ANANTHASAGAR 2454 | C28: =VLOOKUP(B28,'Rent Data'!D:I,6,0) -> 5255 | D28: NULL | Q28: =SUM(E28:P28) -> 0 | AD28: =SUM(R28:AC28) -> 0 | AQ28: =SUM(AE28:AP28) -> 0 | AT28: =SUM(AR28:AS28) -> 0
A29: Rent | B29: ANANTHASAGAR 2455 | C29: =VLOOKUP(B29,'Rent Data'!D:I,6,0) -> 5255 | D29: NULL | Q29: =SUM(E29:P29) -> 0 | AD29: =SUM(R29:AC29) -> 0 | AQ29: =SUM(AE29:AP29) -> 0 | AT29: =SUM(AR29:AS29) -> 0
A30: Rent | B30: ANNUR 3076 | C30: =VLOOKUP(B30,'Rent Data'!D:I,6,0) -> 3723 | D30: WH-LE-3076 | Q30: =SUM(E30:P30) -> 0 | AC30: 119786 | AD30: =SUM(R30:AC30) -> 119786 | AE30: 195440 | AF30: 195440 | AG30: 195440 | AH30: 195440 | AI30: 195440 | AJ30: 195440 | AK30: 195440 | AL30: 195440 | AM30: 195440 | AN30: 195440 | AO30: 27920 | AQ30: =SUM(AE30:AP30) -> 1982320 | AT30: =SUM(AR30:AS30) -> 0
A31: Rent | B31: ANTAWADI 2549 | C31: =VLOOKUP(B31,'Rent Data'!D:I,6,0) -> 4215 | D31: NULL | Q31: =SUM(E31:P31) -> 0 | AD31: =SUM(R31:AC31) -> 0 | AQ31: =SUM(AE31:AP31) -> 0 | AT31: =SUM(AR31:AS31) -> 0
A32: Rent | B32: ARUPPUKOTTAI 3053 | C32: =VLOOKUP(B32,'Rent Data'!D:I,6,0) -> 4000 | D32: WH-LE-3053 | Q32: =SUM(E32:P32) -> 0 | Z32: 209032 | AA32: 240000 | AB32: 240000 | AC32: 240000 | AD32: =SUM(R32:AC32) -> 929032 | AE32: -176000 | AQ32: =SUM(AE32:AP32) -> -176000 | AT32: =SUM(AR32:AS32) -> 0
A33: Rent | B33: ARUPPUKOTTAI 3210 | C33: =VLOOKUP(B33,'Rent Data'!D:I,6,0) -> 10218 | D33: WH-LE-3210 | Q33: =SUM(E33:P33) -> 0 | AD33: =SUM(R33:AC33) -> 0 | AM33: 373787 | AN33: 429163 | AO33: 429163 | AP33: 429163 | AQ33: =SUM(AE33:AP33) -> 1661276 | AR33: 429163 | AS33: 429163 | AT33: =SUM(AR33:AS33) -> 858326
A34: Rent | B34: ARUPPUKOTTAI 3211 | C34: =VLOOKUP(B34,'Rent Data'!D:I,6,0) -> 3660 | D34: WH-LE-3211 | Q34: =SUM(E34:P34) -> 0 | AD34: =SUM(R34:AC34) -> 0 | AM34: 193390 | AN34: 285480 | AO34: 285480 | AP34: 285480 | AQ34: =SUM(AE34:AP34) -> 1049830 | AR34: 285480 | AS34: 285480 | AT34: =SUM(AR34:AS34) -> 570960
A35: Rent | B35: ARUPPUKOTTAI 3218 | C35: =VLOOKUP(B35,'Rent Data'!D:I,6,0) -> 23047 | D35: WH-LE-3218 | Q35: =SUM(E35:P35) -> 0 | AD35: =SUM(R35:AC35) -> 0 | AM35: 602183 | AN35: 933383 | AO35: 933383 | AP35: 933383 | AQ35: =SUM(AE35:AP35) -> 3402332 | AR35: 933383 | AS35: 933383 | AT35: =SUM(AR35:AS35) -> 1866766
A36: Rent | B36: ARUPPUKOTTAI 3221 | C36: =VLOOKUP(B36,'Rent Data'!D:I,6,0) -> 10827 | D36: WH-LE-3221 | Q36: =SUM(E36:P36) -> 0 | AD36: =SUM(R36:AC36) -> 0 | AM36: 235759 | AN36: 487236 | AO36: 487236 | AP36: 487236 | AQ36: =SUM(AE36:AP36) -> 1697467 | AR36: 487236 | AS36: 487236 | AT36: =SUM(AR36:AS36) -> 974472
A37: Rent | B37: Ashok Nagar 453 | C37: =VLOOKUP(B37,'Rent Data'!D:I,6,0) -> 2169 | D37: WH-LE-453 | E37: 197030 | F37: 197030 | G37: 197030 | H37: 197030 | I37: 197030 | J37: 197030 | K37: 197030 | L37: 197030 | M37: 197030 | N37: 197030 | O37: 197030 | P37: 197030 | Q37: =SUM(E37:P37) -> 2364360 | R37: 197030 | S37: 197030 | T37: 197030 | U37: 197030 | V37: 197030 | W37: 197030 | X37: 197030 | Y37: 197030 | Z37: 197030 | AA37: 197030 | AB37: 197030 | AC37: 197030 | AD37: =SUM(R37:AC37) -> 2364360 | AE37: 197030 | AF37: 197030 | AG37: 197030 | AH37: 197030 | AI37: 197030 | AJ37: 197030 | AK37: 197030 | AL37: 197030 | AM37: 197030 | AN37: 197030 | AO37: 197030 | AP37: 197030 | AQ37: =SUM(AE37:AP37) -> 2364360 | AR37: 197030 | AS37: 197030 | AT37: =SUM(AR37:AS37) -> 394060
A38: Rent | B38: ASHOKNAGAR 2540 | C38: =VLOOKUP(B38,'Rent Data'!D:I,6,0) -> 4214 | D38: WH-LE-2540 | E38: 227811 | F38: 227811 | G38: 227811 | H38: 227811 | I38: 227811 | J38: 227811 | K38: 227811 | L38: 78635 | M38: 78635 | N38: 78635 | O38: 78635 | P38: 78635 | Q38: =SUM(E38:P38) -> 1987852 | R38: 78635 | S38: 157270 | T38: 78635 | U38: 78635 | V38: 78635 | W38: 78635 | X38: 78635 | Y38: 78635 | Z38: 78635 | AA38: 78635 | AB38: 78635 | AC38: 78635 | AD38: =SUM(R38:AC38) -> 1022255 | AE38: 78635 | AF38: 78635 | AG38: 78635 | AH38: 78635 | AI38: 78635 | AJ38: 78635 | AK38: 78635 | AL38: 78635 | AM38: 66640 | AN38: 66640 | AO38: 66640 | AP38: 66640 | AQ38: =SUM(AE38:AP38) -> 895640 | AR38: 66640 | AS38: 66640 | AT38: =SUM(AR38:AS38) -> 133280
A39: Rent | B39: ASHOKNAGAR CON 3171 | C39: =VLOOKUP(B39,'Rent Data'!D:I,6,0) -> 5032 | D39: WH-LE-3171 | Q39: =SUM(E39:P39) -> 0 | AD39: =SUM(R39:AC39) -> 0 | AG39: 135878 | AH39: 135878 | AI39: 135878 | AJ39: 135878 | AK39: 135878 | AL39: 135878 | AM39: 135878 | AN39: 135878 | AO39: 135878 | AP39: 135878 | AQ39: =SUM(AE39:AP39) -> 1358780 | AR39: 135878 | AS39: 135878 | AT39: =SUM(AR39:AS39) -> 271756
A40: Rent | B40: ATMAKUR 2964 | C40: =VLOOKUP(B40,'Rent Data'!D:I,6,0) -> 1605 | D40: WH-LE-2964 | Q40: =SUM(E40:P40) -> 0 | S40: 158895 | T40: 158895 | U40: 158895 | V40: 158895 | AD40: =SUM(R40:AC40) -> 635580 | AQ40: =SUM(AE40:AP40) -> 0 | AT40: =SUM(AR40:AS40) -> 0
A41: Rent | B41: ATRAULI 3160 | C41: =VLOOKUP(B41,'Rent Data'!D:I,6,0) -> 1084 | D41: WH-LE-3160 | Q41: =SUM(E41:P41) -> 0 | AD41: =SUM(R41:AC41) -> 0 | AF41: 46087 | AG41: 75195 | AH41: 75195 | AI41: 75195 | AJ41: 75195 | AK41: 75195 | AL41: 75195 | AM41: 75195 | AN41: 75195 | AO41: 75195 | AP41: 75195 | AQ41: =SUM(AE41:AP41) -> 798037 | AR41: 75195 | AS41: 75195 | AT41: =SUM(AR41:AS41) -> 150390
A42: Rent | B42: BAHRAICH 2601 | C42: =VLOOKUP(B42,'Rent Data'!D:I,6,0) -> 1518 | D42: WH-LE-2601 | Q42: =SUM(E42:P42) -> 0 | AD42: =SUM(R42:AC42) -> 0 | AQ42: =SUM(AE42:AP42) -> 0 | AT42: =SUM(AR42:AS42) -> 0
A43: Rent | B43: BALABHADRAPURAM 3220 | C43: =VLOOKUP(B43,'Rent Data'!D:I,6,0) -> 4108 | D43: WH-LE-3220 | Q43: =SUM(E43:P43) -> 0 | AD43: =SUM(R43:AC43) -> 0 | AM43: 7875 | AN43: 100351 | AO43: 110207 | AP43: 110207 | AQ43: =SUM(AE43:AP43) -> 328640 | AR43: 110207 | AS43: 110207 | AT43: =SUM(AR43:AS43) -> 220414
A44: Rent | B44: BANGALORE 2785 | C44: =VLOOKUP(B44,'Rent Data'!D:I,6,0) -> 803 | D44: WH-LE-2785 | H44: 14687 | I44: 65043 | J44: 65043 | K44: 65043 | L44: 65043 | M44: 65043 | N44: 65043 | O44: 65043 | P44: 65043 | Q44: =SUM(E44:P44) -> 535031 | R44: 65043 | S44: 65043 | T44: 65043 | U44: 65043 | V44: 65043 | W44: 41193.5 | AD44: =SUM(R44:AC44) -> 366408.5 | AQ44: =SUM(AE44:AP44) -> 0 | AT44: =SUM(AR44:AS44) -> 0
A45: Rent | B45: BANGALORE 2786 | C45: =VLOOKUP(B45,'Rent Data'!D:I,6,0) -> 1000 | D45: WH-LE-2786 | H45: 1935.4839 | Q45: =SUM(E45:P45) -> 1935.4839 | AD45: =SUM(R45:AC45) -> 0 | AQ45: =SUM(AE45:AP45) -> 0 | AT45: =SUM(AR45:AS45) -> 0
A46: Rent | B46: BARABANKI 2667 | C46: =VLOOKUP(B46,'Rent Data'!D:I,6,0) -> 3117 | D46: WH-LE-2667 | E46: 140265 | F46: 140265 | G46: 140265 | H46: 140265 | I46: 140265 | J46: 140265 | K46: 140265 | L46: 140265 | M46: 140265 | N46: 67870 | Q46: =SUM(E46:P46) -> 1330255 | R46: 39898 | S46: 149616 | T46: 149616 | U46: 149616 | V46: 149616 | W46: 149616 | X46: 149616 | Y46: 149616 | Z46: 149616 | AD46: =SUM(R46:AC46) -> 1236826 | AQ46: =SUM(AE46:AP46) -> 0 | AT46: =SUM(AR46:AS46) -> 0
A47: Rent | B47: BARABANKI 2880 | C47: =VLOOKUP(B47,'Rent Data'!D:I,6,0) -> 3246 | D47: WH-LE-2880 | N47: 140739 | O47: 155818 | P47: 155818 | Q47: =SUM(E47:P47) -> 452375 | R47: 155818 | S47: 155818 | T47: 155818 | U47: 155818 | V47: 155818 | W47: 155818 | X47: 155818 | Y47: 155818 | Z47: 155818 | AA47: 155818 | AD47: =SUM(R47:AC47) -> 1558180 | AQ47: =SUM(AE47:AP47) -> 0 | AT47: =SUM(AR47:AS47) -> 0
A48: Rent | B48: BARABANKI 3102 | C48: =VLOOKUP(B48,'Rent Data'!D:I,6,0) -> 3117 | D48: WH-LE-3102 | Q48: =SUM(E48:P48) -> 0 | AD48: =SUM(R48:AC48) -> 0 | AE48: 166448 | AF48: 166448 | AG48: 166448 | AH48: 166448 | AI48: 166448 | AJ48: 166448 | AK48: 166448 | AL48: 166448 | AM48: 166448 | AN48: 107386 | AQ48: =SUM(AE48:AP48) -> 1605418 | AT48: =SUM(AR48:AS48) -> 0
A49: Rent | B49: BARABANKI 3136 | C49: =VLOOKUP(B49,'Rent Data'!D:I,6,0) -> 3246 | D49: WH-LE-3136 | Q49: =SUM(E49:P49) -> 0 | AD49: =SUM(R49:AC49) -> 0 | AE49: 92452 | AF49: 173348 | AG49: 173348 | AH49: 173348 | AI49: 173348 | AJ49: 173348 | AK49: 173348 | AL49: 86674 | AQ49: =SUM(AE49:AP49) -> 1219214 | AT49: =SUM(AR49:AS49) -> 0
A50: Rent | B50: BARAN 3073 | C50: =VLOOKUP(B50,'Rent Data'!D:I,6,0) -> 1484 | D50: WH-LE-3073 | Q50: =SUM(E50:P50) -> 0 | AD50: =SUM(R50:AC50) -> 0 | AE50: 48978 | AF50: 48978 | AG50: 48978 | AH50: 48978 | AI50: 48978 | AJ50: 48978 | AK50: 48978 | AL50: 48978 | AM50: 48978 | AN50: 48978 | AO50: 48978 | AQ50: =SUM(AE50:AP50) -> 538758 | AR50: 48978 | AS50: 48978 | AT50: =SUM(AR50:AS50) -> 97956
A51: Rent | B51: Barauni 2435 | C51: =VLOOKUP(B51,'Rent Data'!D:I,6,0) -> 2325 | D51: NULL | Q51: =SUM(E51:P51) -> 0 | AD51: =SUM(R51:AC51) -> 0 | AQ51: =SUM(AE51:AP51) -> 0 | AT51: =SUM(AR51:AS51) -> 0
A52: Rent | B52: Barauni 2445 | C52: =VLOOKUP(B52,'Rent Data'!D:I,6,0) -> 2383 | D52: NULL | Q52: =SUM(E52:P52) -> 0 | AD52: =SUM(R52:AC52) -> 0 | AQ52: =SUM(AE52:AP52) -> 0 | AT52: =SUM(AR52:AS52) -> 0
A53: Rent | B53: Barauni 2446 | C53: =VLOOKUP(B53,'Rent Data'!D:I,6,0) -> 2027 | D53: NULL | Q53: =SUM(E53:P53) -> 0 | AD53: =SUM(R53:AC53) -> 0 | AQ53: =SUM(AE53:AP53) -> 0 | AT53: =SUM(AR53:AS53) -> 0
A54: Rent | B54: BARAUNI 2591 | C54: =VLOOKUP(B54,'Rent Data'!D:I,6,0) -> 2027 | D54: NULL | Q54: =SUM(E54:P54) -> 0 | AD54: =SUM(R54:AC54) -> 0 | AQ54: =SUM(AE54:AP54) -> 0 | AT54: =SUM(AR54:AS54) -> 0
A55: Rent | B55: BARAUNI 2592 | C55: =VLOOKUP(B55,'Rent Data'!D:I,6,0) -> 2460 | D55: NULL | Q55: =SUM(E55:P55) -> 0 | AD55: =SUM(R55:AC55) -> 0 | AQ55: =SUM(AE55:AP55) -> 0 | AT55: =SUM(AR55:AS55) -> 0
A56: Rent | B56: BARAUNI 2593 | C56: =VLOOKUP(B56,'Rent Data'!D:I,6,0) -> 2130 | D56: NULL | Q56: =SUM(E56:P56) -> 0 | AD56: =SUM(R56:AC56) -> 0 | AQ56: =SUM(AE56:AP56) -> 0 | AT56: =SUM(AR56:AS56) -> 0
A57: Rent | B57: BASMATH 2867 | C57: =VLOOKUP(B57,'Rent Data'!D:I,6,0) -> 1607 | D57: WH-LE-2867 | O57: 153558 | P57: 202419 | Q57: =SUM(E57:P57) -> 355977 | R57: 202419 | S57: 97945 | T57: 67473 | U57: 67473 | V57: 67473 | AD57: =SUM(R57:AC57) -> 502783 | AQ57: =SUM(AE57:AP57) -> 0 | AT57: =SUM(AR57:AS57) -> 0
A58: Rent | B58: BASTI 3120 | C58: =VLOOKUP(B58,'Rent Data'!D:I,6,0) -> 2000 | D58: WH-LE-3120 | Q58: =SUM(E58:P58) -> 0 | AD58: =SUM(R58:AC58) -> 0 | AE58: 168000 | AF58: 168000 | AG58: 168000 | AH58: 168000 | AI58: 168000 | AJ58: 168000 | AK58: 168000 | AL58: 168000 | AM58: 168000 | AN58: 168000 | AO58: 168000 | AQ58: =SUM(AE58:AP58) -> 1848000 | AT58: =SUM(AR58:AS58) -> 0
A59: Rent | B59: Beed 2293 | C59: =VLOOKUP(B59,'Rent Data'!D:I,6,0) -> 5000 | D59: NULL | Q59: =SUM(E59:P59) -> 0 | AD59: =SUM(R59:AC59) -> 0 | AQ59: =SUM(AE59:AP59) -> 0 | AT59: =SUM(AR59:AS59) -> 0
A60: Rent | B60: BEED 2783 | C60: =VLOOKUP(B60,'Rent Data'!D:I,6,0) -> 5000 | D60: WH-LE-2783 | G60: 18000 | H60: 180000 | I60: 180000 | J60: 180000 | N60: 33871 | O60: 210000 | P60: 210000 | Q60: =SUM(E60:P60) -> 1011871 | R60: 210000 | S60: 210000 | T60: 210000 | U60: 210000 | V60: 189677 | AD60: =SUM(R60:AC60) -> 1029677 | AQ60: =SUM(AE60:AP60) -> 0 | AT60: =SUM(AR60:AS60) -> 0
A61: Rent | B61: BEED 2784 | C61: =VLOOKUP(B61,'Rent Data'!D:I,6,0) -> 3300 | D61: WH-LE-2784 | G61: 11862 | H61: 118620 | I61: 118620 | J61: 106758 | Q61: =SUM(E61:P61) -> 355860 | AD61: =SUM(R61:AC61) -> 0 | AQ61: =SUM(AE61:AP61) -> 0 | AT61: =SUM(AR61:AS61) -> 0
A62: Rent | B62: BEED 2856 | C62: =VLOOKUP(B62,'Rent Data'!D:I,6,0) -> 3333 | D62: WH-LE-2856 | O62: 140000 | P62: 140000 | Q62: =SUM(E62:P62) -> 280000 | R62: 140000 | S62: 140000 | T62: 140000 | U62: 140000 | V62: 135484 | AD62: =SUM(R62:AC62) -> 695484 | AQ62: =SUM(AE62:AP62) -> 0 | AT62: =SUM(AR62:AS62) -> 0
A63: Rent | B63: BEED 2866 | C63: =VLOOKUP(B63,'Rent Data'!D:I,6,0) -> 1261 | D63: WH-LE-2866 | O63: 49166 | P63: 49166 | Q63: =SUM(E63:P63) -> 98332 | R63: 49166 | S63: 49166 | T63: 26222 | AD63: =SUM(R63:AC63) -> 124554 | AQ63: =SUM(AE63:AP63) -> 0 | AT63: =SUM(AR63:AS63) -> 0
A64: Rent | B64: BEGUSARAI 2919 | C64: =VLOOKUP(B64,'Rent Data'!D:I,6,0) -> 3500 | D64: WH-LE-2919 | Q64: =SUM(E64:P64) -> 0 | S64: 231000 | T64: 231000 | U64: 231000 | V64: 231000 | W64: 231000 | X64: 231000 | Y64: 231000 | Z64: 231000 | AA64: 231000 | AD64: =SUM(R64:AC64) -> 2079000 | AQ64: =SUM(AE64:AP64) -> 0 | AT64: =SUM(AR64:AS64) -> 0
A65: Rent | B65: BEGUSARAI 2673 | C65: =VLOOKUP(B65,'Rent Data'!D:I,6,0) -> 2329 | D65: WH-LE-2673 | E65: 396110 | F65: 396110 | G65: 396110 | H65: 396110 | I65: 396110 | J65: 396110 | K65: 396110 | L65: 396110 | M65: 396110 | N65: 153725 | O65: 153725 | Q65: =SUM(E65:P65) -> 3872440 | AD65: =SUM(R65:AC65) -> 0 | AQ65: =SUM(AE65:AP65) -> 0 | AT65: =SUM(AR65:AS65) -> 0
A66: Rent | B66: BEGUSARAI 2674 | C66: =VLOOKUP(B66,'Rent Data'!D:I,6,0) -> 2200 | D66: WH-LE-2674 | E66: 145200 | F66: 145200 | G66: 145200 | H66: 145200 | I66: 145200 | J66: 145200 | K66: 145200 | L66: 145200 | M66: 145200 | N66: 145200 | O66: 145200 | Q66: =SUM(E66:P66) -> 1597200 | AD66: =SUM(R66:AC66) -> 0 | AQ66: =SUM(AE66:AP66) -> 0 | AT66: =SUM(AR66:AS66) -> 0
A67: Rent | B67: BEGUSARAI 2704 | C67: =VLOOKUP(B67,'Rent Data'!D:I,6,0) -> 1156 | D67: WH-LE-2704 | E67: 76285 | F67: 76285 | G67: 76285 | H67: 76285 | I67: 76285 | J67: 76285 | K67: 76285 | L67: 76285 | M67: 76285 | N67: 76285 | O67: 76285 | P67: 76285 | Q67: =SUM(E67:P67) -> 915420 | R67: 83220 | S67: 83220 | T67: 83220 | U67: 83220 | V67: 83220 | W67: 83220 | X67: 83220 | Y67: 83220 | Z67: 83220 | AA67: 83220 | AB67: 83220 | AD67: =SUM(R67:AC67) -> 915420 | AQ67: =SUM(AE67:AP67) -> 0 | AR67: 3005.1667 | AS67: 90155 | AT67: =SUM(AR67:AS67) -> 93160.167
A68: Rent | B68: BEGUSARAI 2705 | C68: =VLOOKUP(B68,'Rent Data'!D:I,6,0) -> 4500 | D68: WH-LE-2705 | E68: 324000 | F68: 324000 | G68: 324000 | H68: 324000 | I68: 324000 | J68: 324000 | K68: 324000 | L68: 324000 | M68: 324000 | N68: 324000 | O68: 324000 | P68: 324000 | Q68: =SUM(E68:P68) -> 3888000 | R68: 324000 | S68: 324000 | T68: 324000 | U68: 324000 | V68: 324000 | W68: 324000 | X68: 324000 | Y68: 324000 | Z68: 324000 | AA68: 324000 | AB68: 138857 | AD68: =SUM(R68:AC68) -> 3378857 | AQ68: =SUM(AE68:AP68) -> 0 | AT68: =SUM(AR68:AS68) -> 0
A69: Rent | B69: BEGUSARAI 2706 | C69: =VLOOKUP(B69,'Rent Data'!D:I,6,0) -> 1625 | D69: WH-LE-2706 | E69: 107261 | F69: 107261 | G69: 107261 | H69: 107261 | I69: 107261 | J69: 107261 | K69: 107261 | L69: 107261 | M69: 107261 | Q69: =SUM(E69:P69) -> 965349 | AD69: =SUM(R69:AC69) -> 0 | AQ69: =SUM(AE69:AP69) -> 0 | AT69: =SUM(AR69:AS69) -> 0
A70: Rent | B70: BEGUSARAI 2707 | C70: =VLOOKUP(B70,'Rent Data'!D:I,6,0) -> 3136 | D70: WH-LE-2707 | E70: 206954 | F70: 206954 | G70: 206954 | H70: 206954 | I70: 206954 | J70: 206954 | K70: 206954 | L70: 206954 | M70: 206954 | N70: 206954 | O70: 206954 | Q70: =SUM(E70:P70) -> 2276494 | AD70: =SUM(R70:AC70) -> 0 | AQ70: =SUM(AE70:AP70) -> 0 | AT70: =SUM(AR70:AS70) -> 0
A71: Rent | B71: BEGUSARAI 2712 | C71: =VLOOKUP(B71,'Rent Data'!D:I,6,0) -> 2933 | D71: WH-LE-2712 | F71: 202400 | G71: 202400 | H71: 202400 | I71: 202400 | J71: 202400 | K71: 202400 | L71: 202400 | M71: 202400 | N71: 202400 | O71: 202400 | Q71: =SUM(E71:P71) -> 2024000 | AD71: =SUM(R71:AC71) -> 0 | AQ71: =SUM(AE71:AP71) -> 0 | AT71: =SUM(AR71:AS71) -> 0
A72: Rent | B72: BEGUSARAI 2929 | C72: =VLOOKUP(B72,'Rent Data'!D:I,6,0) -> 1625 | D72: WH-LE-2929 | Q72: =SUM(E72:P72) -> 0 | R72: 107261 | S72: 107261 | T72: 107261 | U72: 107261 | V72: 107261 | W72: 107261 | X72: 107261 | Y72: 107261 | Z72: 107261 | AA72: 107261 | AB72: 107261 | AC72: 107261 | AD72: =SUM(R72:AC72) -> 1287132 | AQ72: =SUM(AE72:AP72) -> 0 | AT72: =SUM(AR72:AS72) -> 0
A73: Rent | B73: BEGUSARAI 2930 | C73: =VLOOKUP(B73,'Rent Data'!D:I,6,0) -> 2933 | D73: WH-LE-2930 | Q73: =SUM(E73:P73) -> 0 | S73: 208560 | T73: 208560 | U73: 208560 | V73: 208560 | W73: 208560 | X73: 208560 | Y73: 208560 | Z73: 208560 | AA73: 208560 | AD73: =SUM(R73:AC73) -> 1877040 | AQ73: =SUM(AE73:AP73) -> 0 | AT73: =SUM(AR73:AS73) -> 0
A74: Rent | B74: BEGUSARAI 2931 | C74: =VLOOKUP(B74,'Rent Data'!D:I,6,0) -> 2200 | D74: WH-LE-2931 | Q74: =SUM(E74:P74) -> 0 | R74: 392230 | S74: 392230 | T74: 392230 | U74: 392230 | V74: 392230 | W74: 392230 | X74: 392230 | Y74: 392230 | Z74: 392230 | AA74: 392230 | AB74: 240430 | AC74: 240430 | AD74: =SUM(R74:AC74) -> 4403160 | AQ74: =SUM(AE74:AP74) -> 0 | AR74: 5575.2 | AS74: 167256 | AT74: =SUM(AR74:AS74) -> 172831.2
A75: Rent | B75: BEGUSARAI 2933 | C75: =VLOOKUP(B75,'Rent Data'!D:I,6,0) -> 2656 | D75: WH-LE-2933 | Q75: =SUM(E75:P75) -> 0 | S75: 191208 | T75: 191208 | U75: 191208 | V75: 191208 | W75: 191208 | X75: 191208 | Y75: 191208 | Z75: 191208 | AA75: 191208 | AD75: =SUM(R75:AC75) -> 1720872 | AQ75: =SUM(AE75:AP75) -> 0 | AS75: 127472 | AT75: =SUM(AR75:AS75) -> 127472
A76: Rent | B76: BEGUSARAI 2934 | C76: =VLOOKUP(B76,'Rent Data'!D:I,6,0) -> 2043 | D76: WH-LE-2934 | Q76: =SUM(E76:P76) -> 0 | R76: 471576 | S76: 471576 | T76: 471576 | U76: 471576 | V76: 471576 | W76: 471576 | X76: 471576 | Y76: 471576 | Z76: 471576 | AA76: 177456 | AB76: 177456 | AD76: =SUM(R76:AC76) -> 4599096 | AQ76: =SUM(AE76:AP76) -> 0 | AT76: =SUM(AR76:AS76) -> 0
A77: Rent | B77: BEGUSARAI 2946 | C77: =VLOOKUP(B77,'Rent Data'!D:I,6,0) -> 1423 | D77: WH-LE-2946 | Q77: =SUM(E77:P77) -> 0 | R77: 102456 | S77: 102456 | T77: 102456 | U77: 102456 | V77: 102456 | W77: 102456 | X77: 102456 | Y77: 102456 | Z77: 102456 | AA77: 102456 | AB77: 102456 | AD77: =SUM(R77:AC77) -> 1127016 | AQ77: =SUM(AE77:AP77) -> 0 | AT77: =SUM(AR77:AS77) -> 0
A78: Rent | B78: BEGUSARAI 2985 | C78: =VLOOKUP(B78,'Rent Data'!D:I,6,0) -> 2323 | D78: WH-LE-2985 | Q78: =SUM(E78:P78) -> 0 | S78: 79143 | T78: 153340 | U78: 153340 | V78: 153340 | W78: 153340 | X78: 153340 | Y78: -66447.333 | AD78: =SUM(R78:AC78) -> 779395.67 | AQ78: =SUM(AE78:AP78) -> 0 | AT78: =SUM(AR78:AS78) -> 0
A79: Rent | B79: BEGUSARAI 3109 | C79: =VLOOKUP(B79,'Rent Data'!D:I,6,0) -> 3517 | D79: WH-LE-3109 | Q79: =SUM(E79:P79) -> 0 | AD79: =SUM(R79:AC79) -> 0 | AE79: 219440 | AF79: 253200 | AG79: 253200 | AH79: 253200 | AI79: 253200 | AJ79: 253200 | AK79: 253200 | AL79: 253200 | AM79: 253200 | AN79: 253200 | AO79: 253200 | AQ79: =SUM(AE79:AP79) -> 2751440 | AT79: =SUM(AR79:AS79) -> 0
A80: Rent | B80: BEGUSARAI 3158 | C80: =VLOOKUP(B80,'Rent Data'!D:I,6,0) -> 4500 | D80: WH-LE-3158 | Q80: =SUM(E80:P80) -> 0 | AD80: =SUM(R80:AC80) -> 0 | AF80: 351000 | AG80: 351000 | AH80: 351000 | AI80: 351000 | AJ80: 351000 | AK80: 351000 | AL80: 351000 | AM80: 351000 | AN80: 351000 | AQ80: =SUM(AE80:AP80) -> 3159000 | AT80: =SUM(AR80:AS80) -> 0
A81: Rent | B81: BEGUSARAI 3185 | C81: =VLOOKUP(B81,'Rent Data'!D:I,6,0) -> 1642 | D81: WH-LE-3185 | Q81: =SUM(E81:P81) -> 0 | AD81: =SUM(R81:AC81) -> 0 | AJ81: 35460 | AK81: 118200 | AL81: 118200 | AM81: 118200 | AN81: 118200 | AO81: 118200 | AP81: 118200 | AQ81: =SUM(AE81:AP81) -> 744660 | AR81: 118200 | AS81: 118200 | AT81: =SUM(AR81:AS81) -> 236400
A82: Rent | B82: BEGUSARAI 3323 | C82: =VLOOKUP(B82,'Rent Data'!D:I,6,0) -> 1713 | D82: WH-LE-3323 | Q82: =SUM(E82:P82) -> 0 | AD82: =SUM(R82:AC82) -> 0 | AQ82: =SUM(AE82:AP82) -> 0 | AR82: 87610.1 | AS82: 223938 | AT82: =SUM(AR82:AS82) -> 311548.1
A83: Rent | B83: BEGUSARAI 3324 | C83: =VLOOKUP(B83,'Rent Data'!D:I,6,0) -> 2325 | D83: WH-LE-3324 | Q83: =SUM(E83:P83) -> 0 | AD83: =SUM(R83:AC83) -> 0 | AQ83: =SUM(AE83:AP83) -> 0 | AR83: 5115 | AS83: 153450 | AT83: =SUM(AR83:AS83) -> 158565
A84: Rent | B84: Bharatpur 1741 | C84: =VLOOKUP(B84,'Rent Data'!D:I,6,0) -> 3277 | D84: WH-LE-1741 | E84: 98307 | F84: 103220 | G84: 103220 | H84: 103220 | I84: 103220 | J84: 103220 | K84: 103220 | L84: 104203 | M84: 104203 | N84: 104203 | O84: 104203 | P84: 104203 | Q84: =SUM(E84:P84) -> 1238642 | R84: 104203 | S84: 104203 | T84: 104203 | U84: 104203 | V84: 104203 | W84: 104203 | X84: 104203 | Y84: 104203 | Z84: 104203 | AA84: 104203 | AB84: 104203 | AC84: 104203 | AD84: =SUM(R84:AC84) -> 1250436 | AE84: 104203 | AF84: 104203 | AG84: 104203 | AH84: 104203 | AI84: 104203 | AJ84: 104203 | AK84: 104203 | AL84: 104203 | AM84: 104203 | AN84: 104203 | AO84: 104203 | AP84: 104203 | AQ84: =SUM(AE84:AP84) -> 1250436 | AR84: 104203 | AS84: 104203 | AT84: =SUM(AR84:AS84) -> 208406
A85: Rent | B85: Bharatpur 2402 | C85: =VLOOKUP(B85,'Rent Data'!D:I,6,0) -> 3442 | D85: NULL | Q85: =SUM(E85:P85) -> 0 | AD85: =SUM(R85:AC85) -> 0 | AQ85: =SUM(AE85:AP85) -> 0 | AT85: =SUM(AR85:AS85) -> 0
A86: Rent | B86: BHARATPUR 2634 | C86: =VLOOKUP(B86,'Rent Data'!D:I,6,0) -> 4342 | D86: NULL | E86: 153902 | Q86: =SUM(E86:P86) -> 153902 | AD86: =SUM(R86:AC86) -> 0 | AQ86: =SUM(AE86:AP86) -> 0 | AT86: =SUM(AR86:AS86) -> 0
A87: Rent | B87: BHARATPUR 2638 | C87: =VLOOKUP(B87,'Rent Data'!D:I,6,0) -> 1958 | D87: WH-LE-2638 | E87: 70500 | F87: 70500 | G87: 70500 | H87: 70500 | Q87: =SUM(E87:P87) -> 282000 | AD87: =SUM(R87:AC87) -> 0 | AQ87: =SUM(AE87:AP87) -> 0 | AT87: =SUM(AR87:AS87) -> 0
A88: Rent | B88: BHARATPUR 2643 | C88: =VLOOKUP(B88,'Rent Data'!D:I,6,0) -> 5707 | D88: WH-LE-2643 | E88: 222554 | F88: 222554 | G88: 222554 | Q88: =SUM(E88:P88) -> 667662 | AD88: =SUM(R88:AC88) -> 0 | AQ88: =SUM(AE88:AP88) -> 0 | AT88: =SUM(AR88:AS88) -> 0
A89: Rent | B89: BHARATPUR 2789 | C89: =VLOOKUP(B89,'Rent Data'!D:I,6,0) -> 4338 | D89: WH-LE-2789 | Q89: =SUM(E89:P89) -> 0 | X89: 182200 | Y89: 182200 | Z89: 182200 | AA89: 182200 | AB89: 182200 | AC89: 182200 | AD89: =SUM(R89:AC89) -> 1093200 | AE89: 182200 | AF89: 182200 | AG89: 182200 | AH89: 182200 | AI89: 182200 | AJ89: 182200 | AK89: 182200 | AL89: 182200 | AM89: 182200 | AN89: 182200 | AO89: 182200 | AP89: 182200 | AQ89: =SUM(AE89:AP89) -> 2186400 | AR89: 182200 | AS89: 182200 | AT89: =SUM(AR89:AS89) -> 364400
A90: Rent | B90: BHARATPUR 2790 | C90: =VLOOKUP(B90,'Rent Data'!D:I,6,0) -> 2275 | D90: WH-LE-2790 | K90: 88725 | L90: 88725 | M90: 88725 | N90: 88725 | O90: 88725 | P90: 88725 | Q90: =SUM(E90:P90) -> 532350 | R90: 88725 | S90: 88725 | T90: 88725 | U90: 88725 | V90: 88725 | W90: 88725 | X90: 88725 | Y90: 88725 | Z90: 88725 | AA90: 88725 | AB90: 88725 | AC90: 88725 | AD90: =SUM(R90:AC90) -> 1064700 | AE90: 88725 | AF90: 88725 | AG90: 88725 | AH90: 88725 | AI90: 88725 | AJ90: 88725 | AK90: 88725 | AQ90: =SUM(AE90:AP90) -> 621075 | AT90: =SUM(AR90:AS90) -> 0
A91: Rent | B91: Bharatpur 400 | C91: =VLOOKUP(B91,'Rent Data'!D:I,6,0) -> 1958 | D91: NULL | Q91: =SUM(E91:P91) -> 0 | AD91: =SUM(R91:AC91) -> 0 | AQ91: =SUM(AE91:AP91) -> 0 | AT91: =SUM(AR91:AS91) -> 0
A92: Rent | B92: BHAWANIPATNA 2502 | C92: =VLOOKUP(B92,'Rent Data'!D:I,6,0) -> 1700 | D92: NULL | Q92: =SUM(E92:P92) -> 0 | AD92: =SUM(R92:AC92) -> 0 | AQ92: =SUM(AE92:AP92) -> 0 | AT92: =SUM(AR92:AS92) -> 0
A93: Rent | B93: BHOJPUR 3217 | C93: =VLOOKUP(B93,'Rent Data'!D:I,6,0) -> 1649 | D93: WH-LE-3217 | Q93: =SUM(E93:P93) -> 0 | AD93: =SUM(R93:AC93) -> 0 | AM93: 45480 | AN93: 93993 | AO93: 53710 | AQ93: =SUM(AE93:AP93) -> 193183 | AT93: =SUM(AR93:AS93) -> 0
A94: Rent | B94: Bihta 2079 | C94: =VLOOKUP(B94,'Rent Data'!D:I,6,0) -> 4480 | D94: NULL | Q94: =SUM(E94:P94) -> 0 | AD94: =SUM(R94:AC94) -> 0 | AQ94: =SUM(AE94:AP94) -> 0 | AT94: =SUM(AR94:AS94) -> 0
A95: Rent | B95: BODWAD 3020 | C95: =VLOOKUP(B95,'Rent Data'!D:I,6,0) -> 1733 | D95: WH-LE-3020 | Q95: =SUM(E95:P95) -> 0 | Y95: 90594 | Z95: 90594 | AA95: 90594 | AB95: 90594 | AC95: 90594 | AD95: =SUM(R95:AC95) -> 452970 | AQ95: =SUM(AE95:AP95) -> 0 | AR95: 2253.3333 | AS95: 67600 | AT95: =SUM(AR95:AS95) -> 69853.333
A96: Rent | B96: BODWAD 3021 | C96: =VLOOKUP(B96,'Rent Data'!D:I,6,0) -> 1008 | D96: WH-LE-3021 | Q96: =SUM(E96:P96) -> 0 | Y96: 42329 | Z96: 42329 | AA96: 42329 | AB96: 42329 | AC96: 42329 | AD96: =SUM(R96:AC96) -> 211645 | AE96: 42329 | AF96: 42329 | AG96: 42329 | AH96: 13655 | AQ96: =SUM(AE96:AP96) -> 140642 | AS96: 40222.097 | AT96: =SUM(AR96:AS96) -> 40222.097
A97: Rent | B97: BODWAD 3039 | C97: =VLOOKUP(B97,'Rent Data'!D:I,6,0) -> 833 | D97: WH-LE-3039 | Q97: =SUM(E97:P97) -> 0 | Y97: 24500 | Z97: 35000 | AA97: 35000 | AB97: 35000 | AC97: 35000 | AD97: =SUM(R97:AC97) -> 164500 | AE97: 35000 | AF97: 58710 | AG97: 70000 | AH97: 35000 | AQ97: =SUM(AE97:AP97) -> 198710 | AT97: =SUM(AR97:AS97) -> 0
A98: Rent | B98: BODWAD 3125 | C98: =VLOOKUP(B98,'Rent Data'!D:I,6,0) -> 2600 | D98: WH-LE-3125 | Q98: =SUM(E98:P98) -> 0 | AD98: =SUM(R98:AC98) -> 0 | AE98: 36400 | AF98: 109200 | AG98: 109200 | AH98: 70452 | AQ98: =SUM(AE98:AP98) -> 325252 | AT98: =SUM(AR98:AS98) -> 0
A99: Rent | B99: BODWAD 3199 | C99: =VLOOKUP(B99,'Rent Data'!D:I,6,0) -> 2600 | D99: WH-LE-3199 | Q99: =SUM(E99:P99) -> 0 | AD99: =SUM(R99:AC99) -> 0 | AL99: 58240 | AM99: 109200 | AN99: 109200 | AO99: 109200 | AP99: 109200 | AQ99: =SUM(AE99:AP99) -> 495040 | AR99: 109200 | AS99: 109200 | AT99: =SUM(AR99:AS99) -> 218400
A100: Rent | B100: BODWAD 3333 | C100: =VLOOKUP(B100,'Rent Data'!D:I,6,0) -> 1967 | D100: WH-LE-3333 | Q100: =SUM(E100:P100) -> 0 | AD100: =SUM(R100:AC100) -> 0 | AQ100: =SUM(AE100:AP100) -> 0 | AR100: 2360 | AS100: 70800 | AT100: =SUM(AR100:AS100) -> 73160
...

Sheet Rent Data
I1: 4015718 | J1: 16130964 | K1: 19251206 | L1: 19044554 | M1: 18447104 | N1: 18370198 | O1: 17577005 | P1: 17550465 | Q1: 17788476 | R1: 18261128 | S1: 14723230 | T1: 14004904 | U1: 14212569 | V1: 14513797 | W1: 19457981 | X1: 19644394 | Y1: 18989995 | Z1: 18536484 | AA1: 17730112 | AB1: 18055737 | AC1: 18154343 | AD1: 17779994 | AE1: 18764053 | AF1: 18158619 | AG1: 17776594 | AH1: 22596804 | AI1: 27766948 | AJ1: 28373833 | AK1: 28073470 | AL1: 27123605 | AM1: 26678379 | AN1: 26443496 | AO1: 25400646 | AP1: 25936637 | AQ1: 26298035 | AR1: 28555547 | AS1: 30241363 | AT1: 34328334 | AU1: 45450847 | AV1: 45901249 | AW1: 45082081 | AX1: 43103628 | AY1: 40676904 | AZ1: 37638459 | BA1: 36519093 | BB1: 34725245 | BC1: 31964049 | BD1: 30792238 | BE1: 29719305 | BF1: 33515822 | BG1: 41093928 | BH1: 40893364 | BI1: 40193164 | BJ1: 40063430 | BK1: 39008234 | BL1: 37393064 | BM1: 36901047 | BN1: 37370970 | BO1: 38368850 | BP1: 36460629 | BQ1: 35106417 | BR1: 36646282 | BS1: 46833759 | BT1: 48486278 | BU1: =SUBTOTAL(9,BU3:BU1048576) -> 2.053618e+08 | BV1: =SUBTOTAL(9,BV3:BV1048576) -> 2.175621e+08 | BW1: =SUBTOTAL(9,BW3:BW1048576) -> 3.2348876e+08 | BX1: =SUBTOTAL(9,BX3:BX1048576) -> 4.5590143e+08 | BY1: =SUBTOTAL(9,BY3:BY1048576) -> 4.5636892e+08 | BZ1: =SUBTOTAL(9,BZ3:BZ1048576) -> 1.3196632e+08
A2: Godown ID | B2: State Name | C2: Location Name | D2: CMP Name | E2: Godown No | F2: Address | G2: Start Date | H2: Close Date | I2: Godown Capacity | J2: Apr-2021 | K2: May-2021 | L2: Jun-2021 | M2: Jul-2021 | N2: Aug-2021 | O2: Sep-2021 | P2: Oct-2021 | Q2: Nov-2021 | R2: Dec-2021 | S2: Jan-2022 | T2: Feb-2022 | U2: Mar-2022 | V2: Apr-2022 | W2: May-2022 | X2: Jun-2022 | Y2: Jul-2022 | Z2: Aug-2022 | AA2: Sep-2022 | AB2: Oct-2022 | AC2: Nov-2022 | AD2: Dec-2022 | AE2: Jan-2023 | AF2: Feb-2023 | AG2: Mar-2023 | AH2: Apr-2023 | AI2: May-2023 | AJ2: Jun-2023 | AK2: Jul-2023 | AL2: Aug-2023 | AM2: Sep-2023 | AN2: Oct-2023 | AO2: Nov-2023 | AP2: Dec-2023 | AQ2: Jan-2024 | AR2: Feb-2024 | AS2: Mar-2024 | AT2: Apr-2024 | AU2: May-2024 | AV2: Jun-2024 | AW2: Jul-2024 | AX2: Aug-2024 | AY2: Sep-2024 | AZ2: Oct-2024 | BA2: Nov-2024 | BB2: Dec-2024 | BC2: Jan-2025 | BD2: Feb-2025 | BE2: Mar-2025 | BF2: Apr-2025 | BG2: May-2025 | BH2: Jun-2025 | BI2: Jul-2025 | BJ2: Aug-2025 | BK2: Sep-2025 | BL2: Oct-2025 | BM2: Nov-2025 | BN2: Dec-2025 | BO2: Jan-2026 | BP2: Feb-2026 | BQ2: Mar-2026 | BR2: Apr-2026 | BS2: May-2026 | BT2: Jun-2026 | BU2: FY 21-22 | BV2: FY 22-23 | BW2: FY 23-24 | BX2: FY 24-25 | BY2: FY 25-26 | BZ2: FY 26-27
A3: 6772 | B3: Andhra Pradesh - South coastal | C3: Atmakur | D3: ATMAKUR 2964 | E3: A | F3: K STAR RURAL FARMERS WAREHOUSE,GODOWN NO-A,SY NO 23/4,KARIVENA(V),ATMAKUR(M),KURNOOL-DIST,ANDHRA PRADESH-518422 | G3: 25-Apr-2024 | H3: 31-Aug-2024 | I3: 1605 | AU3: 52965 | AV3: 52965 | AW3: 52965 | AX3: 52965 | BU3: =SUM(J3:U3) -> 0 | BV3: =SUM(V3:AG3) -> 0 | BW3: =SUM(AH3:AS3) -> 0 | BX3: =SUM(AT3:BE3) -> 211860 | BY3: =SUM(BF3:BQ3) -> 0 | BZ3: =SUM(BR3:BT3) -> 0 | CA3: =BV3/BU3 -> #DIV/0!
A4: 6773 | B4: Andhra Pradesh - South coastal | C4: Atmakur | D4: ATMAKUR 2964 | E4: B | F4: K STAR RURAL FARMERS WAREHOUSE,GODOWN NO-B,SY NO 23/4,KARIVENA(V),ATMAKUR(M),KURNOOL-DIST,ANDHRA PRADESH-518422 | G4: 25-Apr-2024 | H4: 31-Aug-2024 | I4: 1605 | AU4: 52965 | AV4: 52965 | AW4: 52965 | AX4: 52965 | BU4: =SUM(J4:U4) -> 0 | BV4: =SUM(V4:AG4) -> 0 | BW4: =SUM(AH4:AS4) -> 0 | BX4: =SUM(AT4:BE4) -> 211860 | BY4: =SUM(BF4:BQ4) -> 0 | BZ4: =SUM(BR4:BT4) -> 0 | CA4: =BV4/BU4 -> #DIV/0!
A5: 6774 | B5: Andhra Pradesh - South coastal | C5: Atmakur | D5: ATMAKUR 2964 | E5: C | F5: K STAR RURAL FARMERS WAREHOUSE,GODOWN NO-C,SY NO 23/4,KARIVENA(V),ATMAKUR(M),KURNOOL-DIST,ANDHRA PRADESH-518422 | G5: 25-Apr-2024 | H5: 31-Aug-2024 | I5: 1605 | AU5: 52965 | AV5: 52965 | AW5: 52965 | AX5: 52965 | BU5: =SUM(J5:U5) -> 0 | BV5: =SUM(V5:AG5) -> 0 | BW5: =SUM(AH5:AS5) -> 0 | BX5: =SUM(AT5:BE5) -> 211860 | BY5: =SUM(BF5:BQ5) -> 0 | BZ5: =SUM(BR5:BT5) -> 0 | CA5: =BV5/BU5 -> #DIV/0!
A6: 7420 | B6: Andhra Pradesh - South coastal | C6: ETUKURU | D6: ETUKURU 3334 | E6: 1 | F6: ANJANI COTTON PVT LTD, GODOWN NO. 1, D NO. 8/215/4, ANANTHAVARAPADU ROAD, ETUKURU - VILLAGE, GUNTUR, ANDHRA PRADESH - 522017 | G6: 24-Apr-2026 | I6: 1917 | BR6: 4791.6667 | BS6: 143750 | BT6: 143750 | BU6: =SUM(J6:U6) -> 0 | BV6: =SUM(V6:AG6) -> 0 | BW6: =SUM(AH6:AS6) -> 0 | BX6: =SUM(AT6:BE6) -> 0 | BY6: =SUM(BF6:BQ6) -> 0 | BZ6: =SUM(BR6:BT6) -> 292291.67 | CA6: =BV6/BU6 -> #DIV/0!
A7: 7395 | B7: Andhra Pradesh - South coastal | C7: GANAPAVARAM | D7: GANAPAVARAM 3317 | E7: 2 | F7: TIRUMALA TURBO LUBES PRIVATE LIMITED GODOWN NO - 2, D.NO - 354, GANAPAVARAM VILLAGE, NADENDLA MANDAL, PALNADU - DIST, ANDHRA PRADESH - 522619 | G7: 15-Apr-2026 | I7: 2000 | BR7: 44800 | BS7: 84000 | BT7: 84000 | BU7: =SUM(J7:U7) -> 0 | BV7: =SUM(V7:AG7) -> 0 | BW7: =SUM(AH7:AS7) -> 0 | BX7: =SUM(AT7:BE7) -> 0 | BY7: =SUM(BF7:BQ7) -> 0 | BZ7: =SUM(BR7:BT7) -> 212800 | CA7: =BV7/BU7 -> #DIV/0!
A8: 4876 | B8: Andhra Pradesh - South coastal | C8: Guntur | D8: Guntur 1872 | E8: 2 | F8: RAMYA COLD STORAGE PVT LTD Lalpuram (village), By-Pass, D.NO:558, Guntur (Rural Mandal), Guntur (Dist), PIN:522005, A.P | G8: 27-Apr-2018 | I8: 1800 | BU8: =SUM(J8:U8) -> 0 | BV8: =SUM(V8:AG8) -> 0 | BW8: =SUM(AH8:AS8) -> 0 | BX8: =SUM(AT8:BE8) -> 0 | BY8: =SUM(BF8:BQ8) -> 0 | BZ8: =SUM(BR8:BT8) -> 0 | CA8: =BV8/BU8 -> #DIV/0!
A9: 4987 | B9: Andhra Pradesh - South coastal | C9: Guntur | D9: Guntur 1936 | E9: 1 | F9: JAYSAM ESTATES, D.No.9-354, Pulladigunta, Vatticherukuru (Mandal), Guntur District, Pin.522017, A.P. | G9: 22-Oct-2018 | I9: 1109 | BU9: =SUM(J9:U9) -> 0 | BV9: =SUM(V9:AG9) -> 0 | BW9: =SUM(AH9:AS9) -> 0 | BX9: =SUM(AT9:BE9) -> 0 | BY9: =SUM(BF9:BQ9) -> 0 | BZ9: =SUM(BR9:BT9) -> 0 | CA9: =BV9/BU9 -> #DIV/0!
A10: 5012 | B10: Andhra Pradesh - South coastal | C10: Guntur | D10: Guntur 1936 | E10: 2 | F10: JAYSAM ESTATES, D.No.9-355, Pulladigunta, Vatticherukuru (Mandal), Guntur District, Pin.522017, A.P. | G10: 15-Nov-2018 | I10: 2198 | BU10: =SUM(J10:U10) -> 0 | BV10: =SUM(V10:AG10) -> 0 | BW10: =SUM(AH10:AS10) -> 0 | BX10: =SUM(AT10:BE10) -> 0 | BY10: =SUM(BF10:BQ10) -> 0 | BZ10: =SUM(BR10:BT10) -> 0 | CA10: =BV10/BU10 -> #DIV/0!
A11: 5048 | B11: Andhra Pradesh - South coastal | C11: Guntur | D11: Guntur 1936 | E11: 3 | F11: JAYSAM ESTATES, D.NO:9-354, Pulladigunta, Vatticherukuru(Mandal), Guntur(District), PIN:522017, A.P. | G11: 15-Dec-2018 | I11: 576 | BU11: =SUM(J11:U11) -> 0 | BV11: =SUM(V11:AG11) -> 0 | BW11: =SUM(AH11:AS11) -> 0 | BX11: =SUM(AT11:BE11) -> 0 | BY11: =SUM(BF11:BQ11) -> 0 | BZ11: =SUM(BR11:BT11) -> 0 | CA11: =BV11/BU11 -> #DIV/0!
A12: 7338 | B12: Andhra Pradesh - South coastal | C12: KALUGOTLAPALLE | D12: KALUGOTLAPALLE 3285 | E12: A | F12: UTTEJITHA RURAL WAREHOUSE GODOWN NO - A , SURVEY NO - 271/2, 273/2B, KALUGOTLAPALLE PANCHAYATI, CHAGALAMARRI MANDAL, NANDYAL - DISTRICT, ANDHRA PRADESH - 518501 | G12: 05-Apr-2026 | I12: 2640 | BR12: 3168 | BS12: 95040 | BT12: 95040 | BU12: =SUM(J12:U12) -> 0 | BV12: =SUM(V12:AG12) -> 0 | BW12: =SUM(AH12:AS12) -> 0 | BX12: =SUM(AT12:BE12) -> 0 | BY12: =SUM(BF12:BQ12) -> 0 | BZ12: =SUM(BR12:BT12) -> 193248 | CA12: =BV12/BU12 -> #DIV/0!
A13: 7339 | B13: Andhra Pradesh - South coastal | C13: KALUGOTLAPALLE | D13: KALUGOTLAPALLE 3285 | E13: B | F13: UTTEJITHA RURAL WAREHOUSE GODOWN NO - B , SURVEY NO - 271/2, 273/2B, KALUGOTLAPALLE PANCHAYATI, CHAGALAMARRI MANDAL, NANDYAL - DISTRICT, ANDHRA PRADESH - 518501 | G13: 08-Apr-2026 | I13: 2640 | BR13: 3168 | BS13: 95040 | BT13: 95040 | BU13: =SUM(J13:U13) -> 0 | BV13: =SUM(V13:AG13) -> 0 | BW13: =SUM(AH13:AS13) -> 0 | BX13: =SUM(AT13:BE13) -> 0 | BY13: =SUM(BF13:BQ13) -> 0 | BZ13: =SUM(BR13:BT13) -> 193248 | CA13: =BV13/BU13 -> #DIV/0!
A14: 7398 | B14: Andhra Pradesh - South coastal | C14: KURNUTHALA | D14: KURNUTHALA 3329 | E14: 1 | F14: UPPUTURI SAMBASIVARAO AGRI GODOWN NO -1, D.NO - 3-53, KURNUTHALA - VILLAGE, VATTICHERUKURU MANDAL, GUNTUR - DIST, ANDHRA PRADESH - 522017 | G14: 22-Apr-2026 | I14: 1655 | BR14: 3309.3333 | BS14: 99280 | BT14: 99280 | BU14: =SUM(J14:U14) -> 0 | BV14: =SUM(V14:AG14) -> 0 | BW14: =SUM(AH14:AS14) -> 0 | BX14: =SUM(AT14:BE14) -> 0 | BY14: =SUM(BF14:BQ14) -> 0 | BZ14: =SUM(BR14:BT14) -> 201869.33 | CA14: =BV14/BU14 -> #DIV/0!
A15: 7385 | B15: Andhra Pradesh - South coastal | C15: PEDAGADELAVARRU | D15: PEDAGADELAVARRU 3297 | E15: 1 | F15: INAMPUDI SUDHARANI GODOWN NO. 1, SURVEY NO - 394-1, PEDAGADELAVARRU VILLAGE, CHINAGADELAVARRU (POST), TSUNDUR MANDAL, BAPATLA DT, ANDHRA PRADESH - 522313 | G15: 10-Apr-2026 | I15: 1667 | BR15: 61250 | BS15: 87500 | BT15: 87500 | BU15: =SUM(J15:U15) -> 0 | BV15: =SUM(V15:AG15) -> 0 | BW15: =SUM(AH15:AS15) -> 0 | BX15: =SUM(AT15:BE15) -> 0 | BY15: =SUM(BF15:BQ15) -> 0 | BZ15: =SUM(BR15:BT15) -> 236250 | CA15: =BV15/BU15 -> #DIV/0!
A16: 7342 | B16: Andhra Pradesh - South coastal | C16: PRATHIPADU | D16: PRATHIPADU 3290 | E16: 1 | F16: SRI BHARATH FERTILISERS GODOWN NO - 1, D.N - 1 - 185, SURVEY NO - 818, MAIN ROAD PRATHIPADU VILLAGE & MANDAL, GUNTUR DIST, ANDHRA PRADESH - 522019 | G16: 10-Apr-2026 | I16: 4889 | BR16: 205338 | BS16: 293340 | BT16: 293340 | BU16: =SUM(J16:U16) -> 0 | BV16: =SUM(V16:AG16) -> 0 | BW16: =SUM(AH16:AS16) -> 0 | BX16: =SUM(AT16:BE16) -> 0 | BY16: =SUM(BF16:BQ16) -> 0 | BZ16: =SUM(BR16:BT16) -> 792018 | CA16: =BV16/BU16 -> #DIV/0!
A17: 6734 | B17: Andhra Pradesh - South coastal | C17: THAMMAVARAM | D17: THAMMAVARAM 2957 | E17: 6A | F17: ONGOLE LOGISTICS PRIVATE LIMITED GODOWNS,GODOWN NO-6A,SURVEY NO 163/1A,163/1C,163/3,164/1A,165,169/1,BODDUVANIPALEM SIVARU ,THAMMAVARAM VILLAGE,KORISAPADU MANADAL,PRAKASAM DT,ANDHRA PRADESH-523212 | G17: 20-Apr-2024 | H17: 19-Mar-2025 | I17: 2500 | AT17: 44000 | AU17: 120000 | AV17: 120000 | AW17: 120000 | AX17: 120000 | AY17: 120000 | AZ17: 120000 | BA17: 120000 | BB17: 120000 | BC17: 120000 | BD17: 120000 | BE17: -65806.452 | BU17: =SUM(J17:U17) -> 0 | BV17: =SUM(V17:AG17) -> 0 | BW17: =SUM(AH17:AS17) -> 0 | BX17: =SUM(AT17:BE17) -> 1178193.5 | BY17: =SUM(BF17:BQ17) -> 0 | BZ17: =SUM(BR17:BT17) -> 0 | CA17: =BV17/BU17 -> #DIV/0!
A18: 6735 | B18: Andhra Pradesh - South coastal | C18: THAMMAVARAM | D18: THAMMAVARAM 2957 | E18: 6B | F18: ONGOLE LOGISTICS PRIVATE LIMITED GODOWNS,GODOWN NO-6B,SURVEY NO 163/1A,163/1C,163/3,164/1A,165,169/1,BODDUVANIPALEM SIVARU ,THAMMAVARAM VILLAGE,KORISAPADU MANADAL,PRAKASAM DT,ANDHRA PRADESH-523212 | G18: 20-Apr-2024 | H18: 19-Mar-2025 | I18: 2500 | AT18: 44000 | AU18: 120000 | AV18: 120000 | AW18: 120000 | AX18: 120000 | AY18: 120000 | AZ18: 120000 | BA18: 120000 | BB18: 120000 | BC18: 120000 | BD18: 120000 | BE18: -65806.452 | BU18: =SUM(J18:U18) -> 0 | BV18: =SUM(V18:AG18) -> 0 | BW18: =SUM(AH18:AS18) -> 0 | BX18: =SUM(AT18:BE18) -> 1178193.5 | BY18: =SUM(BF18:BQ18) -> 0 | BZ18: =SUM(BR18:BT18) -> 0 | CA18: =BV18/BU18 -> #DIV/0!
A19: 7387 | B19: Andhra Pradesh - South coastal | C19: VADLAMUDI | D19: VADLAMUDI 3275 | E19: 3 | F19: K MOHANARAO ESTATES PRIVATE LIMITED WAREHOUSE, GODOWN NO. 3, D.NO. 10 - 280, GUNTUR TENALI ROAD, VADLAMUDI VILLAGE, CHEBROLE MANDAL, GUNTUR DT, ANDHRA PRADESH - 522213 | G19: 01-Apr-2026 | I19: 750 | BR19: 39358 | BS19: 39358 | BT19: 39358 | BU19: =SUM(J19:U19) -> 0 | BV19: =SUM(V19:AG19) -> 0 | BW19: =SUM(AH19:AS19) -> 0 | BX19: =SUM(AT19:BE19) -> 0 | BY19: =SUM(BF19:BQ19) -> 0 | BZ19: =SUM(BR19:BT19) -> 118074 | CA19: =BV19/BU19 -> #DIV/0!
A20: 7388 | B20: Andhra Pradesh - South coastal | C20: VADLAMUDI | D20: VADLAMUDI 3275 | E20: 4 | F20: K MOHANARAO ESTATES PRIVATE LIMITED WAREHOUSE, GODOWN NO. 4, D.NO. 10 - 280, GUNTUR TENALI ROAD, VADLAMUDI VILLAGE, CHEBROLE MANDAL, GUNTUR DT, ANDHRA PRADESH - 522213 | G20: 01-Apr-2026 | I20: 1878 | BR20: 98595 | BS20: 98595 | BT20: 98595 | BU20: =SUM(J20:U20) -> 0 | BV20: =SUM(V20:AG20) -> 0 | BW20: =SUM(AH20:AS20) -> 0 | BX20: =SUM(AT20:BE20) -> 0 | BY20: =SUM(BF20:BQ20) -> 0 | BZ20: =SUM(BR20:BT20) -> 295785 | CA20: =BV20/BU20 -> #DIV/0!
A21: 7386 | B21: Andhra Pradesh - South coastal | C21: VADLAMUDI | D21: VADLAMUDI 3275 | E21: 5 | F21: K MOHANARAO ESTATES PRIVATE LIMITED WAREHOUSE, GODOWN NO. 5, D.NO. 10 - 280, GUNTUR TENALI ROAD, VADLAMUDI VILLAGE, CHEBROLE MANDAL, GUNTUR DT, ANDHRA PRADESH - 522213 | G21: 01-Apr-2026 | I21: 512 | BR21: 26898 | BS21: 26898 | BT21: 26898 | BU21: =SUM(J21:U21) -> 0 | BV21: =SUM(V21:AG21) -> 0 | BW21: =SUM(AH21:AS21) -> 0 | BX21: =SUM(AT21:BE21) -> 0 | BY21: =SUM(BF21:BQ21) -> 0 | BZ21: =SUM(BR21:BT21) -> 80694 | CA21: =BV21/BU21 -> #DIV/0!
A22: 7222 | B22: Andhra Pradesh -North coastal | C22: Balabhadrapuram | D22: BALABHADRAPURAM 3220 | E22: 2A | F22: YAMANA SANTHA KUMARI WAREHOUSE GODOWN NO - 2A, S NO 63 AND 64, DOOR NO 10-149, SRI VIAJAYA DURGA FOOD STORAGES, BALABHADR PURAM VILLAGE, BIKKAVOLU MANDAL, BALABHADRAPURAM B.O, EAST GODAVARI, ANDHRA PRADESH - 533343 | G22: 02-Jan-2026 | I22: 4108 | BO22: 35775 | BP22: 36968 | BQ22: 36968 | BR22: 36968 | BS22: 36968 | BT22: 36968 | BU22: =SUM(J22:U22) -> 0 | BV22: =SUM(V22:AG22) -> 0 | BW22: =SUM(AH22:AS22) -> 0 | BX22: =SUM(AT22:BE22) -> 0 | BY22: =SUM(BF22:BQ22) -> 109711 | BZ22: =SUM(BR22:BT22) -> 110904 | CA22: =BV22/BU22 -> #DIV/0!
A23: 7223 | B23: Andhra Pradesh -North coastal | C23: Balabhadrapuram | D23: BALABHADRAPURAM 3220 | E23: 2B | F23: YAMANA SANTHA KUMARI WAREHOUSE GODOWN NO - 2B, S NO 63 AND 64, DOOR NO 10-149, SRI VIAJAYA DURGA FOOD STORAGES, BALABHADR PURAM VILLAGE, BIKKAVOLU MANDAL, BALABHADRAPURAM B.O, EAST GODAVARI, ANDHRA PRADESH - 533343 | G23: 05-Jan-2026 | I23: 2713 | BO23: 21263 | BP23: 24413 | BQ23: 24413 | BR23: 24413 | BS23: 24413 | BT23: 24413 | BU23: =SUM(J23:U23) -> 0 | BV23: =SUM(V23:AG23) -> 0 | BW23: =SUM(AH23:AS23) -> 0 | BX23: =SUM(AT23:BE23) -> 0 | BY23: =SUM(BF23:BQ23) -> 70089 | BZ23: =SUM(BR23:BT23) -> 73239 | CA23: =BV23/BU23 -> #DIV/0!
A24: 7224 | B24: Andhra Pradesh -North coastal | C24: Balabhadrapuram | D24: BALABHADRAPURAM 3220 | E24: 2C | F24: YAMANA SANTHA KUMARI WAREHOUSE GODOWN NO - 2C, S NO 63 AND 64, DOOR NO 10-149, SRI VIAJAYA DURGA FOOD STORAGES, BALABHADR PURAM VILLAGE, BIKKAVOLU MANDAL, BALABHADRAPURAM B.O, EAST GODAVARI, ANDHRA PRADESH - 533343 | G24: 08-Jan-2026 | I24: 2713 | BO24: 18900 | BP24: 24413 | BQ24: 24413 | BR24: 24413 | BS24: 24413 | BT24: 24413 | BU24: =SUM(J24:U24) -> 0 | BV24: =SUM(V24:AG24) -> 0 | BW24: =SUM(AH24:AS24) -> 0 | BX24: =SUM(AT24:BE24) -> 0 | BY24: =SUM(BF24:BQ24) -> 67726 | BZ24: =SUM(BR24:BT24) -> 73239 | CA24: =BV24/BU24 -> #DIV/0!
A25: 7221 | B25: Andhra Pradesh -North coastal | C25: Balabhadrapuram | D25: BALABHADRAPURAM 3220 | E25: 3C | F25: YAMANA SANTHA KUMARI WAREHOUSE GODOWN NO - 3C, S NO 63 AND 64, DOOR NO 10-151, SRI VIAJAYA DURGA FOOD STORAGES, BALABHADR PURAM VILLAGE, BIKKAVOLU MANDAL, BALABHADRAPURAM B.O, EAST GODAVARI, ANDHRA PRADESH - 533343 | G25: 22-Dec-2025 | I25: 2713 | BN25: 7875 | BO25: 24413 | BP25: 24413 | BQ25: 24413 | BR25: 24413 | BS25: 24413 | BT25: 24413 | BU25: =SUM(J25:U25) -> 0 | BV25: =SUM(V25:AG25) -> 0 | BW25: =SUM(AH25:AS25) -> 0 | BX25: =SUM(AT25:BE25) -> 0 | BY25: =SUM(BF25:BQ25) -> 81114 | BZ25: =SUM(BR25:BT25) -> 73239 | CA25: =BV25/BU25 -> #DIV/0!
A26: 7356 | B26: Andhra Pradesh -North coastal | C26: Gavaravaram | D26: GAVARAVARAM 3304 | E26: 2 | F26: SRI SATYANARAYANA PADDY BOILED UNIT GODOWN NO. 2, DOOR NO. 6-36, R.S.NO - 76/3, NEAR MNR WEIGHBRIDGE, NALLAJARLA ROAD, GAVARAVARAM VILLAGE, KOYYALAGUDEM MANDAL, ELURU - DISTT, AP - 534312 | G26: 13-Apr-2026 | I26: 2408 | BR26: 3371.6667 | BS26: 101150 | BT26: 101150 | BU26: =SUM(J26:U26) -> 0 | BV26: =SUM(V26:AG26) -> 0 | BW26: =SUM(AH26:AS26) -> 0 | BX26: =SUM(AT26:BE26) -> 0 | BY26: =SUM(BF26:BQ26) -> 0 | BZ26: =SUM(BR26:BT26) -> 205671.67 | CA26: =BV26/BU26 -> #DIV/0!
A27: 6693 | B27: Andhra Pradesh -North coastal | C27: VIZIANAGARAM | D27: VIZIANAGARAM 2922 | E27: 2 | F27: PYDA SWAPNA WH, GODOWN NO 2, SURVEY NO 54/1, 54/2, 54/3, BOBBILI ROAD, GOTLAM(V) BONDAPALLI(M) VIZIANAGARAM ANDHRA PRADESH - 535003. | G27: 15-Apr-2024 | H27: 05-Aug-2024 | I27: 4170 | AT27: 66667 | AU27: 125000 | AV27: 125000 | AW27: 125000 | AX27: 4032 | BU27: =SUM(J27:U27) -> 0 | BV27: =SUM(V27:AG27) -> 0 | BW27: =SUM(AH27:AS27) -> 0 | BX27: =SUM(AT27:BE27) -> 445699 | BY27: =SUM(BF27:BQ27) -> 0 | BZ27: =SUM(BR27:BT27) -> 0 | CA27: =BV27/BU27 -> #DIV/0!
A28: 6793 | B28: Assam | C28: Guwahati | D28: GUWAHATI 2947 | E28: 1 | F28: SAKET KUMAR JAIN WH,GODOWN NO 1, DAG NO:241, PATTA NO: 612, REVENUE VILL: 3 NO, MOUZA- RAMPUR, DISTT: KAMRUP, ASSAM PIN: 781001, STATE : ASSAM | G28: 15-May-2024 | H28: 31-Jan-2025 | I28: 3083 | AU28: 126815 | AV28: 231250 | AW28: 231250 | AX28: 231250 | AY28: 231250 | AZ28: 231250 | BA28: 231250 | BB28: 231250 | BC28: 231250 | BU28: =SUM(J28:U28) -> 0 | BV28: =SUM(V28:AG28) -> 0 | BW28: =SUM(AH28:AS28) -> 0 | BX28: =SUM(AT28:BE28) -> 1976815 | BY28: =SUM(BF28:BQ28) -> 0 | BZ28: =SUM(BR28:BT28) -> 0 | CA28: =BV28/BU28 -> #DIV/0!
A29: 6957 | B29: Assam | C29: Guwahati | D29: GUWAHATI 2948 | E29: 1 | F29: SURESH KUMAR JAIN & PRITY SETHI WH,GODOWN NO.1,DAG NO: 193, 313, 314, 315, 317 PATTA NO : 209, 169, 423, 337, 232 VILL- UPARHALI, MOUZA-RAMPUR DISTT: KAMRUP, ASSAM : 781122 STATE: ASSAM | G29: 01-Feb-2025 | I29: 4937 | BD29: 388372 | BE29: 388372 | BF29: 388372 | BG29: 388372 | BH29: 388372 | BI29: 388372 | BJ29: 388372 | BK29: 388372 | BL29: 388372 | BM29: 388372 | BN29: 388372 | BO29: 388372 | BP29: 407330 | BQ29: 407330 | BR29: 407330 | BS29: 407330 | BT29: 407330 | BU29: =SUM(J29:U29) -> 0 | BV29: =SUM(V29:AG29) -> 0 | BW29: =SUM(AH29:AS29) -> 0 | BX29: =SUM(AT29:BE29) -> 776744 | BY29: =SUM(BF29:BQ29) -> 4698380 | BZ29: =SUM(BR29:BT29) -> 1221990 | CA29: =BV29/BU29 -> #DIV/0!
A30: 6775 | B30: Assam | C30: Guwahati | D30: GUWAHATI 2948 | E30: 1 OLD | F30: SURESH KUMAR JAIN & PRITY SETHI WH,GODOWN NO.-1,DAG NO: 193, 313, 314, 315, 317 PATTA NO : 209, 169, 423, 337, 232 VILL- UPARHALI, MOUZA-RAMPUR DISTT: KAMRUP, ASSAM : 781122 STATE: ASSAM | G30: 01-May-2024 | H30: 31-Dec-2024 | I30: 4937 | AU30: 488796 | AV30: 488796 | AW30: 488796 | AX30: 488796 | AY30: 488796 | AZ30: 488796 | BA30: 488796 | BB30: 977592 | BU30: =SUM(J30:U30) -> 0 | BV30: =SUM(V30:AG30) -> 0 | BW30: =SUM(AH30:AS30) -> 0 | BX30: =SUM(AT30:BE30) -> 4399164 | BY30: =SUM(BF30:BQ30) -> 0 | BZ30: =SUM(BR30:BT30) -> 0 | CA30: =BV30/BU30 -> #DIV/0!
A31: 6958 | B31: Assam | C31: Guwahati | D31: GUWAHATI 2948 | E31: 2 | F31: SURESH KUMAR JAIN & PRITY SETHI WH,GODOWN NO. 2, DAG NO: 193, 313, 314, 315, 317 PATTA NO : 209, 169, 423, 337, 232 VILL- UPARHALI, MOUZA-RAMPUR DISTT: KAMRUP, ASSAM : 781122 STATE: ASSAM | G31: 01-Feb-2025 | I31: 6074 | BD31: 477794 | BE31: 477794 | BF31: 477794 | BG31: 477794 | BH31: 477794 | BI31: 477794 | BJ31: 477794 | BK31: 477794 | BL31: 477794 | BM31: 477794 | BN31: 477794 | BO31: 477794 | BP31: 501120 | BQ31: 501120 | BR31: 501120 | BS31: 501120 | BT31: 501120 | BU31: =SUM(J31:U31) -> 0 | BV31: =SUM(V31:AG31) -> 0 | BW31: =SUM(AH31:AS31) -> 0 | BX31: =SUM(AT31:BE31) -> 955588 | BY31: =SUM(BF31:BQ31) -> 5780180 | BZ31: =SUM(BR31:BT31) -> 1503360 | CA31: =BV31/BU31 -> #DIV/0!
A32: 6776 | B32: Assam | C32: Guwahati | D32: GUWAHATI 2948 | E32: 2 OLD | F32: SURESH KUMAR JAIN & PRITY SETHI WH,GODOWN NO.-2,DAG NO: 193, 313, 314, 315, 317 PATTA NO : 209, 169, 423, 337, 232 VILL- UPARHALI, MOUZA-RAMPUR DISTT: KAMRUP, ASSAM : 781122 STATE: ASSAM | G32: 01-May-2024 | H32: 31-Dec-2024 | I32: 6074 | AU32: 601343 | AV32: 601343 | AW32: 601343 | AX32: 601343 | AY32: 601343 | AZ32: 601343 | BA32: 601343 | BU32: =SUM(J32:U32) -> 0 | BV32: =SUM(V32:AG32) -> 0 | BW32: =SUM(AH32:AS32) -> 0 | BX32: =SUM(AT32:BE32) -> 4209401 | BY32: =SUM(BF32:BQ32) -> 0 | BZ32: =SUM(BR32:BT32) -> 0 | CA32: =BV32/BU32 -> #DIV/0!
A33: 7067 | B33: Assam | C33: Guwahati | D33: GUWAHATI 2972 | E33: 1 | F33: LAVIN AGRAWAL & JITENDRA KUMAR AGRAWAL W/H GODOWN NO 1, DAG NO:-377,376 PATT NO:-201,125 VILL:-RAMPUR, MOZA:- RAMPUR DISTT:-KAMRUP, ASSAM-781132 | G33: 01-May-2025 | H33: 30-Nov-2025 | I33: 7449 | BG33: 558663 | BH33: 558663 | BI33: 558663 | BJ33: 558663 | BK33: 558663 | BL33: 558663 | BM33: 558663 | BU33: =SUM(J33:U33) -> 0 | BV33: =SUM(V33:AG33) -> 0 | BW33: =SUM(AH33:AS33) -> 0 | BX33: =SUM(AT33:BE33) -> 0 | BY33: =SUM(BF33:BQ33) -> 3910641 | BZ33: =SUM(BR33:BT33) -> 0 | CA33: =BV33/BU33 -> #DIV/0!
A34: 6777 | B34: Assam | C34: Guwahati | D34: GUWAHATI 2972 | E34: 1 old | F34: LAVIN AGRAWAL & JITENDRA KUMAR AGRAWAL W/H DAG NO:-377,376 PATT NO:-201,125 VILL:-RAMPUR,MOZA:-RAMPUR DISTT:-KAMRUP,ASSAM-781132 | G34: 01-May-2024 | H34: 31-Jan-2025 | I34: 7449 | AU34: 737435 | AV34: 737435 | AW34: 737435 | AX34: 737435 | AY34: 737435 | AZ34: 737435 | BA34: 737435 | BB34: 737435 | BC34: 737435 | BU34: =SUM(J34:U34) -> 0 | BV34: =SUM(V34:AG34) -> 0 | BW34: =SUM(AH34:AS34) -> 0 | BX34: =SUM(AT34:BE34) -> 6636915 | BY34: =SUM(BF34:BQ34) -> 0 | BZ34: =SUM(BR34:BT34) -> 0 | CA34: =BV34/BU34 -> #DIV/0!
A35: 7103 | B35: Assam | C35: Guwahati | D35: GUWAHATI 2974 | E35: 1 | F35: WHEAT PRODUCT COMPANY WH , GOD NO - 1 , DAG NO. 1301,1302,PATTA NO.22,241,VILLAGE: 3 NO RAMPUR,MOUZA: RAMPUR, DISTT - KAMRUP, GUHAWATI 781005, ASSAM | G35: 01-May-2025 | H35: 31-Mar-2026 | I35: 3883 | BG35: 291200 | BH35: 291200 | BI35: 291200 | BJ35: 291200 | BK35: 291200 | BL35: 291200 | BM35: 291200 | BN35: 291200 | BO35: 291200 | BP35: 291200 | BQ35: 291200 | BU35: =SUM(J35:U35) -> 0 | BV35: =SUM(V35:AG35) -> 0 | BW35: =SUM(AH35:AS35) -> 0 | BX35: =SUM(AT35:BE35) -> 0 | BY35: =SUM(BF35:BQ35) -> 3203200 | BZ35: =SUM(BR35:BT35) -> 0 | CA35: =BV35/BU35 -> #DIV/0!
A36: 6783 | B36: Assam | C36: Guwahati | D36: GUWAHATI 2974 | E36: 1 old | F36: WHEAT PRODUCT COMPANY WH , GOD NO - 1 , DAG NO. 1301,1302,PATTA NO.22,241,VILLAGE: 3 NO RAMPUR,MOUZA: RAMPUR, DISTT - KAMRUP, GUHAWATI -781005, ASSAM | G36: 28-Apr-2024 | H36: 28-Feb-2025 | I36: 3883 | AU36: 291200 | AV36: 291200 | AW36: 291200 | AX36: 291200 | AY36: 291200 | AZ36: 291200 | BA36: 291200 | BB36: 291200 | BC36: 291200 | BD36: 291200 | BU36: =SUM(J36:U36) -> 0 | BV36: =SUM(V36:AG36) -> 0 | BW36: =SUM(AH36:AS36) -> 0 | BX36: =SUM(AT36:BE36) -> 2912000 | BY36: =SUM(BF36:BQ36) -> 0 | BZ36: =SUM(BR36:BT36) -> 0 | CA36: =BV36/BU36 -> #DIV/0!
A37: 7362 | B37: Assam | C37: Guwahati | D37: GUWAHATI 2992 | E37: 1 | F37: PUSPA DEVI JAIN WH, GOD NO - 1, DAG NO - 322, PATTA NO - 301, REVENUE VILL - 3 NO, MOUZA - RAMPUR, DISTT - KAMRUP, ASSAM - 781132 | G37: 01-May-2026 | I37: 4164 | BS37: 299796 | BT37: 299796 | BU37: =SUM(J37:U37) -> 0 | BV37: =SUM(V37:AG37) -> 0 | BW37: =SUM(AH37:AS37) -> 0 | BX37: =SUM(AT37:BE37) -> 0 | BY37: =SUM(BF37:BQ37) -> 0 | BZ37: =SUM(BR37:BT37) -> 599592 | CA37: =BV37/BU37 -> #DIV/0!
A38: 6822 | B38: Assam | C38: Guwahati | D38: GUWAHATI 2992 | E38: 1 old | F38: PUSPA DEVI JAIN WH,GODOWN NO. 1, DAG NO. 322,PATTA NO.301,REVENUE VILL:-3 NO,MOUZA: RAMPUR,DISTT:KAMRUP, ASSAM - 781132. | G38: 01-May-2024 | I38: 4164 | AU38: 412220 | AV38: 412220 | AW38: 412220 | AX38: 412220 | AY38: 412220 | AZ38: 412220 | BA38: 412220 | BB38: 412220 | BC38: 412220 | BD38: 412220 | BE38: 412220 | BF38: 424711 | BG38: 424711 | BH38: 424711 | BI38: 424711 | BJ38: 424711 | BK38: 424711 | BL38: 424711 | BM38: 424711 | BU38: =SUM(J38:U38) -> 0 | BV38: =SUM(V38:AG38) -> 0 | BW38: =SUM(AH38:AS38) -> 0 | BX38: =SUM(AT38:BE38) -> 4534420 | BY38: =SUM(BF38:BQ38) -> 3397688 | BZ38: =SUM(BR38:BT38) -> 0 | CA38: =BV38/BU38 -> #DIV/0!
A39: 7144 | B39: Assam | C39: Guwahati | D39: GUWAHATI 3174 | E39: 1 | F39: NRB ASSOCIATES WAREHOUSE GODOWN NO - 1, DAG NO - 649, 674, 620, PATTA NO - 266, 105, 46, VILLAGE - KOCHPARA, MOUZA - CHAYANI, CIRCLE - PALASHBARI, DISTT - KAMRUP, ASSAM - 781128 | G39: 17-May-2025 | H39: 31-Oct-2025 | I39: 2500 | BG39: 127016 | BH39: 262500 | BI39: 262500 | BJ39: 262500 | BK39: 262500 | BL39: 262500 | BU39: =SUM(J39:U39) -> 0 | BV39: =SUM(V39:AG39) -> 0 | BW39: =SUM(AH39:AS39) -> 0 | BX39: =SUM(AT39:BE39) -> 0 | BY39: =SUM(BF39:BQ39) -> 1439516 | BZ39: =SUM(BR39:BT39) -> 0 | CA39: =BV39/BU39 -> #DIV/0!
A40: 7329 | B40: Assam | C40: KAMRUP | D40: KAMRUP 3289 | E40: 1 | F40: KAMAL PREET KAUR WAREHOUSE, GODOWN NO 1, DAG NO 1544, 1545, 1546, 1547, PATT NO 742,743, 744, 745, VILL-3 NO RAMPUR, MAUZA - RAMPUR, CIRCLE- PALASHBARI, DISTRICT- KAMRUP, ASSAM- 781132 | G40: 15-Apr-2026 | I40: 7449 | BR40: 286035 | BS40: 536316 | BT40: 536316 | BU40: =SUM(J40:U40) -> 0 | BV40: =SUM(V40:AG40) -> 0 | BW40: =SUM(AH40:AS40) -> 0 | BX40: =SUM(AT40:BE40) -> 0 | BY40: =SUM(BF40:BQ40) -> 0 | BZ40: =SUM(BR40:BT40) -> 1358667 | CA40: =BV40/BU40 -> #DIV/0!
A41: 7519 | B41: Assam | C41: KAMRUP | D41: KAMRUP 3340 | E41: 1 | F41: TIRUPATI FOODS WAREHOUSE GODOWN NO - 1, DAG NO - 832 & 844 OF PATTA NO - 432 & 349, REVENUE VILLAGE - TEZPUR, MAUZA - RAMPUR, CIRCLE - PALASBARI, KAMRUP ASSAM - 781132 | G41: 01-May-2026 | I41: 5000 | BS41: 450000 | BT41: 450000 | BU41: =SUM(J41:U41) -> 0 | BV41: =SUM(V41:AG41) -> 0 | BW41: =SUM(AH41:AS41) -> 0 | BX41: =SUM(AT41:BE41) -> 0 | BY41: =SUM(BF41:BQ41) -> 0 | BZ41: =SUM(BR41:BT41) -> 900000 | CA41: =BV41/BU41 -> #DIV/0!
A42: 7424 | B42: Bihar East | C42: Katihar | D42: KATIHAR 3341 | E42: 1 | F42: USHA DEVI AGARWAL WAREHOUSE GODOWN NO - 1, KHATA NO - 613, KHASRA NO - 1478, 1514, 1515, MOUZA - BANSGADHA, ANCHAL - KORHA, KATIHAR, BIHAR - 854104 | G42: 01-May-2026 | H42: 03-Jun-2026 | I42: 5705 | BU42: =SUM(J42:U42) -> 0 | BV42: =SUM(V42:AG42) -> 0 | BW42: =SUM(AH42:AS42) -> 0 | BX42: =SUM(AT42:BE42) -> 0 | BY42: =SUM(BF42:BQ42) -> 0 | BZ42: =SUM(BR42:BT42) -> 0 | CA42: =BV42/BU42 -> #DIV/0!
A43: 4849 | B43: Bihar East | C43: Purnea | D43: Purnea 1437 | E43: 1B | F43: Ranju Saha W/H Khasara No:-876,Khata No:-209, Village:-Sisabari,Mauza:-Hasda,NH-57,Distt:-Purnea,PIN:-854326 | G43: 01-May-2018 | I43: 2533 | J43: 114000 | K43: 114000 | L43: 114000 | M43: 114000 | N43: 114000 | O43: 114000 | P43: 114000 | Q43: 114000 | R43: 114000 | S43: 114000 | T43: 114000 | U43: 114000 | V43: 114000 | W43: 114000 | X43: 114000 | Y43: 114000 | Z43: 114000 | AA43: 114000 | AB43: 114000 | AC43: 114000 | AD43: 121600 | AE43: 121600 | AF43: 121600 | AG43: 121600 | AH43: 121600 | AI43: 121600 | AJ43: 121600 | AK43: 121600 | AL43: 121600 | AM43: 121600 | AN43: 121600 | AO43: 125400 | AP43: 125400 | AQ43: 125400 | AR43: 125400 | AS43: 125400 | AT43: 125400 | AU43: 125400 | AV43: 125400 | AW43: 125400 | AX43: 125400 | AY43: 125400 | AZ43: 125400 | BA43: 125400 | BB43: 125400 | BC43: 125400 | BD43: 125400 | BE43: 125400 | BF43: 167200 | BG43: 167200 | BH43: 167200 | BI43: 167200 | BJ43: 167200 | BK43: 167200 | BL43: 167200 | BM43: 167200 | BN43: 167200 | BO43: 167200 | BP43: 167200 | BQ43: 167200 | BR43: 129200 | BS43: 129200 | BT43: 129200 | BU43: =SUM(J43:U43) -> 1368000 | BV43: =SUM(V43:AG43) -> 1398400 | BW43: =SUM(AH43:AS43) -> 1478200 | BX43: =SUM(AT43:BE43) -> 1504800 | BY43: =SUM(BF43:BQ43) -> 2006400 | BZ43: =SUM(BR43:BT43) -> 387600 | CA43: =BV43/BU43 -> 1.0222222
A44: 7043 | B44: Bihar East | C44: Purnea | D44: Purnea 1627 | E44: 2 | F44: RANDHIR SAHA WH ,GODOWN NO.2,CH NO. 1,2,3 & 4,KHESRA NO. 880, KHATA NO. 212, VILLAGE - HASDA,TALUKA- GULABBAGH,DIST-PURNEA,STATE-BIHAR, PIN- 854326 | G44: 01-Apr-2025 | I44: 8936 | BF44: 536130 | BG44: 536130 | BH44: 536130 | BI44: 536130 | BJ44: 536130 | BK44: 536130 | BL44: 536130 | BM44: 536130 | BN44: 536130 | BO44: 536130 | BP44: 536130 | BQ44: 536130 | BR44: 455712 | BS44: 455712 | BT44: 455712 | BU44: =SUM(J44:U44) -> 0 | BV44: =SUM(V44:AG44) -> 0 | BW44: =SUM(AH44:AS44) -> 0 | BX44: =SUM(AT44:BE44) -> 0 | BY44: =SUM(BF44:BQ44) -> 6433560 | BZ44: =SUM(BR44:BT44) -> 1367136 | CA44: =BV44/BU44 -> #DIV/0!
A45: 4848 | B45: Bihar East | C45: Purnea | D45: Purnea 1627 | E45: 2 old | F45: RANDHIR SAHA WH CH NO. 1,2,3 & 4,KHESRA NO. 866, KHATA NO. 214, VILLAGE - HASDA,TALUKA- GULABBAGH,DIST-PURNEA,STATE-BIHAR, PIN- 854326 | G45: 01-May-2018 | H45: 30-Apr-2025 | I45: 8936 | J45: 402098 | K45: 402098 | L45: 402098 | M45: 402098 | N45: 402098 | O45: 402098 | P45: 402098 | Q45: 402098 | R45: 402098 | S45: 402098 | T45: 402098 | U45: 402098 | V45: 402098 | W45: 402098 | X45: 402098 | Y45: 402098 | Z45: 402098 | AA45: 402098 | AB45: 402098 | AC45: 402098 | AD45: 428904 | AE45: 428904 | AF45: 428904 | AG45: 428904 | AH45: 428904 | AI45: 428904 | AJ45: 428904 | AK45: 428904 | AL45: 428904 | AM45: 428904 | AN45: 428904 | AO45: 428904 | AP45: 442306 | AQ45: 442306 | AR45: 442306 | AS45: 442306 | AT45: 442306 | AU45: 442306 | AV45: 442306 | AW45: 442306 | AX45: 442306 | AY45: 442306 | AZ45: 442306 | BA45: 442306 | BB45: 442306 | BC45: 442306 | BD45: 442306 | BE45: 442306 | BU45: =SUM(J45:U45) -> 4825176 | BV45: =SUM(V45:AG45) -> 4932400 | BW45: =SUM(AH45:AS45) -> 5200456 | BX45: =SUM(AT45:BE45) -> 5307672 | BY45: =SUM(BF45:BQ45) -> 0 | BZ45: =SUM(BR45:BT45) -> 0 | CA45: =BV45/BU45 -> 1.0222218
A46: 4883 | B46: Bihar East | C46: Purnea | D46: Purnea 1850 | E46: 1 | F46: YADAV WAREHOUSE Khasra No:-209/Khata No:-876,Moza:-Hansda,Village:-Shisabadi,Taluka:-Gulabbagh Distt:-Purnea,Pin:-854326,State:-Bihar. | G46: 01-May-2018 | H46: 31-Mar-2024 | I46: 2521 | J46: 121000 | K46: 121000 | L46: 121000 | M46: 121000 | N46: 121000 | O46: 121000 | P46: 121000 | Q46: 121000 | R46: 121000 | S46: 121000 | T46: 121000 | U46: 121000 | V46: 121000 | W46: 121000 | X46: 121000 | Y46: 121000 | Z46: 121000 | AA46: 121000 | AB46: 121000 | AC46: 121000 | AD46: 136125 | AE46: 136125 | AF46: 136125 | AG46: 136125 | AH46: 136125 | AI46: 136125 | AJ46: 136125 | AK46: 136125 | AL46: 136125 | AM46: 136125 | AN46: 136125 | AO46: 136125 | AP46: 136125 | AQ46: 136125 | AR46: 136125 | AS46: 136125 | BU46: =SUM(J46:U46) -> 1452000 | BV46: =SUM(V46:AG46) -> 1512500 | BW46: =SUM(AH46:AS46) -> 1633500 | BX46: =SUM(AT46:BE46) -> 0 | BY46: =SUM(BF46:BQ46) -> 0 | BZ46: =SUM(BR46:BT46) -> 0 | CA46: =BV46/BU46 -> 1.0416667
A47: 7533 | B47: Bihar East | C47: Purnea | D47: Purnea 2041 | E47: 1 | F47: MONA SANCHETI W/H, khata No : 113,153,Khasra No: 216,218,Mauza:-Fatehpur,Near NH-57, Araria Road, Kasba,Purnea, Bihar-854330,State:-Bihar | G47: 01-Jun-2026 | I47: 2615 | BT47: 94140 | BU47: =SUM(J47:U47) -> 0 | BV47: =SUM(V47:AG47) -> 0 | BW47: =SUM(AH47:AS47) -> 0 | BX47: =SUM(AT47:BE47) -> 0 | BY47: =SUM(BF47:BQ47) -> 0 | BZ47: =SUM(BR47:BT47) -> 94140 | CA47: =BV47/BU47 -> #DIV/0!
A48: 5152 | B48: Bihar East | C48: Purnea | D48: Purnea 2041 | E48: 1old | F48: MONA SANCHETI W/H, khata No : 113,153,Khasra No: 216,218,Mauza:-Fatehpur,Near NH-57, Araria Road, Kasba,Purnea, Bihar-854330,State:-Bihar | G48: 16-Apr-2019 | H48: 31-Mar-2026 | I48: 2615 | J48: 125520 | K48: 125520 | L48: 125520 | M48: 125520 | N48: 125520 | O48: 125520 | P48: 125520 | Q48: 125520 | R48: 125520 | S48: 129569 | T48: 133365 | U48: 133365 | V48: 133365 | W48: 133365 | X48: 133365 | Y48: 133365 | Z48: 133365 | AA48: 133365 | AB48: 133365 | AC48: 133365 | AD48: 133365 | AE48: 133365 | AF48: 133365 | AG48: 133365 | AH48: 133365 | AI48: 133365 | AJ48: 133365 | AK48: 133365 | AL48: 133365 | AM48: 133365 | AN48: 133365 | AO48: 141210 | AP48: 149055 | AQ48: 149055 | AR48: 149055 | AS48: 149055 | AT48: 149055 | AU48: 149055 | AV48: 149055 | AW48: 149055 | AX48: 149055 | AY48: 149055 | AZ48: 149055 | BA48: 149055 | BB48: 149055 | BC48: 149055 | BD48: 149055 | BE48: 149055 | BF48: 149055 | BG48: 149055 | BH48: 149055 | BI48: 149055 | BJ48: 149055 | BK48: 149056 | BL48: 149055 | BM48: 149055 | BN48: 149055 | BO48: 149055 | BP48: 149055 | BQ48: 149055 | BU48: =SUM(J48:U48) -> 1525979 | BV48: =SUM(V48:AG48) -> 1600380 | BW48: =SUM(AH48:AS48) -> 1670985 | BX48: =SUM(AT48:BE48) -> 1788660 | BY48: =SUM(BF48:BQ48) -> 1788661 | BZ48: =SUM(BR48:BT48) -> 0 | CA48: =BV48/BU48 -> 1.0487562
A49: 7518 | B49: Bihar East | C49: Purnea | D49: Purnea 2042 | E49: 1 | F49: MEENA DEVI SANCHETI W/H, KHATA NO : 171,100,KHASRA NO: 259,219,222,MAUZA:-FATEHPUR,NEAR NH-57, ARARIA ROAD, KASBA,PURNEA, BIHAR-854330,STATE:-BIHAR | G49: 19-May-2026 | I49: 3267 | BS49: 5059.0968 | BT49: 156832 | BU49: =SUM(J49:U49) -> 0 | BV49: =SUM(V49:AG49) -> 0 | BW49: =SUM(AH49:AS49) -> 0 | BX49: =SUM(AT49:BE49) -> 0 | BY49: =SUM(BF49:BQ49) -> 0 | BZ49: =SUM(BR49:BT49) -> 161891.1 | CA49: =BV49/BU49 -> #DIV/0!
A50: 5147 | B50: Bihar East | C50: Purnea | D50: Purnea 2042 | E50: 1 Old | F50: MEENA DEVI SANCHETI W/H, khata No : 171,100,Khasra No: 259,219,222,Mauza:-Fatehpur,Near NH-57, Araria Road, Kasba,Purnea, Bihar-854330,State:-Bihar | G50: 16-Apr-2019 | H50: 31-Mar-2026 | I50: 5406 | J50: 259504 | K50: 259504 | L50: 259504 | M50: 259504 | N50: 259504 | O50: 259504 | P50: 259504 | Q50: 259504 | R50: 259504 | S50: 267875 | T50: 275723 | U50: 275723 | V50: 275723 | W50: 275723 | X50: 275723 | Y50: 275723 | Z50: 275723 | AA50: 275723 | AB50: 275723 | AC50: 275723 | AD50: 275723 | AE50: 275723 | AF50: 275723 | AG50: 275723 | AH50: 275723 | AI50: 275723 | AJ50: 275723 | AK50: 275723 | AL50: 275723 | AM50: 275723 | AN50: 275723 | AO50: 291942 | AP50: 308161 | AQ50: 308161 | AR50: 308161 | AS50: 308161 | AT50: 308161 | AU50: 308161 | AV50: 308161 | AW50: 308161 | AX50: 308161 | AY50: 308161 | AZ50: 308161 | BA50: 308161 | BB50: 308161 | BC50: 308161 | BD50: 308161 | BE50: 308161 | BF50: 308161 | BG50: 308161 | BH50: 308161 | BI50: 308161 | BJ50: 308161 | BK50: 308160 | BL50: 308161 | BM50: 308161 | BN50: 308161 | BO50: 308161 | BP50: 308161 | BQ50: 308161 | BU50: =SUM(J50:U50) -> 3154857 | BV50: =SUM(V50:AG50) -> 3308676 | BW50: =SUM(AH50:AS50) -> 3454647 | BX50: =SUM(AT50:BE50) -> 3697932 | BY50: =SUM(BF50:BQ50) -> 3697931 | BZ50: =SUM(BR50:BT50) -> 0 | CA50: =BV50/BU50 -> 1.0487563
A51: 7532 | B51: Bihar East | C51: Purnea | D51: Purnea 2042 | E51: 2 | F51: MEENA DEVI SANCHETI W/H GODOWN NO 2, KHATA NO : 171,100,KHASRA NO: 259,219,222,MAUZA:-FATEHPUR,NEAR NH-57, ARARIA ROAD, KASBA,PURNEA, BIHAR-854330,STATE:-BIHAR | G51: 01-Jun-2026 | I51: 2139 | BT51: 77004 | BU51: =SUM(J51:U51) -> 0 | BV51: =SUM(V51:AG51) -> 0 | BW51: =SUM(AH51:AS51) -> 0 | BX51: =SUM(AT51:BE51) -> 0 | BY51: =SUM(BF51:BQ51) -> 0 | BZ51: =SUM(BR51:BT51) -> 77004 | CA51: =BV51/BU51 -> #DIV/0!
A52: 7425 | B52: Bihar East | C52: Purnea | D52: Purnea 2043 | E52: 1 | F52: JYOTI SANCHETI W/H, GODOWN NO. 1, KHATA NO : 113, KHASRA NO.: 218 MAUZA: -FATEHPUR, NEAR NH-57, ARARIA ROAD, KASBA, PURNEA, BIHAR - 854330, STATE: BIHAR | G52: 01-May-2026 | I52: 5154 | BS52: 247384 | BT52: 247384 | BU52: =SUM(J52:U52) -> 0 | BV52: =SUM(V52:AG52) -> 0 | BW52: =SUM(AH52:AS52) -> 0 | BX52: =SUM(AT52:BE52) -> 0 | BY52: =SUM(BF52:BQ52) -> 0 | BZ52: =SUM(BR52:BT52) -> 494768 | CA52: =BV52/BU52 -> #DIV/0!
A53: 5148 | B53: Bihar East | C53: Purnea | D53: Purnea 2043 | E53: 1old | F53: JYOTI SANCHETI W/H, CHAMBER NO 1 AND 2 khata No : 113,Khasra No: 218Mauza:-Fatehpur,Near NH-57, Araria Road, Kasba,Purnea, Bihar-854330,State:-Bihar | G53: 16-Apr-2019 | H53: 31-Mar-2026 | I53: 5154 | J53: 247384 | K53: 247384 | L53: 247384 | M53: 247384 | N53: 247384 | O53: 247384 | P53: 247384 | Q53: 247384 | R53: 247384 | S53: 255364 | T53: 262845 | U53: 262845 | V53: 262845 | W53: 262845 | X53: 262845 | Y53: 262845 | Z53: 262845 | AA53: 262845 | AB53: 262845 | AC53: 262845 | AD53: 262845 | AE53: 262845 | AF53: 262845 | AG53: 262845 | AH53: 262845 | AI53: 262845 | AJ53: 262845 | AK53: 262845 | AL53: 262845 | AM53: 262845 | AN53: 262845 | AO53: 278306 | AP53: 293769 | AQ53: 293769 | AR53: 293769 | AS53: 293769 | AT53: 293769 | AU53: 293769 | AV53: 293769 | AW53: 293769 | AX53: 293769 | AY53: 293769 | AZ53: 293769 | BA53: 293769 | BB53: 293769 | BC53: 293769 | BD53: 293769 | BE53: 293769 | BF53: 293769 | BG53: 293769 | BH53: 293769 | BI53: 293769 | BJ53: 293769 | BK53: 293768 | BL53: 293769 | BM53: 293769 | BN53: 293769 | BO53: 293769 | BP53: 293769 | BQ53: 293769 | BU53: =SUM(J53:U53) -> 3007510 | BV53: =SUM(V53:AG53) -> 3154140 | BW53: =SUM(AH53:AS53) -> 3293297 | BX53: =SUM(AT53:BE53) -> 3525228 | BY53: =SUM(BF53:BQ53) -> 3525227 | BZ53: =SUM(BR53:BT53) -> 0 | CA53: =BV53/BU53 -> 1.0487546
A54: 5833 | B54: Bihar East | C54: Purnea | D54: Purnea 2419 | E54: 1 | F54: GOURI GOYAL W/H KHASRA NO:-462,463,465/ KHATA NO:-150. MOUZA:-FATEHPUR NEAR NH-57 , P.S:-KASBA , DISTRICT:-PURNEA,PIN:-854326 , STATE:-BIHAR. | G54: 01-May-2021 | H54: 30-Apr-2022 | I54: 4867 | K54: 245314 | L54: 245314 | M54: 245314 | N54: 245314 | O54: 245314 | P54: 245314 | Q54: 245314 | R54: 245314 | S54: 245314 | T54: 245314 | U54: 245314 | V54: 81354 | BU54: =SUM(J54:U54) -> 2698454 | BV54: =SUM(V54:AG54) -> 81354 | BW54: =SUM(AH54:AS54) -> 0 | BX54: =SUM(AT54:BE54) -> 0 | BY54: =SUM(BF54:BQ54) -> 0 | BZ54: =SUM(BR54:BT54) -> 0 | CA54: =BV54/BU54 -> 0.030148374
A55: 5834 | B55: Bihar East | C55: Purnea | D55: Purnea 2420 | E55: 1 | F55: SILKY GOYAL W/H KHASRA NO:-462,465/ KHATA NO:-150. MOUZA:-FATEHPUR NEAR NH-57 , P.S:-KASBA , DISTRICT:-PURNEA,PIN:-854326 , STATE:-BIHAR | G55: 01-May-2021 | H55: 31-Mar-2022 | I55: 5864 | K55: 295537 | L55: 295537 | M55: 295537 | N55: 295537 | O55: 295537 | P55: 295537 | Q55: 295537 | R55: 295537 | S55: 295537 | T55: 295537 | U55: 295537 | BU55: =SUM(J55:U55) -> 3250907 | BV55: =SUM(V55:AG55) -> 0 | BW55: =SUM(AH55:AS55) -> 0 | BX55: =SUM(AT55:BE55) -> 0 | BY55: =SUM(BF55:BQ55) -> 0 | BZ55: =SUM(BR55:BT55) -> 0 | CA55: =BV55/BU55 -> 0
A56: 5830 | B56: Bihar East | C56: Purnea | D56: Purnea 2421 | E56: 1 | F56: GOYAL WH GODOWN NO. 1 CHAMBER NO.-1,2,3,4&5 KHASRA NO:-433,462,464,468,471/ KHATA NO:-150,137. MOUZA:-FATEHPUR NEAR NH-57 , P.S:-KASBA , DISTRICT:-PURNEA,PIN:-854326 , STATE:-BIHAR | G56: 01-May-2021 | H56: 31-Mar-2022 | I56: 11424 | K56: 575753 | L56: 575753 | M56: 575753 | N56: 575753 | O56: 575753 | P56: 575753 | Q56: 575753 | R56: 575753 | S56: 575753 | T56: 214066 | U56: 106294 | BU56: =SUM(J56:U56) -> 5502137 | BV56: =SUM(V56:AG56) -> 0 | BW56: =SUM(AH56:AS56) -> 0 | BX56: =SUM(AT56:BE56) -> 0 | BY56: =SUM(BF56:BQ56) -> 0 | BZ56: =SUM(BR56:BT56) -> 0 | CA56: =BV56/BU56 -> 0
A57: 5842 | B57: Bihar East | C57: Purnea | D57: PURNEA 2453 | E57: 1 | F57: KRISHAN GOYAL AND RAVI GOEL W/H KHATA NO:-133,153,120/ KHASRA NO:-100,111,97 MOUZA:-FATEHPUR , KASBA , PURNEA,BIHAR-854326,STATE-BIHAR | G57: 01-May-2021 | H57: 31-Mar-2022 | I57: 2631 | K57: 138908 | L57: 138908 | M57: 138908 | N57: 138908 | O57: 138908 | P57: 138908 | Q57: 138908 | R57: 138908 | BU57: =SUM(J57:U57) -> 1111264 | BV57: =SUM(V57:AG57) -> 0 | BW57: =SUM(AH57:AS57) -> 0 | BX57: =SUM(AT57:BE57) -> 0 | BY57: =SUM(BF57:BQ57) -> 0 | BZ57: =SUM(BR57:BT57) -> 0 | CA57: =BV57/BU57 -> 0
A58: 5843 | B58: Bihar East | C58: Purnea | D58: PURNEA 2453 | E58: 2 | F58: KRISHAN GOYAL AND RAVI GOEL W/H KHATA NO:-133,153,120/ KHASRA NO:-100,111,97 MOUZA:-FATEHPUR , KASBA , PURNEA,BIHAR-854326,STATE-BIHAR. | G58: 01-May-2021 | H58: 31-Mar-2022 | I58: 1584 | K58: 83635 | L58: 83635 | M58: 83635 | N58: 83635 | O58: 83635 | P58: 83635 | Q58: 83635 | R58: 83635 | BU58: =SUM(J58:U58) -> 669080 | BV58: =SUM(V58:AG58) -> 0 | BW58: =SUM(AH58:AS58) -> 0 | BX58: =SUM(AT58:BE58) -> 0 | BY58: =SUM(BF58:BQ58) -> 0 | BZ58: =SUM(BR58:BT58) -> 0 | CA58: =BV58/BU58 -> 0
A59: 5844 | B59: Bihar East | C59: Purnea | D59: PURNEA 2453 | E59: 3 | F59: KRISHAN GOYAL AND RAVI GOEL W/H KHATA NO:-133,153,120/ KHASRA NO:-100,111,97 MOUZA:-FATEHPUR , KASBA , PURNEA,BIHAR-854326,STATE-BIHAR. | G59: 01-May-2021 | H59: 31-Mar-2022 | I59: 979 | K59: 51709 | L59: 51709 | M59: 51709 | N59: 51709 | O59: 51709 | P59: 51709 | Q59: 51709 | R59: 51709 | S59: 51709 | T59: 51709 | U59: 51709 | BU59: =SUM(J59:U59) -> 568799 | BV59: =SUM(V59:AG59) -> 0 | BW59: =SUM(AH59:AS59) -> 0 | BX59: =SUM(AT59:BE59) -> 0 | BY59: =SUM(BF59:BQ59) -> 0 | BZ59: =SUM(BR59:BT59) -> 0 | CA59: =BV59/BU59 -> 0
A60: 5841 | B60: Bihar East | C60: Purnea | D60: PURNEA 2456 | E60: 1 | F60: PUNAM WAREHOUSE, KHATA NO:-122/ KHASRA NO:-1110, MOUZA:-FATEHPUR , KASBA , PURNEA,BIHAR-854326,STATE-BIHAR | G60: 15-May-2021 | H60: 14-Apr-2022 | I60: 1960 | K60: 51584 | L60: 94064 | M60: 94064 | N60: 94064 | O60: 94064 | P60: 94064 | Q60: 94064 | R60: 94064 | S60: 94064 | T60: 94064 | U60: 94064 | V60: 43896 | BU60: =SUM(J60:U60) -> 992224 | BV60: =SUM(V60:AG60) -> 43896 | BW60: =SUM(AH60:AS60) -> 0 | BX60: =SUM(AT60:BE60) -> 0 | BY60: =SUM(BF60:BQ60) -> 0 | BZ60: =SUM(BR60:BT60) -> 0 | CA60: =BV60/BU60 -> 0.04424001
A61: 5840 | B61: Bihar East | C61: Purnea | D61: PURNEA 2456 | E61: 2 | F61: PUNAM WAREHOUSE, GD . NO.-2 CH. NO.- 1 & 2 KHATA NO:-122/ KHASRA NO:-1110, MOUZA:-FATEHPUR , KASBA , PURNEA,BIHAR-854326,STATE-BIHAR | G61: 01-May-2021 | H61: 07-Apr-2022 | I61: 3553 | K61: 170528 | L61: 170528 | M61: 170528 | N61: 170528 | O61: 170528 | P61: 170528 | Q61: 170528 | R61: 170528 | S61: 170528 | T61: 170528 | U61: 170528 | BU61: =SUM(J61:U61) -> 1875808 | BV61: =SUM(V61:AG61) -> 0 | BW61: =SUM(AH61:AS61) -> 0 | BX61: =SUM(AT61:BE61) -> 0 | BY61: =SUM(BF61:BQ61) -> 0 | BZ61: =SUM(BR61:BT61) -> 0 | CA61: =BV61/BU61 -> 0
A62: 5854 | B62: Bihar East | C62: Purnea | D62: PURNEA 2462 | E62: 1 | F62: ANNAPURNA DISPOSABLE PRIVATE LIMITED WAREHOUSE, KHATA NO - 117,118 KHASRA NO -13,15,16 MOUZA:-SIKANDARPUR, THANA NO- 243, PURNEA,BIHAR-854326 | G62: 01-May-2021 | H62: 31-Mar-2022 | I62: 3576 | K62: 193104 | L62: 193104 | M62: 193104 | N62: 193104 | O62: 193104 | P62: 193104 | Q62: 193104 | R62: 193104 | S62: 193104 | T62: 193104 | U62: 193104 | BU62: =SUM(J62:U62) -> 2124144 | BV62: =SUM(V62:AG62) -> 0 | BW62: =SUM(AH62:AS62) -> 0 | BX62: =SUM(AT62:BE62) -> 0 | BY62: =SUM(BF62:BQ62) -> 0 | BZ62: =SUM(BR62:BT62) -> 0 | CA62: =BV62/BU62 -> 0
A63: 6116 | B63: Bihar East | C63: Purnea | D63: PURNEA 2579 | E63: 1 | F63: SUNITA AGRAWAL WAREHOUSE ,KHATA NO:-117,91,4 / KHASRA NO:-13,94,12, MOUZA - SIKANDARPUR , THANA - SADAR , DISTRICT -PURNEA,BIHAR - 854326 | G63: 01-May-2022 | H63: 31-Mar-2023 | I63: 1766 | W63: 98546 | X63: 98546 | Y63: 98546 | Z63: 98546 | AA63: 98546 | AB63: 98546 | AC63: 98546 | AD63: 98546 | AE63: 98546 | AF63: 98546 | AG63: 98546 | BU63: =SUM(J63:U63) -> 0 | BV63: =SUM(V63:AG63) -> 1084006 | BW63: =SUM(AH63:AS63) -> 0 | BX63: =SUM(AT63:BE63) -> 0 | BY63: =SUM(BF63:BQ63) -> 0 | BZ63: =SUM(BR63:BT63) -> 0 | CA63: =BV63/BU63 -> #DIV/0!
A64: 6117 | B64: Bihar East | C64: Purnea | D64: PURNEA 2579 | E64: 2 | F64: SUNITA AGRAWAL WAREHOUSE ,KHATA NO:-117,91,4 / KHASRA NO:-13,94,12, MOUZA - SIKANDARPUR , THANA - SADAR , DISTRICT -PURNEA,BIHAR - 854326 | G64: 01-May-2022 | H64: 31-Mar-2023 | I64: 1593 | W64: 88896 | X64: 88896 | Y64: 88896 | Z64: 88896 | AA64: 88896 | AB64: 88896 | AC64: 88896 | AD64: 88896 | AE64: 88896 | AF64: 88896 | AG64: 88896 | BU64: =SUM(J64:U64) -> 0 | BV64: =SUM(V64:AG64) -> 977856 | BW64: =SUM(AH64:AS64) -> 0 | BX64: =SUM(AT64:BE64) -> 0 | BY64: =SUM(BF64:BQ64) -> 0 | BZ64: =SUM(BR64:BT64) -> 0 | CA64: =BV64/BU64 -> #DIV/0!
A65: 6118 | B65: Bihar East | C65: Purnea | D65: PURNEA 2579 | E65: 3 | F65: SUNITA AGRAWAL WAREHOUSE ,KHATA NO:-117,91,4 / KHASRA NO:-13,94,12, MOUZA - SIKANDARPUR , THANA - SADAR , DISTRICT -PURNEA,BIHAR - 854326 | G65: 01-May-2022 | H65: 31-Mar-2023 | I65: 2295 | W65: 128048 | X65: 128048 | Y65: 128048 | Z65: 128048 | AA65: 128048 | AB65: 128048 | AC65: 128048 | AD65: 128048 | AE65: 128048 | AF65: 128048 | AG65: 128048 | BU65: =SUM(J65:U65) -> 0 | BV65: =SUM(V65:AG65) -> 1408528 | BW65: =SUM(AH65:AS65) -> 0 | BX65: =SUM(AT65:BE65) -> 0 | BY65: =SUM(BF65:BQ65) -> 0 | BZ65: =SUM(BR65:BT65) -> 0 | CA65: =BV65/BU65 -> #DIV/0!
A66: 6119 | B66: Bihar East | C66: Purnea | D66: PURNEA 2579 | E66: 4 | F66: SUNITA AGRAWAL WAREHOUSE ,KHATA NO:-117,91,4 / KHASRA NO:-13,94,12, MOUZA - SIKANDARPUR , THANA - SADAR , DISTRICT -PURNEA,BIHAR - 854326 | G66: 01-May-2022 | H66: 31-Mar-2023 | I66: 455 | W66: 25373 | X66: 25373 | Y66: 25373 | Z66: 25373 | AA66: 25373 | AB66: 25373 | AC66: 25373 | AD66: 25373 | AE66: 25373 | AF66: 25373 | AG66: 25373 | BU66: =SUM(J66:U66) -> 0 | BV66: =SUM(V66:AG66) -> 279103 | BW66: =SUM(AH66:AS66) -> 0 | BX66: =SUM(AT66:BE66) -> 0 | BY66: =SUM(BF66:BQ66) -> 0 | BZ66: =SUM(BR66:BT66) -> 0 | CA66: =BV66/BU66 -> #DIV/0!
A67: 6109 | B67: Bihar East | C67: Purnea | D67: PURNEA 2580 | E67: 1 | F67: FARM INDIA IMPEX PRIVATE LIMITED WAREHOUSE ,KHATA NO:-348,128,129/KHASRA NO:-314,317&318,322,323,MOHALLA - NEMA TOLA, MOUZA - MORACHA UZAIARPUR , THANA - KASBA ,ANCHAL - KASBA, DISTRICT - PURNEA, BIHAR - 854330 | G67: 01-May-2022 | H67: 31-Mar-2023 | I67: 1589 | W67: 100137 | X67: 100137 | Y67: 100137 | Z67: 100137 | AA67: 100137 | AB67: 100137 | AC67: 100137 | AD67: 100137 | AE67: 100137 | AF67: 100137 | AG67: 100137 | BU67: =SUM(J67:U67) -> 0 | BV67: =SUM(V67:AG67) -> 1101507 | BW67: =SUM(AH67:AS67) -> 0 | BX67: =SUM(AT67:BE67) -> 0 | BY67: =SUM(BF67:BQ67) -> 0 | BZ67: =SUM(BR67:BT67) -> 0 | CA67: =BV67/BU67 -> #DIV/0!
A68: 6110 | B68: Bihar East | C68: Purnea | D68: PURNEA 2580 | E68: 2 | F68: FARM INDIA IMPEX PRIVATE LIMITED WAREHOUSE ,KHATA NO:-348,128,129/KHASRA NO:-314,317&318,322,323,MOHALLA - NEMA TOLA, MOUZA - MORACHA UZAIARPUR , THANA - KASBA ,ANCHAL - KASBA, DISTRICT - PURNEA, BIHAR - 854330 | G68: 01-May-2022 | H68: 31-Mar-2023 | I68: 1569 | W68: 98876 | X68: 98876 | Y68: 98876 | Z68: 98876 | AA68: 98876 | AB68: 98876 | AC68: 98876 | AD68: 98876 | AE68: 98876 | AF68: 98876 | AG68: 98876 | BU68: =SUM(J68:U68) -> 0 | BV68: =SUM(V68:AG68) -> 1087636 | BW68: =SUM(AH68:AS68) -> 0 | BX68: =SUM(AT68:BE68) -> 0 | BY68: =SUM(BF68:BQ68) -> 0 | BZ68: =SUM(BR68:BT68) -> 0 | CA68: =BV68/BU68 -> #DIV/0!
A69: 6111 | B69: Bihar East | C69: Purnea | D69: PURNEA 2580 | E69: 3 | F69: FARM INDIA IMPEX PRIVATE LIMITED WAREHOUSE ,KHATA NO:-348,128,129/KHASRA NO:-314,317&318,322,323,MOHALLA - NEMA TOLA, MOUZA - MORACHA UZAIARPUR , THANA - KASBA ,ANCHAL - KASBA, DISTRICT - PURNEA, BIHAR - 854330 | G69: 01-May-2022 | H69: 31-Mar-2023 | I69: 1574 | W69: 99189 | X69: 99189 | Y69: 99189 | Z69: 99189 | AA69: 99189 | AB69: 99189 | AC69: 99189 | AD69: 99189 | AE69: 99189 | AF69: 99189 | AG69: 99189 | BU69: =SUM(J69:U69) -> 0 | BV69: =SUM(V69:AG69) -> 1091079 | BW69: =SUM(AH69:AS69) -> 0 | BX69: =SUM(AT69:BE69) -> 0 | BY69: =SUM(BF69:BQ69) -> 0 | BZ69: =SUM(BR69:BT69) -> 0 | CA69: =BV69/BU69 -> #DIV/0!
A70: 6112 | B70: Bihar East | C70: Purnea | D70: PURNEA 2580 | E70: 4 | F70: FARM INDIA IMPEX PRIVATE LIMITED WAREHOUSE ,KHATA NO:-348,128,129/KHASRA NO:-314,317&318,322,323,MOHALLA - NEMA TOLA, MOUZA - MORACHA UZAIARPUR , THANA - KASBA ,ANCHAL - KASBA, DISTRICT - PURNEA, BIHAR - 854330 | G70: 01-May-2022 | H70: 31-Mar-2023 | I70: 1584 | W70: 99805 | X70: 99805 | Y70: 99805 | Z70: 99805 | AA70: 99805 | AB70: 99805 | AC70: 99805 | AD70: 99805 | AE70: 99805 | AF70: 99805 | AG70: 99805 | BU70: =SUM(J70:U70) -> 0 | BV70: =SUM(V70:AG70) -> 1097855 | BW70: =SUM(AH70:AS70) -> 0 | BX70: =SUM(AT70:BE70) -> 0 | BY70: =SUM(BF70:BQ70) -> 0 | BZ70: =SUM(BR70:BT70) -> 0 | CA70: =BV70/BU70 -> #DIV/0!
A71: 6114 | B71: Bihar East | C71: Purnea | D71: PURNEA 2581 | E71: 1 | F71: JAI PRAKASH YADAV WAREHOUSE ,KHATA NO:-119,162 KHASRA NO:-87,88,89. MOUZA - FATEHPUR,THANA - KASBA , ANCHAL - KASBA,DISTRICT - PURNEA, BIHAR - 854330 | G71: 01-May-2022 | H71: 31-Mar-2023 | I71: 2283 | W71: 138507 | X71: 138507 | Y71: 138507 | Z71: 138507 | AA71: 138507 | AB71: 138507 | AC71: 138507 | AD71: 138507 | AE71: 138507 | AF71: 138507 | AG71: 138507 | BU71: =SUM(J71:U71) -> 0 | BV71: =SUM(V71:AG71) -> 1523577 | BW71: =SUM(AH71:AS71) -> 0 | BX71: =SUM(AT71:BE71) -> 0 | BY71: =SUM(BF71:BQ71) -> 0 | BZ71: =SUM(BR71:BT71) -> 0 | CA71: =BV71/BU71 -> #DIV/0!
A72: 6070 | B72: Bihar East | C72: Purnea | D72: PURNEA 2582 | E72: 1 | F72: SANGAM BHARTI WAREHOUSE ,GODOWN NO. - 1 , CHAMBER NO 1 AND 2 AT KHATA NO:138,KHASRA NO-2,3,4,MAUZA -SIKANADARPUR,THANA NO-243, DISTRICT - PURNEA, BIHAR - 854326 | G72: 01-May-2022 | H72: 31-Mar-2023 | I72: 4477 | W72: 214912 | X72: 214912 | Y72: 214912 | Z72: 214912 | AA72: 214912 | AB72: 214912 | AC72: 214912 | AD72: 214912 | AE72: 214912 | AF72: 214912 | AG72: 214912 | BU72: =SUM(J72:U72) -> 0 | BV72: =SUM(V72:AG72) -> 2364032 | BW72: =SUM(AH72:AS72) -> 0 | BX72: =SUM(AT72:BE72) -> 0 | BY72: =SUM(BF72:BQ72) -> 0 | BZ72: =SUM(BR72:BT72) -> 0 | CA72: =BV72/BU72 -> #DIV/0!
A73: 6069 | B73: Bihar East | C73: Purnea | D73: PURNEA 2583 | E73: 1 | F73: DILIP SAH WAREHOUSE,GODOWN NO. - 1 ,KHASRA NO. 876,KHATA NO. 209, VILLAGE- REMELI CHAMP, TALUKA- HASDA, DISTRICT - PURNEA, BIHAR - 854326 | G73: 01-May-2022 | H73: 31-Mar-2023 | I73: 1108 | W73: 53200 | X73: 53200 | Y73: 53200 | Z73: 53200 | AA73: 53200 | AB73: 53200 | AC73: 53200 | AD73: 53200 | AE73: 53200 | AF73: 53200 | AG73: 53200 | BU73: =SUM(J73:U73) -> 0 | BV73: =SUM(V73:AG73) -> 585200 | BW73: =SUM(AH73:AS73) -> 0 | BX73: =SUM(AT73:BE73) -> 0 | BY73: =SUM(BF73:BQ73) -> 0 | BZ73: =SUM(BR73:BT73) -> 0 | CA73: =BV73/BU73 -> #DIV/0!
A74: 6087 | B74: Bihar East | C74: Purnea | D74: PURNEA 2584 | E74: 1 | F74: ARUNA JAISWAL WAREHOUSE , KHATA NO:-38,35,16/KHASRA NO:-574,216, 217,218, 225,212, 213&214, MOUZA - LAKHANJAHRI , THANA - PURNEA SADAR , ANCHAL - PURNEA EAST, DISTRICT - PURNEA, BIHAR - 854326 | G74: 01-May-2022 | H74: 31-Mar-2023 | I74: 1621 | W74: 106993 | X74: 106993 | Y74: 106993 | Z74: 106993 | AA74: 106993 | AB74: 106993 | AC74: 106993 | AD74: 106993 | AE74: 106993 | AF74: 106993 | AG74: 106993 | BU74: =SUM(J74:U74) -> 0 | BV74: =SUM(V74:AG74) -> 1176923 | BW74: =SUM(AH74:AS74) -> 0 | BX74: =SUM(AT74:BE74) -> 0 | BY74: =SUM(BF74:BQ74) -> 0 | BZ74: =SUM(BR74:BT74) -> 0 | CA74: =BV74/BU74 -> #DIV/0!
A75: 6088 | B75: Bihar East | C75: Purnea | D75: PURNEA 2584 | E75: 2 | F75: ARUNA JAISWAL WAREHOUSE , KHATA NO:-38,35,16/KHASRA NO:-574,216, 217,218, 225,212, 213&214, MOUZA - LAKHANJAHRI , THANA - PURNEA SADAR , ANCHAL - PURNEA EAST, DISTRICT - PURNEA, BIHAR - 854326 | G75: 01-May-2022 | H75: 31-Mar-2023 | I75: 1725 | W75: 113875 | X75: 113875 | Y75: 113875 | Z75: 113875 | AA75: 113875 | AB75: 113875 | AC75: 113875 | AD75: 113875 | AE75: 113875 | AF75: 113875 | AG75: 113875 | BU75: =SUM(J75:U75) -> 0 | BV75: =SUM(V75:AG75) -> 1252625 | BW75: =SUM(AH75:AS75) -> 0 | BX75: =SUM(AT75:BE75) -> 0 | BY75: =SUM(BF75:BQ75) -> 0 | BZ75: =SUM(BR75:BT75) -> 0 | CA75: =BV75/BU75 -> #DIV/0!
A76: 6089 | B76: Bihar East | C76: Purnea | D76: PURNEA 2595 | E76: 1 | F76: GOYAL WAREHOUSE , CHAMBER NO 1, 2, 3, 4 AND 5, KHATA NO:-150,137/KHASRA NO -433,462,463,464,465,468,471, MOUZA - FATEHPUR , P.S. - KASBA , DISTRICT -PURNEA, BIHAR - 854326 | G76: 01-May-2022 | I76: 11424 | W76: 575752 | X76: 575752 | Y76: 575752 | Z76: 575752 | AA76: 575752 | AB76: 575752 | AC76: 575752 | AD76: 575752 | AE76: 575752 | AF76: 575752 | AG76: 575752 | AH76: 575753 | AI76: 575753 | AJ76: 575753 | AK76: 575753 | AL76: 575753 | AM76: 575753 | AN76: 575753 | AO76: 575753 | AP76: 575753 | AQ76: 575753 | AR76: 575753 | AS76: 668285 | AT76: 668285 | AU76: 668285 | AV76: 668285 | AW76: 668285 | AX76: 668285 | AY76: 668285 | AZ76: 668285 | BA76: 668285 | BB76: 668285 | BC76: 668285 | BD76: 668284 | BE76: 668284 | BF76: 668284 | BG76: 668284 | BH76: 668284 | BI76: 668284 | BJ76: 668284 | BK76: 668284 | BL76: 668284 | BM76: 668284 | BN76: 668284 | BO76: 668284 | BP76: 668284 | BQ76: 668284 | BR76: 634014 | BS76: 634014 | BT76: 634014 | BU76: =SUM(J76:U76) -> 0 | BV76: =SUM(V76:AG76) -> 6333272 | BW76: =SUM(AH76:AS76) -> 7001568 | BX76: =SUM(AT76:BE76) -> 8019418 | BY76: =SUM(BF76:BQ76) -> 8019408 | BZ76: =SUM(BR76:BT76) -> 1902042 | CA76: =BV76/BU76 -> #DIV/0!
A77: 6083 | B77: Bihar East | C77: Purnea | D77: PURNEA 2596 | E77: 1 | F77: SILKI GOYAL WAREHOUSE, CHAMBER NO 1,2 AND 3, KHASRA NO:-462,465/ KHATA NO:-150. MOUZA:-FATEHPUR NEAR NH-57 , P.S:-KASBA , DISTRICT:-PURNEA,PIN:-854326 , STATE:-BIHAR | G77: 01-May-2022 | I77: 5864 | W77: 295537 | X77: 295537 | Y77: 295537 | Z77: 295537 | AA77: 295537 | AB77: 295537 | AC77: 295537 | AD77: 295537 | AE77: 295537 | AF77: 295537 | AG77: 295537 | AH77: 295537 | AI77: 295537 | AJ77: 295537 | AK77: 295537 | AL77: 295537 | AM77: 295537 | AN77: 295537 | AO77: 295537 | AP77: 295537 | AQ77: 295537 | AR77: 295537 | AS77: 343034 | AT77: 343034 | AU77: 343034 | AV77: 343034 | AW77: 343034 | AX77: 343034 | AY77: 343034 | AZ77: 343034 | BA77: 343034 | BB77: 343034 | BC77: 343034 | BD77: 343034 | BE77: 343034 | BF77: 343034 | BG77: 343034 | BH77: 343034 | BI77: 343034 | BJ77: 343034 | BK77: 343034 | BL77: 343034 | BM77: 343034 | BN77: 343034 | BO77: 343034 | BP77: 343034 | BQ77: 343034 | BR77: 325443 | BS77: 325443 | BT77: 325443 | BU77: =SUM(J77:U77) -> 0 | BV77: =SUM(V77:AG77) -> 3250907 | BW77: =SUM(AH77:AS77) -> 3593941 | BX77: =SUM(AT77:BE77) -> 4116408 | BY77: =SUM(BF77:BQ77) -> 4116408 | BZ77: =SUM(BR77:BT77) -> 976329 | CA77: =BV77/BU77 -> #DIV/0!
A78: 6086 | B78: Bihar East | C78: Purnea | D78: PURNEA 2597 | E78: 1 | F78: PUNAM WAREHOUSE , , CHAMBER NO 1, 2 AND 3, KHASRA NO:-1110/ KHATA NO:-122, MOUZA:-FATEHPUR , P.S. - KASBA , DISTRICT - PURNEA, BIHAR 854326 | G78: 01-May-2022 | H78: 31-Mar-2023 | I78: 5512 | W78: 279806 | X78: 279806 | Y78: 279806 | Z78: 279806 | AA78: 279806 | AB78: 279806 | AC78: 279806 | AD78: 279806 | AE78: 279806 | AF78: 279806 | AG78: 279806 | BU78: =SUM(J78:U78) -> 0 | BV78: =SUM(V78:AG78) -> 3077866 | BW78: =SUM(AH78:AS78) -> 0 | BX78: =SUM(AT78:BE78) -> 0 | BY78: =SUM(BF78:BQ78) -> 0 | BZ78: =SUM(BR78:BT78) -> 0 | CA78: =BV78/BU78 -> #DIV/0!
A79: 6082 | B79: Bihar East | C79: Purnea | D79: PURNEA 2598 | E79: 1 | F79: KRISHAN GOYAL AND RAVI GOEL WAREHOUSE, KHATA NO - 133,153,120/ KHASRA NO - 100,111,97 MOUZA:-FATEHPUR , KASBA , PURNEA,BIHAR - 854330 | G79: 01-May-2022 | H79: 31-Jan-2023 | I79: 2631 | W79: 149958 | X79: 149958 | Y79: 149958 | Z79: 149958 | AA79: 149958 | AB79: 149958 | AC79: 149958 | AD79: 149958 | AE79: 149958 | BU79: =SUM(J79:U79) -> 0 | BV79: =SUM(V79:AG79) -> 1349622 | BW79: =SUM(AH79:AS79) -> 0 | BX79: =SUM(AT79:BE79) -> 0 | BY79: =SUM(BF79:BQ79) -> 0 | BZ79: =SUM(BR79:BT79) -> 0 | CA79: =BV79/BU79 -> #DIV/0!
A80: 6084 | B80: Bihar East | C80: Purnea | D80: PURNEA 2598 | E80: 2 | F80: KRISHAN GOYAL AND RAVI GOEL WAREHOUSE, KHATA NO - 133,153,120/ KHASRA NO - 100,111,97 MOUZA:-FATEHPUR , KASBA , PURNEA,BIHAR - 854330 | G80: 01-May-2022 | H80: 31-Jan-2023 | I80: 1584 | W80: 90288 | X80: 90288 | Y80: 90288 | Z80: 90288 | AA80: 90288 | AB80: 90288 | AC80: 90288 | AD80: 90288 | AE80: 90288 | BU80: =SUM(J80:U80) -> 0 | BV80: =SUM(V80:AG80) -> 812592 | BW80: =SUM(AH80:AS80) -> 0 | BX80: =SUM(AT80:BE80) -> 0 | BY80: =SUM(BF80:BQ80) -> 0 | BZ80: =SUM(BR80:BT80) -> 0 | CA80: =BV80/BU80 -> #DIV/0!
A81: 6085 | B81: Bihar East | C81: Purnea | D81: PURNEA 2598 | E81: 3 | F81: KRISHAN GOYAL AND RAVI GOEL WAREHOUSE, KHATA NO - 133,153,120/ KHASRA NO - 100,111,97 MOUZA:-FATEHPUR , KASBA , PURNEA,BIHAR - 854330 | G81: 01-May-2022 | H81: 28-Feb-2023 | I81: 979 | W81: 55826 | X81: 55826 | Y81: 55826 | Z81: 55826 | AA81: 55826 | AB81: 55826 | AC81: 55826 | AD81: 55826 | AE81: 55826 | AF81: 55826 | BU81: =SUM(J81:U81) -> 0 | BV81: =SUM(V81:AG81) -> 558260 | BW81: =SUM(AH81:AS81) -> 0 | BX81: =SUM(AT81:BE81) -> 0 | BY81: =SUM(BF81:BQ81) -> 0 | BZ81: =SUM(BR81:BT81) -> 0 | CA81: =BV81/BU81 -> #DIV/0!
A82: 6143 | B82: Bihar East | C82: Purnea | D82: PURNEA 2624 | E82: 1 | F82: GOURI GOYAL W/H GODOWN NO 1, CHAMBER NO 1,2 AND 3, KHASRA NO:-462,463,465/ KHATA NO:-150. MOUZA:-FATEHPUR NEAR NH-57 , P.S:-KASBA , DISTRICT:-PURNEA,PIN:-854326 , STATE:-BIHAR | G82: 01-May-2022 | I82: 4867 | W82: 245314 | X82: 245314 | Y82: 245314 | Z82: 245314 | AA82: 245314 | AB82: 245314 | AC82: 245314 | AD82: 245314 | AE82: 245314 | AF82: 245314 | AG82: 245314 | AH82: 245314 | AI82: 245314 | AJ82: 245314 | AK82: 245314 | AL82: 245314 | AM82: 245314 | AN82: 245314 | AO82: 245314 | AP82: 245314 | AQ82: 245314 | AR82: 245314 | AS82: 284739 | AT82: 284739 | AU82: 284739 | AV82: 284739 | AW82: 284739 | AX82: 284739 | AY82: 284739 | AZ82: 284739 | BA82: 284739 | BB82: 284739 | BC82: 284739 | BD82: 284739 | BE82: 284739 | BF82: 284739 | BG82: 284739 | BH82: 284739 | BI82: 284739 | BJ82: 284739 | BK82: 284739 | BL82: 284739 | BM82: 284739 | BN82: 284739 | BO82: 284739 | BP82: 284739 | BQ82: 284739 | BR82: 270137 | BS82: 270137 | BT82: 270137 | BU82: =SUM(J82:U82) -> 0 | BV82: =SUM(V82:AG82) -> 2698454 | BW82: =SUM(AH82:AS82) -> 2983193 | BX82: =SUM(AT82:BE82) -> 3416868 | BY82: =SUM(BF82:BQ82) -> 3416868 | BZ82: =SUM(BR82:BT82) -> 810411 | CA82: =BV82/BU82 -> #DIV/0!
A83: 6253 | B83: Bihar East | C83: Purnea | D83: PURNEA 2698 | E83: 1 | F83: CHITRA NOLKHA WAREHOUSE GODOWN-1, KHATA NO. 60, KHASRA NO. 440,441, MAUZA-MORACHA UJAIRPUR, THANA-KASBA, THANA NO.-248, DIST--PURNEA, BIHAR-854330 | G83: 01-May-2023 | I83: 3139 | AI83: 169515 | AJ83: 169515 | AK83: 169515 | AL83: 169515 | AM83: 169515 | AN83: 169515 | AO83: 169515 | AP83: 169515 | AQ83: 169515 | AR83: 169515 | AS83: 169515 | AT83: 178933 | AU83: 178933 | AV83: 178933 | AW83: 178933 | AX83: 178933 | AY83: 178933 | AZ83: 178933 | BA83: 178933 | BB83: 178933 | BC83: 178933 | BD83: 178933 | BE83: 197768 | BF83: 197768 | BG83: 197768 | BH83: 197768 | BI83: 197768 | BJ83: 197768 | BK83: 197768 | BL83: 197768 | BM83: 197768 | BN83: 197768 | BO83: 197768 | BP83: 197768 | BQ83: 197768 | BR83: 174224 | BS83: 174224 | BT83: 174224 | BU83: =SUM(J83:U83) -> 0 | BV83: =SUM(V83:AG83) -> 0 | BW83: =SUM(AH83:AS83) -> 1864665 | BX83: =SUM(AT83:BE83) -> 2166031 | BY83: =SUM(BF83:BQ83) -> 2373216 | BZ83: =SUM(BR83:BT83) -> 522672 | CA83: =BV83/BU83 -> #DIV/0!
A84: 6310 | B84: Bihar East | C84: Purnea | D84: PURNEA 2699 | E84: 1 | F84: KARNI WAREHOUSE GODOWN-1, KHATA NO. 119, KHASRA NO.66,92,94,95,96 ,MAUZA-FATEHPUR,THANA-KASBA,ANCHAL-KASBA,DIST--PURNEA, BIHAR-854330 | G84: 01-May-2023 | I84: 3134 | AI84: 169200 | AJ84: 169200 | AK84: 169200 | AL84: 169200 | AM84: 169200 | AN84: 169200 | AO84: 169200 | AP84: 169200 | AQ84: 169200 | AR84: 169200 | AS84: 169200 | AT84: 178600 | AU84: 178600 | AV84: 178600 | AW84: 178600 | AX84: 178600 | AY84: 178600 | AZ84: 178600 | BA84: 178600 | BB84: 178600 | BC84: 178600 | BD84: 178600 | BE84: 197400 | BF84: 197400 | BG84: 197400 | BH84: 197400 | BI84: 197400 | BJ84: 197400 | BK84: 197400 | BL84: 197400 | BM84: 197400 | BN84: 197400 | BO84: 197400 | BP84: 197400 | BQ84: 197400 | BR84: 173900 | BS84: 173900 | BT84: 173900 | BU84: =SUM(J84:U84) -> 0 | BV84: =SUM(V84:AG84) -> 0 | BW84: =SUM(AH84:AS84) -> 1861200 | BX84: =SUM(AT84:BE84) -> 2162000 | BY84: =SUM(BF84:BQ84) -> 2368800 | BZ84: =SUM(BR84:BT84) -> 521700 | CA84: =BV84/BU84 -> #DIV/0!
A85: 6345 | B85: Bihar East | C85: Purnea | D85: PURNEA 2700 | E85: 2 | F85: RAN VIJAY SINGH WAREHOUSE GODOWN NO 2 ,COMPARTMENT-2,CHAMBER NO. -1&2, KHATA NO. 133,324, KHASRA NO. 29,29,38 ,VILLAGE-DHARAMPUR,TALUKA-HARDA,DIST--PURNEA, BIHAR-854303 | G85: 01-May-2023 | I85: 3368 | AI85: 173806 | AJ85: 173806 | AK85: 173806 | AL85: 173806 | AM85: 173806 | AN85: 173806 | AO85: 173806 | AP85: 173806 | AQ85: 173806 | AR85: 173806 | AS85: 173806 | AT85: 173806 | AU85: 173806 | AV85: 173806 | AW85: 173806 | AX85: 173806 | AY85: 173806 | AZ85: 173806 | BA85: 173806 | BB85: 173806 | BC85: 173806 | BD85: 173806 | BE85: 173806 | BF85: 173806 | BG85: 173806 | BH85: 173806 | BI85: 173806 | BJ85: 173806 | BK85: 173806 | BL85: 173806 | BM85: 173806 | BN85: 173806 | BO85: 173806 | BP85: 173806 | BQ85: 173806 | BR85: 161680 | BS85: 161680 | BT85: 161680 | BU85: =SUM(J85:U85) -> 0 | BV85: =SUM(V85:AG85) -> 0 | BW85: =SUM(AH85:AS85) -> 1911866 | BX85: =SUM(AT85:BE85) -> 2085672 | BY85: =SUM(BF85:BQ85) -> 2085672 | BZ85: =SUM(BR85:BT85) -> 485040 | CA85: =BV85/BU85 -> #DIV/0!
A86: 6313 | B86: Bihar East | C86: Purnea | D86: PURNEA 2701 | E86: 1 | F86: JULI DEVI WAREHOUSE GODOWN-1, KHATA NO. 150, KHASRA NO. 463,1042 ,MAUZA-FATEHPUR,THANANO:244,THANA-KASBA,DISTRICT--PURNEA, BIHAR-854326 | G86: 01-May-2023 | H86: 28-Feb-2025 | I86: 1600 | AI86: 86382 | AJ86: 86382 | AK86: 86382 | AL86: 86382 | AM86: 86382 | AN86: 86382 | AO86: 86382 | AP86: 86382 | AQ86: 86382 | AR86: 86382 | AS86: 86382 | AT86: 86382 | AU86: 86382 | AV86: 86382 | AW86: 86382 | AX86: 86382 | AY86: 86382 | AZ86: 86382 | BA86: 86382 | BB86: 86382 | BC86: 86382 | BD86: 86382 | BU86: =SUM(J86:U86) -> 0 | BV86: =SUM(V86:AG86) -> 0 | BW86: =SUM(AH86:AS86) -> 950202 | BX86: =SUM(AT86:BE86) -> 950202 | BY86: =SUM(BF86:BQ86) -> 0 | BZ86: =SUM(BR86:BT86) -> 0 | CA86: =BV86/BU86 -> #DIV/0!
A87: 6290 | B87: Bihar East | C87: Purnea | D87: PURNEA 2702 | E87: 1 | F87: SANGITA DEVI WAREHOUSE GODOWN-1, KHATA NO. 150, KHASRA NO.: 463,1042 ,MAUZA-FATEHPUR,THANA NO:244,THANA-KASBA,DISTRICT--PURNEA, BIHAR-854326 | G87: 01-May-2023 | H87: 28-Feb-2025 | I87: 1662 | AI87: 89766 | AJ87: 89766 | AK87: 89766 | AL87: 89766 | AM87: 89766 | AN87: 89766 | AO87: 89766 | AP87: 89766 | AQ87: 89766 | AR87: 89766 | AS87: 89766 | AT87: 89766 | AU87: 89766 | AV87: 89766 | AW87: 89766 | AX87: 89766 | AY87: 89766 | AZ87: 89766 | BA87: 89766 | BB87: 89766 | BC87: 89766 | BD87: 89766 | BU87: =SUM(J87:U87) -> 0 | BV87: =SUM(V87:AG87) -> 0 | BW87: =SUM(AH87:AS87) -> 987426 | BX87: =SUM(AT87:BE87) -> 987426 | BY87: =SUM(BF87:BQ87) -> 0 | BZ87: =SUM(BR87:BT87) -> 0 | CA87: =BV87/BU87 -> #DIV/0!
A88: 6312 | B88: Bihar East | C88: Purnea | D88: PURNEA 2703 | E88: 1 | F88: YADAV WAREHOUSE GODOWN-1, KHATA NO. 255, KHASRA NO.: 875 ,VILL-SHISABADI,MAUZA-HANSDA,TALUKA-GULABBAGH,DISTRICT--PURNEA, BIHAR-854326 | G88: 01-May-2023 | H88: 28-Feb-2025 | I88: 2154 | AI88: 116316 | AJ88: 116316 | AK88: 116316 | AL88: 116316 | AM88: 116316 | AN88: 116316 | AO88: 116316 | AP88: 116316 | AQ88: 116316 | AR88: 116316 | AS88: 116316 | AT88: 116316 | AU88: 116316 | AV88: 116316 | AW88: 116316 | AX88: 116316 | AY88: 116316 | AZ88: 116316 | BA88: 116316 | BB88: 116316 | BC88: 116316 | BD88: 116316 | BU88: =SUM(J88:U88) -> 0 | BV88: =SUM(V88:AG88) -> 0 | BW88: =SUM(AH88:AS88) -> 1279476 | BX88: =SUM(AT88:BE88) -> 1279476 | BY88: =SUM(BF88:BQ88) -> 0 | BZ88: =SUM(BR88:BT88) -> 0 | CA88: =BV88/BU88 -> #DIV/0!
A89: 7419 | B89: Bihar East | C89: Purnea | D89: PURNEA 2718 | E89: 1 | F89: SANGAM BHARTI WAREHOUSE(GODOWN-1)CHAMBER-1 & 2, KHATA NO. 138, KHASRA NO. 2,3,4 ,MAUZA-SIKANADARPUR,THANA-SADAR,THANA NO.-243,ANCHAL--PURNEA, BIHAR-854326 | G89: 01-May-2026 | I89: 4477 | BS89: 214912 | BT89: 214912 | BU89: =SUM(J89:U89) -> 0 | BV89: =SUM(V89:AG89) -> 0 | BW89: =SUM(AH89:AS89) -> 0 | BX89: =SUM(AT89:BE89) -> 0 | BY89: =SUM(BF89:BQ89) -> 0 | BZ89: =SUM(BR89:BT89) -> 429824 | CA89: =BV89/BU89 -> #DIV/0!
A90: 6275 | B90: Bihar East | C90: Purnea | D90: PURNEA 2718 | E90: 1 old | F90: SANGAM BHARTI WAREHOUSE(GODOWN-1)CHAMBER-1 & 2, KHATA NO. 138, KHASRA NO. 2,3,4 ,MAUZA-SIKANADARPUR,THANA-SADAR,THANA NO.-243,ANCHAL--PURNEA, BIHAR-854326 | G90: 01-May-2023 | H90: 31-Mar-2024 | I90: 4477 | AI90: 261924 | AJ90: 261924 | AK90: 261924 | AL90: 261924 | AM90: 261924 | AN90: 261924 | AO90: 261924 | AP90: 261924 | AQ90: 261924 | AR90: 261924 | AS90: 261924 | BU90: =SUM(J90:U90) -> 0 | BV90: =SUM(V90:AG90) -> 0 | BW90: =SUM(AH90:AS90) -> 2881164 | BX90: =SUM(AT90:BE90) -> 0 | BY90: =SUM(BF90:BQ90) -> 0 | BZ90: =SUM(BR90:BT90) -> 0 | CA90: =BV90/BU90 -> #DIV/0!
A91: 6683 | B91: Bihar East | C91: Purnea | D91: PURNEA 2718 | E91: 1old | F91: SANGAM BHARTI WAREHOUSE(GODOWN-1)CHAMBER-1 & 2, KHATA NO. 138, KHASRA NO. 2,3,4 ,MAUZA-SIKANADARPUR,THANA-SADAR,THANA NO.-243,ANCHAL--PURNEA, BIHAR-854326 | G91: 01-May-2024 | H91: 31-Mar-2026 | I91: 4477 | AU91: 308936 | AV91: 308936 | AW91: 308936 | AX91: 308936 | AY91: 308936 | AZ91: 308936 | BA91: 308936 | BB91: 308936 | BC91: 308936 | BD91: 308936 | BE91: 308936 | BF91: 308936 | BG91: 308936 | BH91: 308936 | BI91: 308936 | BJ91: 308936 | BK91: 308936 | BL91: 308936 | BM91: 308936 | BN91: 308936 | BO91: 308936 | BP91: 308936 | BQ91: 308936 | BU91: =SUM(J91:U91) -> 0 | BV91: =SUM(V91:AG91) -> 0 | BW91: =SUM(AH91:AS91) -> 0 | BX91: =SUM(AT91:BE91) -> 3398296 | BY91: =SUM(BF91:BQ91) -> 3707232 | BZ91: =SUM(BR91:BT91) -> 0 | CA91: =BV91/BU91 -> #DIV/0!
A92: 6276 | B92: Bihar East | C92: Purnea | D92: PURNEA 2719 | E92: 1 old | F92: DILIP SAH WAREHOUSE(GODOWN-1), KHATA NO. 209, KHASRA NO. 876,VILLAGE-RAMELI CHAMP,TALUKA-HASDA,DIST-PURNEA, BIHAR-854326 | G92: 01-May-2023 | H92: 31-Mar-2024 | I92: 1108 | AI92: 64838 | AJ92: 64838 | AK92: 64838 | AL92: 64838 | AM92: 64838 | AN92: 64838 | AO92: 64838 | AP92: 64838 | AQ92: 64838 | AR92: 64838 | AS92: 64838 | BU92: =SUM(J92:U92) -> 0 | BV92: =SUM(V92:AG92) -> 0 | BW92: =SUM(AH92:AS92) -> 713218 | BX92: =SUM(AT92:BE92) -> 0 | BY92: =SUM(BF92:BQ92) -> 0 | BZ92: =SUM(BR92:BT92) -> 0 | CA92: =BV92/BU92 -> #DIV/0!
A93: 6685 | B93: Bihar East | C93: Purnea | D93: PURNEA 2719 | E93: 1old | F93: DILIP SAH WAREHOUSE , GODOWN NO 1, KHATA NO. 209, KHASRA NO. 876,VILLAGE-RAMELI CHAMP,TALUKA-HASDA,DIST-PURNEA, BIHAR-854326 | G93: 01-May-2024 | H93: 31-Mar-2026 | I93: 1108 | AU93: 76476 | AV93: 76476 | AW93: 76476 | AX93: 76476 | AY93: 76476 | AZ93: 76476 | BA93: 76476 | BB93: 76476 | BC93: 76476 | BD93: 76476 | BE93: 76476 | BF93: 76476 | BG93: 76476 | BH93: 76476 | BI93: 76476 | BJ93: 76476 | BK93: 76476 | BL93: 76476 | BM93: 76476 | BN93: 76476 | BO93: 76476 | BP93: 76476 | BQ93: 76476 | BU93: =SUM(J93:U93) -> 0 | BV93: =SUM(V93:AG93) -> 0 | BW93: =SUM(AH93:AS93) -> 0 | BX93: =SUM(AT93:BE93) -> 841236 | BY93: =SUM(BF93:BQ93) -> 917712 | BZ93: =SUM(BR93:BT93) -> 0 | CA93: =BV93/BU93 -> #DIV/0!
A94: 7411 | B94: Bihar East | C94: Purnea | D94: PURNEA 2720 | E94: 1 | F94: JAI PRAKASH YADAV WAREHOUSE(GODOWN-1), KHATA NO. 119,162, KHASRA NO.87,88,89 ,MAUZA-FATEHPUR,THANA-KASBA,ANCHAL-KASBA,DIST--PURNEA, BIHAR-854330 | G94: 01-May-2026 | I94: 2283 | BS94: 109600 | BT94: 109600 | BU94: =SUM(J94:U94) -> 0 | BV94: =SUM(V94:AG94) -> 0 | BW94: =SUM(AH94:AS94) -> 0 | BX94: =SUM(AT94:BE94) -> 0 | BY94: =SUM(BF94:BQ94) -> 0 | BZ94: =SUM(BR94:BT94) -> 219200 | CA94: =BV94/BU94 -> #DIV/0!
A95: 6274 | B95: Bihar East | C95: Purnea | D95: PURNEA 2720 | E95: 1 old | F95: JAI PRAKASH YADAV WAREHOUSE(GODOWN-1), KHATA NO. 119,162, KHASRA NO.87,88,89 ,MAUZA-FATEHPUR,THANA-KASBA,ANCHAL-KASBA,DIST--PURNEA, BIHAR-854330 | G95: 01-May-2023 | H95: 31-Mar-2024 | I95: 2283 | AI95: 140425 | AJ95: 140425 | AK95: 140425 | AL95: 140425 | AM95: 140425 | AN95: 140425 | AO95: 140425 | AP95: 140425 | AQ95: 140425 | AR95: 140425 | AS95: 140425 | BU95: =SUM(J95:U95) -> 0 | BV95: =SUM(V95:AG95) -> 0 | BW95: =SUM(AH95:AS95) -> 1544675 | BX95: =SUM(AT95:BE95) -> 0 | BY95: =SUM(BF95:BQ95) -> 0 | BZ95: =SUM(BR95:BT95) -> 0 | CA95: =BV95/BU95 -> #DIV/0!
A96: 6674 | B96: Bihar East | C96: Purnea | D96: PURNEA 2720 | E96: 1OLD | F96: JAI PRAKASH YADAV WH GODOWN NO 1, KHATA NO. 119,162, KHASRA NO.87,88,89 ,MAUZA-FATEHPUR,THANA-KASBA,ANCHAL-KASBA,DIST--PURNEA, BIHAR-854330 | G96: 01-May-2024 | H96: 31-Mar-2025 | I96: 2283 | AU96: 143850 | AV96: 143850 | AW96: 143850 | AX96: 143850 | AY96: 143850 | AZ96: 143850 | BA96: 143850 | BB96: 143850 | BC96: 143850 | BD96: 143850 | BE96: 143850 | BU96: =SUM(J96:U96) -> 0 | BV96: =SUM(V96:AG96) -> 0 | BW96: =SUM(AH96:AS96) -> 0 | BX96: =SUM(AT96:BE96) -> 1582350 | BY96: =SUM(BF96:BQ96) -> 0 | BZ96: =SUM(BR96:BT96) -> 0 | CA96: =BV96/BU96 -> #DIV/0!
A97: 7098 | B97: Bihar East | C97: Purnea | D97: PURNEA 2720 | E97: 1old. | F97: JAI PRAKASH YADAV WAREHOUSE(GODOWN-1), KHATA NO. 119,162, KHASRA NO.87,88,89 ,MAUZA-FATEHPUR,THANA-KASBA,ANCHAL-KASBA,DIST--PURNEA, BIHAR-854330 | G97: 01-May-2025 | H97: 31-Mar-2026 | I97: 2283 | BG97: 156180 | BH97: 156180 | BI97: 156180 | BJ97: 156180 | BK97: 156180 | BL97: 156180 | BM97: 156180 | BN97: 156180 | BO97: 156180 | BP97: 156180 | BQ97: 156180 | BU97: =SUM(J97:U97) -> 0 | BV97: =SUM(V97:AG97) -> 0 | BW97: =SUM(AH97:AS97) -> 0 | BX97: =SUM(AT97:BE97) -> 0 | BY97: =SUM(BF97:BQ97) -> 1717980 | BZ97: =SUM(BR97:BT97) -> 0 | CA97: =BV97/BU97 -> #DIV/0!
A98: 6273 | B98: Bihar East | C98: Purnea | D98: PURNEA 2721 | E98: 1 | F98: PUNAM WAREHOUSE(GODOWN-1),CHAMBER-1,2,3 , KHATA NO. 122, KHASRA NO. 1110, MAUZA:FATEHPUR,KASBA,DIST-PURNEA, BIHAR-854326 | G98: 01-May-2023 | I98: 5512 | AI98: 337354 | AJ98: 337354 | AK98: 337354 | AL98: 337354 | AM98: 337354 | AN98: 337354 | AO98: 337354 | AP98: 337354 | AQ98: 337354 | AR98: 337354 | AS98: 337354 | AT98: 337358 | AU98: 337354 | AV98: 337354 | AW98: 337354 | AX98: 337354 | AY98: 337354 | AZ98: 337354 | BA98: 337354 | BB98: 337354 | BC98: 337354 | BD98: 337354 | BE98: 337354 | BF98: 337354 | BG98: 337354 | BH98: 337354 | BI98: 337354 | BJ98: 337354 | BK98: 337354 | BL98: 337354 | BM98: 337354 | BN98: 337354 | BO98: 337354 | BP98: 337354 | BQ98: 337354 | BR98: 337354 | BS98: 281128 | BT98: 281128 | BU98: =SUM(J98:U98) -> 0 | BV98: =SUM(V98:AG98) -> 0 | BW98: =SUM(AH98:AS98) -> 3710894 | BX98: =SUM(AT98:BE98) -> 4048252 | BY98: =SUM(BF98:BQ98) -> 4048248 | BZ98: =SUM(BR98:BT98) -> 899610 | CA98: =BV98/BU98 -> #DIV/0!
A99: 6318 | B99: Bihar East | C99: Purnea | D99: PURNEA 2737 | E99: 1 | F99: SKYLARK FEEDS PVT LTD, CO SANJAY KUMAR GUPTA WAREHOUSE,GODOWN NO.1,KHATA NO.163,KHASRA NO.-951,991,953,AT: LALBALU/BARSONI ,PRAKHANDN-DAGARUA,GRAM PANCHAYAT-HARKHAILI,ANUMANDAL-BAISI,DIST : PURNEA,STATE:BIHAR-854326 | G99: 12-Apr-2023 | H99: 28-Feb-2025 | I99: 2500 | AH99: 59660 | AI99: 94200 | AJ99: 94200 | AK99: 94200 | AL99: 94200 | AM99: 94200 | AN99: 94200 | AO99: 94200 | AP99: 94200 | AQ99: 94200 | AR99: 94200 | AS99: 94200 | AT99: 94200 | AU99: 94200 | AV99: 94200 | AW99: 94200 | AX99: 94200 | AY99: 94200 | AZ99: 94200 | BA99: 94200 | BB99: 94200 | BC99: 94200 | BD99: 94200 | BU99: =SUM(J99:U99) -> 0 | BV99: =SUM(V99:AG99) -> 0 | BW99: =SUM(AH99:AS99) -> 1095860 | BX99: =SUM(AT99:BE99) -> 1036200 | BY99: =SUM(BF99:BQ99) -> 0 | BZ99: =SUM(BR99:BT99) -> 0 | CA99: =BV99/BU99 -> #DIV/0!
A100: 6315 | B100: Bihar East | C100: Purnea | D100: PURNEA 2737 | E100: 3 | F100: SKYLARK FEEDS PVT LTD, CO RANI DEVI WAREHOUSE,GODOWN NO.3,KHATA NO.163,KHESRA NO.-950,952,953,AT: LALBALU/BARSONI ,PRAKHANDN-DAGARUA,GRAM PANCHAYAT-HARKHAILI,ANUMANDAL-BAISI,DIST : PURNEA,STATE:BIHAR-854326 | G100: 12-Apr-2023 | I100: 2500 | AH100: 59751 | AI100: 94344 | AJ100: 94344 | AK100: 94344 | AL100: 94344 | AM100: 94344 | AN100: 94344 | AO100: 94344 | AP100: 94344 | AQ100: 94344 | AR100: 94344 | AS100: 94344 | AT100: 94344 | AU100: 94344 | AV100: 94344 | AW100: 94344 | AX100: 94344 | AY100: 94344 | AZ100: 94344 | BA100: 94344 | BB100: 94344 | BC100: 94344 | BD100: 94344 | BU100: =SUM(J100:U100) -> 0 | BV100: =SUM(V100:AG100) -> 0 | BW100: =SUM(AH100:AS100) -> 1097535 | BX100: =SUM(AT100:BE100) -> 1037784 | BY100: =SUM(BF100:BQ100) -> 0 | BZ100: =SUM(BR100:BT100) -> 0 | CA100: =BV100/BU100 -> #DIV/0!
...
